Workbook

Sheet DETAILS
H2: XEROX
A3: 1 | B3: PAN & AADHAR CARD & PHOTO | H3: YES
A4: 2 | B4: NAME AS PER PAN
A5: 3 | B5: TRADE NAME & NATURE OF BUSINES | C5: 1
B6: SHOP ACT LICENCE / SSI /MSME | C6: 2 | H6: YES
C7: 3
C8: 4
A9: 4 | B9: PRINCIPAL PLACE OF BUSINESS | H9: YES
A10: 5 | B10: ADDITIONAL PLACE OF BUSINESS /GODOWN | H10: YES
B11: owner +TAX RECEIPT | C11: 1
B12: RENT AGREEMENT + TAX RECEIPT | C12: 2 | H12: YES
B13: CONSENT LETTER + TAX RECEIPT | C13: 3 | H13: YES
B14: LEASE AGREEMENT + TAX RECEIPT | C14: 4 | H14: YES
A15: 6 | B15: NAME OF COMMODITY & HSN CODE | C15: 1
C16: 2
C17: 3
C18: 4
C19: 5
A20: 7 | B20: NATURE OF SERVICES & SAC CODE | C20: 1
C21: 2
C22: 3
C23: 4
C24: 5
A25: 6 | B25: DETAILS OF PROPRIETOR/PARTNE/DIRECTOR
B26: NAME AS PER PAN
B27: DESIGNATION
B28: MOBILE NUMBER
B29: LANDLINE NUMBER
B30: E-MAIL ADDRESS
A31: 7 | B31: NAME OF THE CONTACT PERSON / ACCOUNTANT
B32: NAME
B33: DESIGNATION
B34: MOBILE NUMBER
B35: E-MAIL ADDRESS
A36: 8 | B36: DETIALS OF BANK ACCOUNTS | D36: NAME OF THE BANK
B37: NAME OF THE BANK | D37: ADDRESS OF THE BRANCH | E37: SB/CA/CC | F37: A/C.NO | G37: IFSC
A38: 1
A39: 2
A40: 3
A41: 4
A42: 5
A43: 6
A44: 7
A45: 8
A46: 9 | B46: PROFESSIONAL TAX NUMBER IF ANY -RC | H46: YES
B47: PROFESSIONAL TAX NUMBER IF ANY -EC | H47: YES
A48: 10 | B48: IMPORT EXPORT CODE | H48: YES
A49: 12 | B49: ANY OTHER LICENCE HELD | H49: YES

Sheet I-T
B2: NAME = | C2: =Yearly!C2 -> 0 | J2: As per Books
B4: Total | J4: =SUM(J6:J13) -> 0 | K4: =SUM(K6:K13) -> 0 | L4: =SUM(L6:L13) -> 0 | M4: =SUM(M6:M13) -> 0 | N4: =SUM(N6:N13) -> 0 | O4: =SUM(O6:O13) -> 0 | P4: =SUM(P6:P13) -> 0 | Q4: =SUM(Q6:Q13) -> 0
B5: Difference | C5: GSTIN = | D5: =Yearly!D5 -> 0 | J5: =SUM(J17:J216)-J4 -> 0 | K5: =SUM(K17:K216)-K4 -> 0 | L5: =SUM(L17:L216)-L4 -> 0 | M5: =SUM(M17:M216)-M4 -> 0 | N5: =SUM(N17:N216)-N4 -> 0 | O5: =SUM(O17:O216)-O4 -> 0 | P5: =SUM(P17:P216)-P4 -> 0 | Q5: =SUM(Q17:Q216)-Q4 -> 0
B6: Sales | J6: =SUMIF($B$17:$Q$516, B6, $J$17:$J$516) -> 0 | K6: =SUMIF($B$17:$Q$516, B6, $K$17:$K$516) -> 0 | L6: =SUMIF($B$17:$Q$516, B6, $L$17:$L$516) -> 0 | M6: =SUMIF($B$17:$Q$516, B6, $M$17:$M$516) -> 0 | N6: =SUMIF($B$17:$Q$516, B6, $N$17:$N$516) -> 0 | O6: =SUMIF($B$17:$Q$516, B6, $O$17:$O$516) -> 0 | P6: =SUMIF($B$17:$Q$516, B6, $P$17:$P$516) -> 0 | Q6: =SUMIF($B$17:$Q$516, B6, $Q$17:$Q$516) -> 0
B7: Direct Incomes | J7: =SUMIF($B$17:$Q$516, B7, $J$17:$J$516) -> 0 | K7: =SUMIF($B$17:$Q$516, B7, $K$17:$K$516) -> 0 | L7: =SUMIF($B$17:$Q$516, B7, $L$17:$L$516) -> 0 | M7: =SUMIF($B$17:$Q$516, B7, $M$17:$M$516) -> 0 | N7: =SUMIF($B$17:$Q$516, B7, $N$17:$N$516) -> 0 | O7: =SUMIF($B$17:$Q$516, B7, $O$17:$O$516) -> 0 | P7: =SUMIF($B$17:$Q$516, B7, $P$17:$P$516) -> 0 | Q7: =SUMIF($B$17:$Q$516, B7, $Q$17:$Q$516) -> 0
B8: Indirect Incomes | C8: YEAR = | D8: =Yearly!D8 -> 2017-18 | J8: =SUMIF($B$17:$Q$516, B8, $J$17:$J$516) -> 0 | K8: =SUMIF($B$17:$Q$516, B8, $K$17:$K$516) -> 0 | L8: =SUMIF($B$17:$Q$516, B8, $L$17:$L$516) -> 0 | M8: =SUMIF($B$17:$Q$516, B8, $M$17:$M$516) -> 0 | N8: =SUMIF($B$17:$Q$516, B8, $N$17:$N$516) -> 0 | O8: =SUMIF($B$17:$Q$516, B8, $O$17:$O$516) -> 0 | P8: =SUMIF($B$17:$Q$516, B8, $P$17:$P$516) -> 0 | Q8: =SUMIF($B$17:$Q$516, B8, $Q$17:$Q$516) -> 0
B9: Purchases | J9: =SUMIF($B$17:$Q$516, B9, $J$17:$J$516) -> 0 | K9: =SUMIF($B$17:$Q$516, B9, $K$17:$K$516) -> 0 | L9: =SUMIF($B$17:$Q$516, B9, $L$17:$L$516) -> 0 | M9: =SUMIF($B$17:$Q$516, B9, $M$17:$M$516) -> 0 | N9: =SUMIF($B$17:$Q$516, B9, $N$17:$N$516) -> 0 | O9: =SUMIF($B$17:$Q$516, B9, $O$17:$O$516) -> 0 | P9: =SUMIF($B$17:$Q$516, B9, $P$17:$P$516) -> 0 | Q9: =SUMIF($B$17:$Q$516, B9, $Q$17:$Q$516) -> 0
B10: Direct Expenses | J10: =SUMIF($B$17:$Q$516, B10, $J$17:$J$516) -> 0 | K10: =SUMIF($B$17:$Q$516, B10, $K$17:$K$516) -> 0 | L10: =SUMIF($B$17:$Q$516, B10, $L$17:$L$516) -> 0 | M10: =SUMIF($B$17:$Q$516, B10, $M$17:$M$516) -> 0 | N10: =SUMIF($B$17:$Q$516, B10, $N$17:$N$516) -> 0 | O10: =SUMIF($B$17:$Q$516, B10, $O$17:$O$516) -> 0 | P10: =SUMIF($B$17:$Q$516, B10, $P$17:$P$516) -> 0 | Q10: =SUMIF($B$17:$Q$516, B10, $Q$17:$Q$516) -> 0
B11: Indirect Expenses | C11: MONTH = | D11: APRIL TO MARCH | J11: =SUMIF($B$17:$Q$516, B11, $J$17:$J$516) -> 0 | K11: =SUMIF($B$17:$Q$516, B11, $K$17:$K$516) -> 0 | L11: =SUMIF($B$17:$Q$516, B11, $L$17:$L$516) -> 0 | M11: =SUMIF($B$17:$Q$516, B11, $M$17:$M$516) -> 0 | N11: =SUMIF($B$17:$Q$516, B11, $N$17:$N$516) -> 0 | O11: =SUMIF($B$17:$Q$516, B11, $O$17:$O$516) -> 0 | P11: =SUMIF($B$17:$Q$516, B11, $P$17:$P$516) -> 0 | Q11: =SUMIF($B$17:$Q$516, B11, $Q$17:$Q$516) -> 0
B12: Capital Assets | J12: =SUMIF($B$17:$Q$516, B12, $J$17:$J$516) -> 0 | K12: =SUMIF($B$17:$Q$516, B12, $K$17:$K$516) -> 0 | L12: =SUMIF($B$17:$Q$516, B12, $L$17:$L$516) -> 0 | M12: =SUMIF($B$17:$Q$516, B12, $M$17:$M$516) -> 0 | N12: =SUMIF($B$17:$Q$516, B12, $N$17:$N$516) -> 0 | O12: =SUMIF($B$17:$Q$516, B12, $O$17:$O$516) -> 0 | P12: =SUMIF($B$17:$Q$516, B12, $P$17:$P$516) -> 0 | Q12: =SUMIF($B$17:$Q$516, B12, $Q$17:$Q$516) -> 0
B13: Others | J13: =SUMIF($B$17:$Q$516, B13, $J$17:$J$516) -> 0 | K13: =SUMIF($B$17:$Q$516, B13, $K$17:$K$516) -> 0 | L13: =SUMIF($B$17:$Q$516, B13, $L$17:$L$516) -> 0 | M13: =SUMIF($B$17:$Q$516, B13, $M$17:$M$516) -> 0 | N13: =SUMIF($B$17:$Q$516, B13, $N$17:$N$516) -> 0 | O13: =SUMIF($B$17:$Q$516, B13, $O$17:$O$516) -> 0 | P13: =SUMIF($B$17:$Q$516, B13, $P$17:$P$516) -> 0 | Q13: =SUMIF($B$17:$Q$516, B13, $Q$17:$Q$516) -> 0
A15: Sr. No. | B15: Nature of Transaction | C15: Head as per Financial Statements | D15: Type of Item | E15: Type of Dealer | F15: Document | G15: HSN | H15: Tax Rate | J15: Total Amount as per Profit & Loss | K15: Non GST liable | L15: in respect of entities registered under GST | P15: Relating to entities not registered under GST | Q15: Difference
L16: Relating to goods or services exempt from GST | M16: Relating to entities falling under composition scheme | N16: Relating to other registered entities | O16: Total payment to registered entities
A17: 1 | B17: =Yearly!B16 -> 0 | C17: =Yearly!C16 -> 0 | D17: =Yearly!D16 -> 0 | E17: =Yearly!E16 -> 0 | F17: =Yearly!F16 -> 0 | G17: =Yearly!G16 -> 0 | H17: =Yearly!H16 -> 0 | K17: =Apr!P16+May!P16+Jun!P16+Jul!P16+Aug!P16+Sep!P16+Oct!P16+Nov!P16+Dec!P16+Jan!P16+Feb!P16+Mar!P16 -> 0 | L17: =IF(H17="Exempt", (Apr!Q16+May!Q16+Jun!Q16+Jul!Q16+Aug!Q16+Sep!Q16+Oct!Q16+Nov!Q16+Dec!Q16+Jan!Q16+Feb!Q16+Mar!Q16)+(Apr!P16+May!P16+Jun!P16+Jul!P16+Aug!P16+Sep!P16+Oct!P16+Nov!P16+Dec!P16+Jan!P16+Feb!P16+Mar!P16),0) -> 0 | M17: =IF(E17="Composition", (Apr!Q16+May!Q16+Jun!Q16+Jul!Q16+Aug!Q16+Sep!Q16+Oct!Q16+Nov!Q16+Dec!Q16+Jan!Q16+Feb!Q16+Mar!Q16)+(Apr!P16+May!P16+Jun!P16+Jul!P16+Aug!P16+Sep!P16+Oct!P16+Nov!P16+Dec!P16+Jan!P16+Feb!P16+Mar!P16),0) -> 0 | N17: =IF(E17="Registered", (Apr!J16+May!J16+Jun!J16+Jul!J16+Aug!J16+Sep!J16+Oct!J16+Nov!J16+Dec!J16+Jan!J16+Feb!J16+Mar!J16),0) -> 0 | O17: =SUM(L17:N17) -> 0 | P17: =IF(E17="Un-registered", (Apr!J16+May!J16+Jun!J16+Jul!J16+Aug!J16+Sep!J16+Oct!J16+Nov!J16+Dec!J16+Jan!J16+Feb!J16+Mar!J16)+(Apr!P16+May!P16+Jun!P16+Jul!P16+Aug!P16+Sep!P16+Oct!P16+Nov!P16+Dec!P16+Jan!P16+Feb!P16+Mar!P16),0) -> 0 | Q17: =J17-K17-O17-P17 -> 0 | T17: Materials | U17: Registered | V17: 28
A18: =+A17+1 -> 2 | B18: =Yearly!B17 -> 0 | C18: =Yearly!C17 -> 0 | D18: =Yearly!D17 -> 0 | E18: =Yearly!E17 -> 0 | F18: =Yearly!F17 -> 0 | G18: =Yearly!G17 -> 0 | H18: =Yearly!H17 -> 0 | K18: =Apr!P17+May!P17+Jun!P17+Jul!P17+Aug!P17+Sep!P17+Oct!P17+Nov!P17+Dec!P17+Jan!P17+Feb!P17+Mar!P17 -> 0 | L18: =IF(H18="Exempt", (Apr!Q17+May!Q17+Jun!Q17+Jul!Q17+Aug!Q17+Sep!Q17+Oct!Q17+Nov!Q17+Dec!Q17+Jan!Q17+Feb!Q17+Mar!Q17)+(Apr!P17+May!P17+Jun!P17+Jul!P17+Aug!P17+Sep!P17+Oct!P17+Nov!P17+Dec!P17+Jan!P17+Feb!P17+Mar!P17),0) -> 0 | M18: =IF(E18="Composition", (Apr!Q17+May!Q17+Jun!Q17+Jul!Q17+Aug!Q17+Sep!Q17+Oct!Q17+Nov!Q17+Dec!Q17+Jan!Q17+Feb!Q17+Mar!Q17)+(Apr!P17+May!P17+Jun!P17+Jul!P17+Aug!P17+Sep!P17+Oct!P17+Nov!P17+Dec!P17+Jan!P17+Feb!P17+Mar!P17),0) -> 0 | N18: =IF(E18="Registered", (Apr!J17+May!J17+Jun!J17+Jul!J17+Aug!J17+Sep!J17+Oct!J17+Nov!J17+Dec!J17+Jan!J17+Feb!J17+Mar!J17),0) -> 0 | O18: =SUM(L18:N18) -> 0 | P18: =IF(E18="Un-registered", (Apr!J17+May!J17+Jun!J17+Jul!J17+Aug!J17+Sep!J17+Oct!J17+Nov!J17+Dec!J17+Jan!J17+Feb!J17+Mar!J17)+(Apr!P17+May!P17+Jun!P17+Jul!P17+Aug!P17+Sep!P17+Oct!P17+Nov!P17+Dec!P17+Jan!P17+Feb!P17+Mar!P17),0) -> 0 | Q18: =J18-K18-O18-P18 -> 0 | T18: Services | U18: Un-registered | V18: 18
A19: =+A18+1 -> 3 | B19: =Yearly!B18 -> 0 | C19: =Yearly!C18 -> 0 | D19: =Yearly!D18 -> 0 | E19: =Yearly!E18 -> 0 | F19: =Yearly!F18 -> 0 | G19: =Yearly!G18 -> 0 | H19: =Yearly!H18 -> 0 | K19: =Apr!P18+May!P18+Jun!P18+Jul!P18+Aug!P18+Sep!P18+Oct!P18+Nov!P18+Dec!P18+Jan!P18+Feb!P18+Mar!P18 -> 0 | L19: =IF(H19="Exempt", (Apr!Q18+May!Q18+Jun!Q18+Jul!Q18+Aug!Q18+Sep!Q18+Oct!Q18+Nov!Q18+Dec!Q18+Jan!Q18+Feb!Q18+Mar!Q18)+(Apr!P18+May!P18+Jun!P18+Jul!P18+Aug!P18+Sep!P18+Oct!P18+Nov!P18+Dec!P18+Jan!P18+Feb!P18+Mar!P18),0) -> 0 | M19: =IF(E19="Composition", (Apr!Q18+May!Q18+Jun!Q18+Jul!Q18+Aug!Q18+Sep!Q18+Oct!Q18+Nov!Q18+Dec!Q18+Jan!Q18+Feb!Q18+Mar!Q18)+(Apr!P18+May!P18+Jun!P18+Jul!P18+Aug!P18+Sep!P18+Oct!P18+Nov!P18+Dec!P18+Jan!P18+Feb!P18+Mar!P18),0) -> 0 | N19: =IF(E19="Registered", (Apr!J18+May!J18+Jun!J18+Jul!J18+Aug!J18+Sep!J18+Oct!J18+Nov!J18+Dec!J18+Jan!J18+Feb!J18+Mar!J18),0) -> 0 | O19: =SUM(L19:N19) -> 0 | P19: =IF(E19="Un-registered", (Apr!J18+May!J18+Jun!J18+Jul!J18+Aug!J18+Sep!J18+Oct!J18+Nov!J18+Dec!J18+Jan!J18+Feb!J18+Mar!J18)+(Apr!P18+May!P18+Jun!P18+Jul!P18+Aug!P18+Sep!P18+Oct!P18+Nov!P18+Dec!P18+Jan!P18+Feb!P18+Mar!P18),0) -> 0 | Q19: =J19-K19-O19-P19 -> 0 | T19: Capital Goods | U19: Composition | V19: 12
A20: =+A19+1 -> 4 | B20: =Yearly!B19 -> 0 | C20: =Yearly!C19 -> 0 | D20: =Yearly!D19 -> 0 | E20: =Yearly!E19 -> 0 | F20: =Yearly!F19 -> 0 | G20: =Yearly!G19 -> 0 | H20: =Yearly!H19 -> 0 | K20: =Apr!P19+May!P19+Jun!P19+Jul!P19+Aug!P19+Sep!P19+Oct!P19+Nov!P19+Dec!P19+Jan!P19+Feb!P19+Mar!P19 -> 0 | L20: =IF(H20="Exempt", (Apr!Q19+May!Q19+Jun!Q19+Jul!Q19+Aug!Q19+Sep!Q19+Oct!Q19+Nov!Q19+Dec!Q19+Jan!Q19+Feb!Q19+Mar!Q19)+(Apr!P19+May!P19+Jun!P19+Jul!P19+Aug!P19+Sep!P19+Oct!P19+Nov!P19+Dec!P19+Jan!P19+Feb!P19+Mar!P19),0) -> 0 | M20: =IF(E20="Composition", (Apr!Q19+May!Q19+Jun!Q19+Jul!Q19+Aug!Q19+Sep!Q19+Oct!Q19+Nov!Q19+Dec!Q19+Jan!Q19+Feb!Q19+Mar!Q19)+(Apr!P19+May!P19+Jun!P19+Jul!P19+Aug!P19+Sep!P19+Oct!P19+Nov!P19+Dec!P19+Jan!P19+Feb!P19+Mar!P19),0) -> 0 | N20: =IF(E20="Registered", (Apr!J19+May!J19+Jun!J19+Jul!J19+Aug!J19+Sep!J19+Oct!J19+Nov!J19+Dec!J19+Jan!J19+Feb!J19+Mar!J19),0) -> 0 | O20: =SUM(L20:N20) -> 0 | P20: =IF(E20="Un-registered", (Apr!J19+May!J19+Jun!J19+Jul!J19+Aug!J19+Sep!J19+Oct!J19+Nov!J19+Dec!J19+Jan!J19+Feb!J19+Mar!J19)+(Apr!P19+May!P19+Jun!P19+Jul!P19+Aug!P19+Sep!P19+Oct!P19+Nov!P19+Dec!P19+Jan!P19+Feb!P19+Mar!P19),0) -> 0 | Q20: =J20-K20-O20-P20 -> 0 | T20: RCM | U20: Others | V20: 5
A21: =+A20+1 -> 5 | B21: =Yearly!B20 -> 0 | C21: =Yearly!C20 -> 0 | D21: =Yearly!D20 -> 0 | E21: =Yearly!E20 -> 0 | F21: =Yearly!F20 -> 0 | G21: =Yearly!G20 -> 0 | H21: =Yearly!H20 -> 0 | K21: =Apr!P20+May!P20+Jun!P20+Jul!P20+Aug!P20+Sep!P20+Oct!P20+Nov!P20+Dec!P20+Jan!P20+Feb!P20+Mar!P20 -> 0 | L21: =IF(H21="Exempt", (Apr!Q20+May!Q20+Jun!Q20+Jul!Q20+Aug!Q20+Sep!Q20+Oct!Q20+Nov!Q20+Dec!Q20+Jan!Q20+Feb!Q20+Mar!Q20)+(Apr!P20+May!P20+Jun!P20+Jul!P20+Aug!P20+Sep!P20+Oct!P20+Nov!P20+Dec!P20+Jan!P20+Feb!P20+Mar!P20),0) -> 0 | M21: =IF(E21="Composition", (Apr!Q20+May!Q20+Jun!Q20+Jul!Q20+Aug!Q20+Sep!Q20+Oct!Q20+Nov!Q20+Dec!Q20+Jan!Q20+Feb!Q20+Mar!Q20)+(Apr!P20+May!P20+Jun!P20+Jul!P20+Aug!P20+Sep!P20+Oct!P20+Nov!P20+Dec!P20+Jan!P20+Feb!P20+Mar!P20),0) -> 0 | N21: =IF(E21="Registered", (Apr!J20+May!J20+Jun!J20+Jul!J20+Aug!J20+Sep!J20+Oct!J20+Nov!J20+Dec!J20+Jan!J20+Feb!J20+Mar!J20),0) -> 0 | O21: =SUM(L21:N21) -> 0 | P21: =IF(E21="Un-registered", (Apr!J20+May!J20+Jun!J20+Jul!J20+Aug!J20+Sep!J20+Oct!J20+Nov!J20+Dec!J20+Jan!J20+Feb!J20+Mar!J20)+(Apr!P20+May!P20+Jun!P20+Jul!P20+Aug!P20+Sep!P20+Oct!P20+Nov!P20+Dec!P20+Jan!P20+Feb!P20+Mar!P20),0) -> 0 | Q21: =J21-K21-O21-P21 -> 0 | T21: Others | V21: 3
A22: =+A21+1 -> 6 | B22: =Yearly!B21 -> 0 | C22: =Yearly!C21 -> 0 | D22: =Yearly!D21 -> 0 | E22: =Yearly!E21 -> 0 | F22: =Yearly!F21 -> 0 | G22: =Yearly!G21 -> 0 | H22: =Yearly!H21 -> 0 | K22: =Apr!P21+May!P21+Jun!P21+Jul!P21+Aug!P21+Sep!P21+Oct!P21+Nov!P21+Dec!P21+Jan!P21+Feb!P21+Mar!P21 -> 0 | L22: =IF(H22="Exempt", (Apr!Q21+May!Q21+Jun!Q21+Jul!Q21+Aug!Q21+Sep!Q21+Oct!Q21+Nov!Q21+Dec!Q21+Jan!Q21+Feb!Q21+Mar!Q21)+(Apr!P21+May!P21+Jun!P21+Jul!P21+Aug!P21+Sep!P21+Oct!P21+Nov!P21+Dec!P21+Jan!P21+Feb!P21+Mar!P21),0) -> 0 | M22: =IF(E22="Composition", (Apr!Q21+May!Q21+Jun!Q21+Jul!Q21+Aug!Q21+Sep!Q21+Oct!Q21+Nov!Q21+Dec!Q21+Jan!Q21+Feb!Q21+Mar!Q21)+(Apr!P21+May!P21+Jun!P21+Jul!P21+Aug!P21+Sep!P21+Oct!P21+Nov!P21+Dec!P21+Jan!P21+Feb!P21+Mar!P21),0) -> 0 | N22: =IF(E22="Registered", (Apr!J21+May!J21+Jun!J21+Jul!J21+Aug!J21+Sep!J21+Oct!J21+Nov!J21+Dec!J21+Jan!J21+Feb!J21+Mar!J21),0) -> 0 | O22: =SUM(L22:N22) -> 0 | P22: =IF(E22="Un-registered", (Apr!J21+May!J21+Jun!J21+Jul!J21+Aug!J21+Sep!J21+Oct!J21+Nov!J21+Dec!J21+Jan!J21+Feb!J21+Mar!J21)+(Apr!P21+May!P21+Jun!P21+Jul!P21+Aug!P21+Sep!P21+Oct!P21+Nov!P21+Dec!P21+Jan!P21+Feb!P21+Mar!P21),0) -> 0 | Q22: =J22-K22-O22-P22 -> 0 | V22: 0.25
A23: =+A22+1 -> 7 | B23: =Yearly!B22 -> 0 | C23: =Yearly!C22 -> 0 | D23: =Yearly!D22 -> 0 | E23: =Yearly!E22 -> 0 | F23: =Yearly!F22 -> 0 | G23: =Yearly!G22 -> 0 | H23: =Yearly!H22 -> 0 | K23: =Apr!P22+May!P22+Jun!P22+Jul!P22+Aug!P22+Sep!P22+Oct!P22+Nov!P22+Dec!P22+Jan!P22+Feb!P22+Mar!P22 -> 0 | L23: =IF(H23="Exempt", (Apr!Q22+May!Q22+Jun!Q22+Jul!Q22+Aug!Q22+Sep!Q22+Oct!Q22+Nov!Q22+Dec!Q22+Jan!Q22+Feb!Q22+Mar!Q22)+(Apr!P22+May!P22+Jun!P22+Jul!P22+Aug!P22+Sep!P22+Oct!P22+Nov!P22+Dec!P22+Jan!P22+Feb!P22+Mar!P22),0) -> 0 | M23: =IF(E23="Composition", (Apr!Q22+May!Q22+Jun!Q22+Jul!Q22+Aug!Q22+Sep!Q22+Oct!Q22+Nov!Q22+Dec!Q22+Jan!Q22+Feb!Q22+Mar!Q22)+(Apr!P22+May!P22+Jun!P22+Jul!P22+Aug!P22+Sep!P22+Oct!P22+Nov!P22+Dec!P22+Jan!P22+Feb!P22+Mar!P22),0) -> 0 | N23: =IF(E23="Registered", (Apr!J22+May!J22+Jun!J22+Jul!J22+Aug!J22+Sep!J22+Oct!J22+Nov!J22+Dec!J22+Jan!J22+Feb!J22+Mar!J22),0) -> 0 | O23: =SUM(L23:N23) -> 0 | P23: =IF(E23="Un-registered", (Apr!J22+May!J22+Jun!J22+Jul!J22+Aug!J22+Sep!J22+Oct!J22+Nov!J22+Dec!J22+Jan!J22+Feb!J22+Mar!J22)+(Apr!P22+May!P22+Jun!P22+Jul!P22+Aug!P22+Sep!P22+Oct!P22+Nov!P22+Dec!P22+Jan!P22+Feb!P22+Mar!P22),0) -> 0 | Q23: =J23-K23-O23-P23 -> 0 | V23: 0.1
A24: =+A23+1 -> 8 | B24: =Yearly!B23 -> 0 | C24: =Yearly!C23 -> 0 | D24: =Yearly!D23 -> 0 | E24: =Yearly!E23 -> 0 | F24: =Yearly!F23 -> 0 | G24: =Yearly!G23 -> 0 | H24: =Yearly!H23 -> 0 | K24: =Apr!P23+May!P23+Jun!P23+Jul!P23+Aug!P23+Sep!P23+Oct!P23+Nov!P23+Dec!P23+Jan!P23+Feb!P23+Mar!P23 -> 0 | L24: =IF(H24="Exempt", (Apr!Q23+May!Q23+Jun!Q23+Jul!Q23+Aug!Q23+Sep!Q23+Oct!Q23+Nov!Q23+Dec!Q23+Jan!Q23+Feb!Q23+Mar!Q23)+(Apr!P23+May!P23+Jun!P23+Jul!P23+Aug!P23+Sep!P23+Oct!P23+Nov!P23+Dec!P23+Jan!P23+Feb!P23+Mar!P23),0) -> 0 | M24: =IF(E24="Composition", (Apr!Q23+May!Q23+Jun!Q23+Jul!Q23+Aug!Q23+Sep!Q23+Oct!Q23+Nov!Q23+Dec!Q23+Jan!Q23+Feb!Q23+Mar!Q23)+(Apr!P23+May!P23+Jun!P23+Jul!P23+Aug!P23+Sep!P23+Oct!P23+Nov!P23+Dec!P23+Jan!P23+Feb!P23+Mar!P23),0) -> 0 | N24: =IF(E24="Registered", (Apr!J23+May!J23+Jun!J23+Jul!J23+Aug!J23+Sep!J23+Oct!J23+Nov!J23+Dec!J23+Jan!J23+Feb!J23+Mar!J23),0) -> 0 | O24: =SUM(L24:N24) -> 0 | P24: =IF(E24="Un-registered", (Apr!J23+May!J23+Jun!J23+Jul!J23+Aug!J23+Sep!J23+Oct!J23+Nov!J23+Dec!J23+Jan!J23+Feb!J23+Mar!J23)+(Apr!P23+May!P23+Jun!P23+Jul!P23+Aug!P23+Sep!P23+Oct!P23+Nov!P23+Dec!P23+Jan!P23+Feb!P23+Mar!P23),0) -> 0 | Q24: =J24-K24-O24-P24 -> 0 | V24: 0
A25: =+A24+1 -> 9 | B25: =Yearly!B24 -> 0 | C25: =Yearly!C24 -> 0 | D25: =Yearly!D24 -> 0 | E25: =Yearly!E24 -> 0 | F25: =Yearly!F24 -> 0 | G25: =Yearly!G24 -> 0 | H25: =Yearly!H24 -> 0 | K25: =Apr!P24+May!P24+Jun!P24+Jul!P24+Aug!P24+Sep!P24+Oct!P24+Nov!P24+Dec!P24+Jan!P24+Feb!P24+Mar!P24 -> 0 | L25: =IF(H25="Exempt", (Apr!Q24+May!Q24+Jun!Q24+Jul!Q24+Aug!Q24+Sep!Q24+Oct!Q24+Nov!Q24+Dec!Q24+Jan!Q24+Feb!Q24+Mar!Q24)+(Apr!P24+May!P24+Jun!P24+Jul!P24+Aug!P24+Sep!P24+Oct!P24+Nov!P24+Dec!P24+Jan!P24+Feb!P24+Mar!P24),0) -> 0 | M25: =IF(E25="Composition", (Apr!Q24+May!Q24+Jun!Q24+Jul!Q24+Aug!Q24+Sep!Q24+Oct!Q24+Nov!Q24+Dec!Q24+Jan!Q24+Feb!Q24+Mar!Q24)+(Apr!P24+May!P24+Jun!P24+Jul!P24+Aug!P24+Sep!P24+Oct!P24+Nov!P24+Dec!P24+Jan!P24+Feb!P24+Mar!P24),0) -> 0 | N25: =IF(E25="Registered", (Apr!J24+May!J24+Jun!J24+Jul!J24+Aug!J24+Sep!J24+Oct!J24+Nov!J24+Dec!J24+Jan!J24+Feb!J24+Mar!J24),0) -> 0 | O25: =SUM(L25:N25) -> 0 | P25: =IF(E25="Un-registered", (Apr!J24+May!J24+Jun!J24+Jul!J24+Aug!J24+Sep!J24+Oct!J24+Nov!J24+Dec!J24+Jan!J24+Feb!J24+Mar!J24)+(Apr!P24+May!P24+Jun!P24+Jul!P24+Aug!P24+Sep!P24+Oct!P24+Nov!P24+Dec!P24+Jan!P24+Feb!P24+Mar!P24),0) -> 0 | Q25: =J25-K25-O25-P25 -> 0
A26: =+A25+1 -> 10 | B26: =Yearly!B25 -> 0 | C26: =Yearly!C25 -> 0 | D26: =Yearly!D25 -> 0 | E26: =Yearly!E25 -> 0 | F26: =Yearly!F25 -> 0 | G26: =Yearly!G25 -> 0 | H26: =Yearly!H25 -> 0 | K26: =Apr!P25+May!P25+Jun!P25+Jul!P25+Aug!P25+Sep!P25+Oct!P25+Nov!P25+Dec!P25+Jan!P25+Feb!P25+Mar!P25 -> 0 | L26: =IF(H26="Exempt", (Apr!Q25+May!Q25+Jun!Q25+Jul!Q25+Aug!Q25+Sep!Q25+Oct!Q25+Nov!Q25+Dec!Q25+Jan!Q25+Feb!Q25+Mar!Q25)+(Apr!P25+May!P25+Jun!P25+Jul!P25+Aug!P25+Sep!P25+Oct!P25+Nov!P25+Dec!P25+Jan!P25+Feb!P25+Mar!P25),0) -> 0 | M26: =IF(E26="Composition", (Apr!Q25+May!Q25+Jun!Q25+Jul!Q25+Aug!Q25+Sep!Q25+Oct!Q25+Nov!Q25+Dec!Q25+Jan!Q25+Feb!Q25+Mar!Q25)+(Apr!P25+May!P25+Jun!P25+Jul!P25+Aug!P25+Sep!P25+Oct!P25+Nov!P25+Dec!P25+Jan!P25+Feb!P25+Mar!P25),0) -> 0 | N26: =IF(E26="Registered", (Apr!J25+May!J25+Jun!J25+Jul!J25+Aug!J25+Sep!J25+Oct!J25+Nov!J25+Dec!J25+Jan!J25+Feb!J25+Mar!J25),0) -> 0 | O26: =SUM(L26:N26) -> 0 | P26: =IF(E26="Un-registered", (Apr!J25+May!J25+Jun!J25+Jul!J25+Aug!J25+Sep!J25+Oct!J25+Nov!J25+Dec!J25+Jan!J25+Feb!J25+Mar!J25)+(Apr!P25+May!P25+Jun!P25+Jul!P25+Aug!P25+Sep!P25+Oct!P25+Nov!P25+Dec!P25+Jan!P25+Feb!P25+Mar!P25),0) -> 0 | Q26: =J26-K26-O26-P26 -> 0
A27: =+A26+1 -> 11 | B27: =Yearly!B26 -> 0 | C27: =Yearly!C26 -> 0 | D27: =Yearly!D26 -> 0 | E27: =Yearly!E26 -> 0 | F27: =Yearly!F26 -> 0 | G27: =Yearly!G26 -> 0 | H27: =Yearly!H26 -> 0 | K27: =Apr!P26+May!P26+Jun!P26+Jul!P26+Aug!P26+Sep!P26+Oct!P26+Nov!P26+Dec!P26+Jan!P26+Feb!P26+Mar!P26 -> 0 | L27: =IF(H27="Exempt", (Apr!Q26+May!Q26+Jun!Q26+Jul!Q26+Aug!Q26+Sep!Q26+Oct!Q26+Nov!Q26+Dec!Q26+Jan!Q26+Feb!Q26+Mar!Q26)+(Apr!P26+May!P26+Jun!P26+Jul!P26+Aug!P26+Sep!P26+Oct!P26+Nov!P26+Dec!P26+Jan!P26+Feb!P26+Mar!P26),0) -> 0 | M27: =IF(E27="Composition", (Apr!Q26+May!Q26+Jun!Q26+Jul!Q26+Aug!Q26+Sep!Q26+Oct!Q26+Nov!Q26+Dec!Q26+Jan!Q26+Feb!Q26+Mar!Q26)+(Apr!P26+May!P26+Jun!P26+Jul!P26+Aug!P26+Sep!P26+Oct!P26+Nov!P26+Dec!P26+Jan!P26+Feb!P26+Mar!P26),0) -> 0 | N27: =IF(E27="Registered", (Apr!J26+May!J26+Jun!J26+Jul!J26+Aug!J26+Sep!J26+Oct!J26+Nov!J26+Dec!J26+Jan!J26+Feb!J26+Mar!J26),0) -> 0 | O27: =SUM(L27:N27) -> 0 | P27: =IF(E27="Un-registered", (Apr!J26+May!J26+Jun!J26+Jul!J26+Aug!J26+Sep!J26+Oct!J26+Nov!J26+Dec!J26+Jan!J26+Feb!J26+Mar!J26)+(Apr!P26+May!P26+Jun!P26+Jul!P26+Aug!P26+Sep!P26+Oct!P26+Nov!P26+Dec!P26+Jan!P26+Feb!P26+Mar!P26),0) -> 0 | Q27: =J27-K27-O27-P27 -> 0
A28: =+A27+1 -> 12 | B28: =Yearly!B27 -> 0 | C28: =Yearly!C27 -> 0 | D28: =Yearly!D27 -> 0 | E28: =Yearly!E27 -> 0 | F28: =Yearly!F27 -> 0 | G28: =Yearly!G27 -> 0 | H28: =Yearly!H27 -> 0 | K28: =Apr!P27+May!P27+Jun!P27+Jul!P27+Aug!P27+Sep!P27+Oct!P27+Nov!P27+Dec!P27+Jan!P27+Feb!P27+Mar!P27 -> 0 | L28: =IF(H28="Exempt", (Apr!Q27+May!Q27+Jun!Q27+Jul!Q27+Aug!Q27+Sep!Q27+Oct!Q27+Nov!Q27+Dec!Q27+Jan!Q27+Feb!Q27+Mar!Q27)+(Apr!P27+May!P27+Jun!P27+Jul!P27+Aug!P27+Sep!P27+Oct!P27+Nov!P27+Dec!P27+Jan!P27+Feb!P27+Mar!P27),0) -> 0 | M28: =IF(E28="Composition", (Apr!Q27+May!Q27+Jun!Q27+Jul!Q27+Aug!Q27+Sep!Q27+Oct!Q27+Nov!Q27+Dec!Q27+Jan!Q27+Feb!Q27+Mar!Q27)+(Apr!P27+May!P27+Jun!P27+Jul!P27+Aug!P27+Sep!P27+Oct!P27+Nov!P27+Dec!P27+Jan!P27+Feb!P27+Mar!P27),0) -> 0 | N28: =IF(E28="Registered", (Apr!J27+May!J27+Jun!J27+Jul!J27+Aug!J27+Sep!J27+Oct!J27+Nov!J27+Dec!J27+Jan!J27+Feb!J27+Mar!J27),0) -> 0 | O28: =SUM(L28:N28) -> 0 | P28: =IF(E28="Un-registered", (Apr!J27+May!J27+Jun!J27+Jul!J27+Aug!J27+Sep!J27+Oct!J27+Nov!J27+Dec!J27+Jan!J27+Feb!J27+Mar!J27)+(Apr!P27+May!P27+Jun!P27+Jul!P27+Aug!P27+Sep!P27+Oct!P27+Nov!P27+Dec!P27+Jan!P27+Feb!P27+Mar!P27),0) -> 0 | Q28: =J28-K28-O28-P28 -> 0
A29: =+A28+1 -> 13 | B29: =Yearly!B28 -> 0 | C29: =Yearly!C28 -> 0 | D29: =Yearly!D28 -> 0 | E29: =Yearly!E28 -> 0 | F29: =Yearly!F28 -> 0 | G29: =Yearly!G28 -> 0 | H29: =Yearly!H28 -> 0 | K29: =Apr!P28+May!P28+Jun!P28+Jul!P28+Aug!P28+Sep!P28+Oct!P28+Nov!P28+Dec!P28+Jan!P28+Feb!P28+Mar!P28 -> 0 | L29: =IF(H29="Exempt", (Apr!Q28+May!Q28+Jun!Q28+Jul!Q28+Aug!Q28+Sep!Q28+Oct!Q28+Nov!Q28+Dec!Q28+Jan!Q28+Feb!Q28+Mar!Q28)+(Apr!P28+May!P28+Jun!P28+Jul!P28+Aug!P28+Sep!P28+Oct!P28+Nov!P28+Dec!P28+Jan!P28+Feb!P28+Mar!P28),0) -> 0 | M29: =IF(E29="Composition", (Apr!Q28+May!Q28+Jun!Q28+Jul!Q28+Aug!Q28+Sep!Q28+Oct!Q28+Nov!Q28+Dec!Q28+Jan!Q28+Feb!Q28+Mar!Q28)+(Apr!P28+May!P28+Jun!P28+Jul!P28+Aug!P28+Sep!P28+Oct!P28+Nov!P28+Dec!P28+Jan!P28+Feb!P28+Mar!P28),0) -> 0 | N29: =IF(E29="Registered", (Apr!J28+May!J28+Jun!J28+Jul!J28+Aug!J28+Sep!J28+Oct!J28+Nov!J28+Dec!J28+Jan!J28+Feb!J28+Mar!J28),0) -> 0 | O29: =SUM(L29:N29) -> 0 | P29: =IF(E29="Un-registered", (Apr!J28+May!J28+Jun!J28+Jul!J28+Aug!J28+Sep!J28+Oct!J28+Nov!J28+Dec!J28+Jan!J28+Feb!J28+Mar!J28)+(Apr!P28+May!P28+Jun!P28+Jul!P28+Aug!P28+Sep!P28+Oct!P28+Nov!P28+Dec!P28+Jan!P28+Feb!P28+Mar!P28),0) -> 0 | Q29: =J29-K29-O29-P29 -> 0
A30: =+A29+1 -> 14 | B30: =Yearly!B29 -> 0 | C30: =Yearly!C29 -> 0 | D30: =Yearly!D29 -> 0 | E30: =Yearly!E29 -> 0 | F30: =Yearly!F29 -> 0 | G30: =Yearly!G29 -> 0 | H30: =Yearly!H29 -> 0 | K30: =Apr!P29+May!P29+Jun!P29+Jul!P29+Aug!P29+Sep!P29+Oct!P29+Nov!P29+Dec!P29+Jan!P29+Feb!P29+Mar!P29 -> 0 | L30: =IF(H30="Exempt", (Apr!Q29+May!Q29+Jun!Q29+Jul!Q29+Aug!Q29+Sep!Q29+Oct!Q29+Nov!Q29+Dec!Q29+Jan!Q29+Feb!Q29+Mar!Q29)+(Apr!P29+May!P29+Jun!P29+Jul!P29+Aug!P29+Sep!P29+Oct!P29+Nov!P29+Dec!P29+Jan!P29+Feb!P29+Mar!P29),0) -> 0 | M30: =IF(E30="Composition", (Apr!Q29+May!Q29+Jun!Q29+Jul!Q29+Aug!Q29+Sep!Q29+Oct!Q29+Nov!Q29+Dec!Q29+Jan!Q29+Feb!Q29+Mar!Q29)+(Apr!P29+May!P29+Jun!P29+Jul!P29+Aug!P29+Sep!P29+Oct!P29+Nov!P29+Dec!P29+Jan!P29+Feb!P29+Mar!P29),0) -> 0 | N30: =IF(E30="Registered", (Apr!J29+May!J29+Jun!J29+Jul!J29+Aug!J29+Sep!J29+Oct!J29+Nov!J29+Dec!J29+Jan!J29+Feb!J29+Mar!J29),0) -> 0 | O30: =SUM(L30:N30) -> 0 | P30: =IF(E30="Un-registered", (Apr!J29+May!J29+Jun!J29+Jul!J29+Aug!J29+Sep!J29+Oct!J29+Nov!J29+Dec!J29+Jan!J29+Feb!J29+Mar!J29)+(Apr!P29+May!P29+Jun!P29+Jul!P29+Aug!P29+Sep!P29+Oct!P29+Nov!P29+Dec!P29+Jan!P29+Feb!P29+Mar!P29),0) -> 0 | Q30: =J30-K30-O30-P30 -> 0
A31: =+A30+1 -> 15 | B31: =Yearly!B30 -> 0 | C31: =Yearly!C30 -> 0 | D31: =Yearly!D30 -> 0 | E31: =Yearly!E30 -> 0 | F31: =Yearly!F30 -> 0 | G31: =Yearly!G30 -> 0 | H31: =Yearly!H30 -> 0 | K31: =Apr!P30+May!P30+Jun!P30+Jul!P30+Aug!P30+Sep!P30+Oct!P30+Nov!P30+Dec!P30+Jan!P30+Feb!P30+Mar!P30 -> 0 | L31: =IF(H31="Exempt", (Apr!Q30+May!Q30+Jun!Q30+Jul!Q30+Aug!Q30+Sep!Q30+Oct!Q30+Nov!Q30+Dec!Q30+Jan!Q30+Feb!Q30+Mar!Q30)+(Apr!P30+May!P30+Jun!P30+Jul!P30+Aug!P30+Sep!P30+Oct!P30+Nov!P30+Dec!P30+Jan!P30+Feb!P30+Mar!P30),0) -> 0 | M31: =IF(E31="Composition", (Apr!Q30+May!Q30+Jun!Q30+Jul!Q30+Aug!Q30+Sep!Q30+Oct!Q30+Nov!Q30+Dec!Q30+Jan!Q30+Feb!Q30+Mar!Q30)+(Apr!P30+May!P30+Jun!P30+Jul!P30+Aug!P30+Sep!P30+Oct!P30+Nov!P30+Dec!P30+Jan!P30+Feb!P30+Mar!P30),0) -> 0 | N31: =IF(E31="Registered", (Apr!J30+May!J30+Jun!J30+Jul!J30+Aug!J30+Sep!J30+Oct!J30+Nov!J30+Dec!J30+Jan!J30+Feb!J30+Mar!J30),0) -> 0 | O31: =SUM(L31:N31) -> 0 | P31: =IF(E31="Un-registered", (Apr!J30+May!J30+Jun!J30+Jul!J30+Aug!J30+Sep!J30+Oct!J30+Nov!J30+Dec!J30+Jan!J30+Feb!J30+Mar!J30)+(Apr!P30+May!P30+Jun!P30+Jul!P30+Aug!P30+Sep!P30+Oct!P30+Nov!P30+Dec!P30+Jan!P30+Feb!P30+Mar!P30),0) -> 0 | Q31: =J31-K31-O31-P31 -> 0
A32: =+A31+1 -> 16 | B32: =Yearly!B31 -> 0 | C32: =Yearly!C31 -> 0 | D32: =Yearly!D31 -> 0 | E32: =Yearly!E31 -> 0 | F32: =Yearly!F31 -> 0 | G32: =Yearly!G31 -> 0 | H32: =Yearly!H31 -> 0 | K32: =Apr!P31+May!P31+Jun!P31+Jul!P31+Aug!P31+Sep!P31+Oct!P31+Nov!P31+Dec!P31+Jan!P31+Feb!P31+Mar!P31 -> 0 | L32: =IF(H32="Exempt", (Apr!Q31+May!Q31+Jun!Q31+Jul!Q31+Aug!Q31+Sep!Q31+Oct!Q31+Nov!Q31+Dec!Q31+Jan!Q31+Feb!Q31+Mar!Q31)+(Apr!P31+May!P31+Jun!P31+Jul!P31+Aug!P31+Sep!P31+Oct!P31+Nov!P31+Dec!P31+Jan!P31+Feb!P31+Mar!P31),0) -> 0 | M32: =IF(E32="Composition", (Apr!Q31+May!Q31+Jun!Q31+Jul!Q31+Aug!Q31+Sep!Q31+Oct!Q31+Nov!Q31+Dec!Q31+Jan!Q31+Feb!Q31+Mar!Q31)+(Apr!P31+May!P31+Jun!P31+Jul!P31+Aug!P31+Sep!P31+Oct!P31+Nov!P31+Dec!P31+Jan!P31+Feb!P31+Mar!P31),0) -> 0 | N32: =IF(E32="Registered", (Apr!J31+May!J31+Jun!J31+Jul!J31+Aug!J31+Sep!J31+Oct!J31+Nov!J31+Dec!J31+Jan!J31+Feb!J31+Mar!J31),0) -> 0 | O32: =SUM(L32:N32) -> 0 | P32: =IF(E32="Un-registered", (Apr!J31+May!J31+Jun!J31+Jul!J31+Aug!J31+Sep!J31+Oct!J31+Nov!J31+Dec!J31+Jan!J31+Feb!J31+Mar!J31)+(Apr!P31+May!P31+Jun!P31+Jul!P31+Aug!P31+Sep!P31+Oct!P31+Nov!P31+Dec!P31+Jan!P31+Feb!P31+Mar!P31),0) -> 0 | Q32: =J32-K32-O32-P32 -> 0
A33: =+A32+1 -> 17 | B33: =Yearly!B32 -> 0 | C33: =Yearly!C32 -> 0 | D33: =Yearly!D32 -> 0 | E33: =Yearly!E32 -> 0 | F33: =Yearly!F32 -> 0 | G33: =Yearly!G32 -> 0 | H33: =Yearly!H32 -> 0 | K33: =Apr!P32+May!P32+Jun!P32+Jul!P32+Aug!P32+Sep!P32+Oct!P32+Nov!P32+Dec!P32+Jan!P32+Feb!P32+Mar!P32 -> 0 | L33: =IF(H33="Exempt", (Apr!Q32+May!Q32+Jun!Q32+Jul!Q32+Aug!Q32+Sep!Q32+Oct!Q32+Nov!Q32+Dec!Q32+Jan!Q32+Feb!Q32+Mar!Q32)+(Apr!P32+May!P32+Jun!P32+Jul!P32+Aug!P32+Sep!P32+Oct!P32+Nov!P32+Dec!P32+Jan!P32+Feb!P32+Mar!P32),0) -> 0 | M33: =IF(E33="Composition", (Apr!Q32+May!Q32+Jun!Q32+Jul!Q32+Aug!Q32+Sep!Q32+Oct!Q32+Nov!Q32+Dec!Q32+Jan!Q32+Feb!Q32+Mar!Q32)+(Apr!P32+May!P32+Jun!P32+Jul!P32+Aug!P32+Sep!P32+Oct!P32+Nov!P32+Dec!P32+Jan!P32+Feb!P32+Mar!P32),0) -> 0 | N33: =IF(E33="Registered", (Apr!J32+May!J32+Jun!J32+Jul!J32+Aug!J32+Sep!J32+Oct!J32+Nov!J32+Dec!J32+Jan!J32+Feb!J32+Mar!J32),0) -> 0 | O33: =SUM(L33:N33) -> 0 | P33: =IF(E33="Un-registered", (Apr!J32+May!J32+Jun!J32+Jul!J32+Aug!J32+Sep!J32+Oct!J32+Nov!J32+Dec!J32+Jan!J32+Feb!J32+Mar!J32)+(Apr!P32+May!P32+Jun!P32+Jul!P32+Aug!P32+Sep!P32+Oct!P32+Nov!P32+Dec!P32+Jan!P32+Feb!P32+Mar!P32),0) -> 0 | Q33: =J33-K33-O33-P33 -> 0
A34: =+A33+1 -> 18 | B34: =Yearly!B33 -> 0 | C34: =Yearly!C33 -> 0 | D34: =Yearly!D33 -> 0 | E34: =Yearly!E33 -> 0 | F34: =Yearly!F33 -> 0 | G34: =Yearly!G33 -> 0 | H34: =Yearly!H33 -> 0 | K34: =Apr!P33+May!P33+Jun!P33+Jul!P33+Aug!P33+Sep!P33+Oct!P33+Nov!P33+Dec!P33+Jan!P33+Feb!P33+Mar!P33 -> 0 | L34: =IF(H34="Exempt", (Apr!Q33+May!Q33+Jun!Q33+Jul!Q33+Aug!Q33+Sep!Q33+Oct!Q33+Nov!Q33+Dec!Q33+Jan!Q33+Feb!Q33+Mar!Q33)+(Apr!P33+May!P33+Jun!P33+Jul!P33+Aug!P33+Sep!P33+Oct!P33+Nov!P33+Dec!P33+Jan!P33+Feb!P33+Mar!P33),0) -> 0 | M34: =IF(E34="Composition", (Apr!Q33+May!Q33+Jun!Q33+Jul!Q33+Aug!Q33+Sep!Q33+Oct!Q33+Nov!Q33+Dec!Q33+Jan!Q33+Feb!Q33+Mar!Q33)+(Apr!P33+May!P33+Jun!P33+Jul!P33+Aug!P33+Sep!P33+Oct!P33+Nov!P33+Dec!P33+Jan!P33+Feb!P33+Mar!P33),0) -> 0 | N34: =IF(E34="Registered", (Apr!J33+May!J33+Jun!J33+Jul!J33+Aug!J33+Sep!J33+Oct!J33+Nov!J33+Dec!J33+Jan!J33+Feb!J33+Mar!J33),0) -> 0 | O34: =SUM(L34:N34) -> 0 | P34: =IF(E34="Un-registered", (Apr!J33+May!J33+Jun!J33+Jul!J33+Aug!J33+Sep!J33+Oct!J33+Nov!J33+Dec!J33+Jan!J33+Feb!J33+Mar!J33)+(Apr!P33+May!P33+Jun!P33+Jul!P33+Aug!P33+Sep!P33+Oct!P33+Nov!P33+Dec!P33+Jan!P33+Feb!P33+Mar!P33),0) -> 0 | Q34: =J34-K34-O34-P34 -> 0
A35: =+A34+1 -> 19 | B35: =Yearly!B34 -> 0 | C35: =Yearly!C34 -> 0 | D35: =Yearly!D34 -> 0 | E35: =Yearly!E34 -> 0 | F35: =Yearly!F34 -> 0 | G35: =Yearly!G34 -> 0 | H35: =Yearly!H34 -> 0 | K35: =Apr!P34+May!P34+Jun!P34+Jul!P34+Aug!P34+Sep!P34+Oct!P34+Nov!P34+Dec!P34+Jan!P34+Feb!P34+Mar!P34 -> 0 | L35: =IF(H35="Exempt", (Apr!Q34+May!Q34+Jun!Q34+Jul!Q34+Aug!Q34+Sep!Q34+Oct!Q34+Nov!Q34+Dec!Q34+Jan!Q34+Feb!Q34+Mar!Q34)+(Apr!P34+May!P34+Jun!P34+Jul!P34+Aug!P34+Sep!P34+Oct!P34+Nov!P34+Dec!P34+Jan!P34+Feb!P34+Mar!P34),0) -> 0 | M35: =IF(E35="Composition", (Apr!Q34+May!Q34+Jun!Q34+Jul!Q34+Aug!Q34+Sep!Q34+Oct!Q34+Nov!Q34+Dec!Q34+Jan!Q34+Feb!Q34+Mar!Q34)+(Apr!P34+May!P34+Jun!P34+Jul!P34+Aug!P34+Sep!P34+Oct!P34+Nov!P34+Dec!P34+Jan!P34+Feb!P34+Mar!P34),0) -> 0 | N35: =IF(E35="Registered", (Apr!J34+May!J34+Jun!J34+Jul!J34+Aug!J34+Sep!J34+Oct!J34+Nov!J34+Dec!J34+Jan!J34+Feb!J34+Mar!J34),0) -> 0 | O35: =SUM(L35:N35) -> 0 | P35: =IF(E35="Un-registered", (Apr!J34+May!J34+Jun!J34+Jul!J34+Aug!J34+Sep!J34+Oct!J34+Nov!J34+Dec!J34+Jan!J34+Feb!J34+Mar!J34)+(Apr!P34+May!P34+Jun!P34+Jul!P34+Aug!P34+Sep!P34+Oct!P34+Nov!P34+Dec!P34+Jan!P34+Feb!P34+Mar!P34),0) -> 0 | Q35: =J35-K35-O35-P35 -> 0
A36: =+A35+1 -> 20 | B36: =Yearly!B35 -> Sales | C36: =Yearly!C35 -> TRANSPORTER SALES | D36: =Yearly!D35 -> Services | E36: =Yearly!E35 -> Registered | F36: =Yearly!F35 -> RCM Invoice | G36: =Yearly!G35 -> 0 | H36: =Yearly!H35 -> 5 | K36: =Apr!P35+May!P35+Jun!P35+Jul!P35+Aug!P35+Sep!P35+Oct!P35+Nov!P35+Dec!P35+Jan!P35+Feb!P35+Mar!P35 -> 0 | L36: =IF(H36="Exempt", (Apr!Q35+May!Q35+Jun!Q35+Jul!Q35+Aug!Q35+Sep!Q35+Oct!Q35+Nov!Q35+Dec!Q35+Jan!Q35+Feb!Q35+Mar!Q35)+(Apr!P35+May!P35+Jun!P35+Jul!P35+Aug!P35+Sep!P35+Oct!P35+Nov!P35+Dec!P35+Jan!P35+Feb!P35+Mar!P35),0) -> 0 | M36: =IF(E36="Composition", (Apr!Q35+May!Q35+Jun!Q35+Jul!Q35+Aug!Q35+Sep!Q35+Oct!Q35+Nov!Q35+Dec!Q35+Jan!Q35+Feb!Q35+Mar!Q35)+(Apr!P35+May!P35+Jun!P35+Jul!P35+Aug!P35+Sep!P35+Oct!P35+Nov!P35+Dec!P35+Jan!P35+Feb!P35+Mar!P35),0) -> 0 | N36: =IF(E36="Registered", (Apr!J35+May!J35+Jun!J35+Jul!J35+Aug!J35+Sep!J35+Oct!J35+Nov!J35+Dec!J35+Jan!J35+Feb!J35+Mar!J35),0) -> 0 | O36: =SUM(L36:N36) -> 0 | P36: =IF(E36="Un-registered", (Apr!J35+May!J35+Jun!J35+Jul!J35+Aug!J35+Sep!J35+Oct!J35+Nov!J35+Dec!J35+Jan!J35+Feb!J35+Mar!J35)+(Apr!P35+May!P35+Jun!P35+Jul!P35+Aug!P35+Sep!P35+Oct!P35+Nov!P35+Dec!P35+Jan!P35+Feb!P35+Mar!P35),0) -> 0 | Q36: =J36-K36-O36-P36 -> 0
... A515: =+A514+1 -> 499 | B515: =Yearly!B514 -> 0 | C515: =Yearly!C514 -> 0 | D515: =Yearly!D514 -> 0 | E515: =Yearly!E514 -> 0 | F515: =Yearly!F514 -> 0 | G515: =Yearly!G514 -> 0 | H515: =Yearly!H514 -> 0 | K515: =Apr!P514+May!P514+Jun!P514+Jul!P514+Aug!P514+Sep!P514+Oct!P514+Nov!P514+Dec!P514+Jan!P514+Feb!P514+Mar!P514 -> 0 | L515: =IF(H515="Exempt", (Apr!Q514+May!Q514+Jun!Q514+Jul!Q514+Aug!Q514+Sep!Q514+Oct!Q514+Nov!Q514+Dec!Q514+Jan!Q514+Feb!Q514+Mar!Q514)+(Apr!P514+May!P514+Jun!P514+Jul!P514+Aug!P514+Sep!P514+Oct!P514+Nov!P514+Dec!P514+Jan!P514+Feb!P514+Mar!P514),0) -> 0 | M515: =IF(E515="Composition", (Apr!Q514+May!Q514+Jun!Q514+Jul!Q514+Aug!Q514+Sep!Q514+Oct!Q514+Nov!Q514+Dec!Q514+Jan!Q514+Feb!Q514+Mar!Q514)+(Apr!P514+May!P514+Jun!P514+Jul!P514+Aug!P514+Sep!P514+Oct!P514+Nov!P514+Dec!P514+Jan!P514+Feb!P514+Mar!P514),0) -> 0 | N515: =IF(E515="Registered", (Apr!J514+May!J514+Jun!J514+Jul!J514+Aug!J514+Sep!J514+Oct!J514+Nov!J514+Dec!J514+Jan!J514+Feb!J514+Mar!J514),0) -> 0 | O515: =SUM(L515:N515) -> 0 | P515: =IF(E515="Un-registered", (Apr!J514+May!J514+Jun!J514+Jul!J514+Aug!J514+Sep!J514+Oct!J514+Nov!J514+Dec!J514+Jan!J514+Feb!J514+Mar!J514)+(Apr!P514+May!P514+Jun!P514+Jul!P514+Aug!P514+Sep!P514+Oct!P514+Nov!P514+Dec!P514+Jan!P514+Feb!P514+Mar!P514),0) -> 0 | Q515: =J515-K515-O515-P515 -> 0
A516: =+A515+1 -> 500 | B516: =Yearly!B515 -> 0 | C516: =Yearly!C515 -> 0 | D516: =Yearly!D515 -> 0 | E516: =Yearly!E515 -> Composition | F516: =Yearly!F515 -> Composition | G516: =Yearly!G515 -> 0 | H516: =Yearly!H515 -> Exempt | J516: 110 | K516: =Apr!P515+May!P515+Jun!P515+Jul!P515+Aug!P515+Sep!P515+Oct!P515+Nov!P515+Dec!P515+Jan!P515+Feb!P515+Mar!P515 -> 0 | L516: =IF(H516="Exempt", (Apr!Q515+May!Q515+Jun!Q515+Jul!Q515+Aug!Q515+Sep!Q515+Oct!Q515+Nov!Q515+Dec!Q515+Jan!Q515+Feb!Q515+Mar!Q515)+(Apr!P515+May!P515+Jun!P515+Jul!P515+Aug!P515+Sep!P515+Oct!P515+Nov!P515+Dec!P515+Jan!P515+Feb!P515+Mar!P515),0) -> 1320 | M516: =IF(E516="Composition", (Apr!Q515+May!Q515+Jun!Q515+Jul!Q515+Aug!Q515+Sep!Q515+Oct!Q515+Nov!Q515+Dec!Q515+Jan!Q515+Feb!Q515+Mar!Q515)+(Apr!P515+May!P515+Jun!P515+Jul!P515+Aug!P515+Sep!P515+Oct!P515+Nov!P515+Dec!P515+Jan!P515+Feb!P515+Mar!P515),0) -> 1320 | N516: =IF(E516="Registered", (Apr!J515+May!J515+Jun!J515+Jul!J515+Aug!J515+Sep!J515+Oct!J515+Nov!J515+Dec!J515+Jan!J515+Feb!J515+Mar!J515),0) -> 0 | O516: =SUM(L516:N516) -> 2640 | P516: =IF(E516="Un-registered", (Apr!J515+May!J515+Jun!J515+Jul!J515+Aug!J515+Sep!J515+Oct!J515+Nov!J515+Dec!J515+Jan!J515+Feb!J515+Mar!J515)+(Apr!P515+May!P515+Jun!P515+Jul!P515+Aug!P515+Sep!P515+Oct!P515+Nov!P515+Dec!P515+Jan!P515+Feb!P515+Mar!P515),0) -> 0 | Q516: =J516-K516-O516-P516 -> -2530

Sheet Yearly
B2: NAME = | J2: As per Books | T2: As per GSTR 3B | AD2: As per GSTR 1 / 2A
B4: Total | J4: =SUM(J6:J13) -> 0 | K4: =SUM(K6:K13) -> 0 | L4: =SUM(L6:L13) -> 0 | M4: =SUM(M6:M13) -> 0 | N4: =SUM(N6:N13) -> 0 | O4: =SUM(O6:O13) -> 0 | P4: =SUM(P6:P13) -> 0 | Q4: =SUM(Q6:Q13) -> 0 | R4: =SUM(R6:R13) -> 0 | T4: =SUM(T6:T13) -> 0 | U4: =SUM(U6:U13) -> 0 | V4: =SUM(V6:V13) -> 0 | W4: =SUM(W6:W13) -> 0 | X4: =SUM(X6:X13) -> 0 | Y4: =SUM(Y6:Y13) -> 0 | Z4: =SUM(Z6:Z13) -> 0 | AA4: =SUM(AA6:AA13) -> 0 | AB4: =SUM(AB6:AB13) -> 0 | AD4: =SUM(AD6:AD13) -> 0 | AE4: =SUM(AE6:AE13) -> 0 | AF4: =SUM(AF6:AF13) -> 0 | AG4: =SUM(AG6:AG13) -> 0 | AH4: =SUM(AH6:AH13) -> 0 | AI4: =SUM(AI6:AI13) -> 0 | AJ4: =SUM(AJ6:AJ13) -> 0 | AK4: =SUM(AK6:AK13) -> 0 | AL4: =SUM(AL6:AL13) -> 0
B5: Difference | C5: GSTIN = | J5: =SUM(J16:J215)-J4 -> 0 | K5: =SUM(K16:K215)-K4 -> 0 | L5: =SUM(L16:L215)-L4 -> 0 | M5: =SUM(M16:M215)-M4 -> 0 | N5: =SUM(N16:N215)-N4 -> 0 | O5: =SUM(O16:O215)-O4 -> 0 | P5: =SUM(P16:P215)-P4 -> 0 | Q5: =SUM(Q16:Q215)-Q4 -> 0 | R5: =SUM(R16:R215)-R4 -> 0 | T5: =SUM(T16:T215)-T4 -> 0 | U5: =SUM(U16:U215)-U4 -> 0 | V5: =SUM(V16:V215)-V4 -> 0 | W5: =SUM(W16:W215)-W4 -> 0 | X5: =SUM(X16:X215)-X4 -> 0 | Y5: =SUM(Y16:Y215)-Y4 -> 0 | Z5: =SUM(Z16:Z215)-Z4 -> 0 | AA5: =SUM(AA16:AA215)-AA4 -> 0 | AB5: =SUM(AB16:AB215)-AB4 -> 0 | AD5: =SUM(AD16:AD215)-AD4 -> 0 | AE5: =SUM(AE16:AE215)-AE4 -> 0 | AF5: =SUM(AF16:AF215)-AF4 -> 0 | AG5: =SUM(AG16:AG215)-AG4 -> 0 | AH5: =SUM(AH16:AH215)-AH4 -> 0 | AI5: =SUM(AI16:AI215)-AI4 -> 0 | AJ5: =SUM(AJ16:AJ215)-AJ4 -> 0 | AK5: =SUM(AK16:AK215)-AK4 -> 0 | AL5: =SUM(AL16:AL215)-AL4 -> 0
B6: Sales | J6: =SUMIF($B$16:$R$515, B6, $J$16:$J$515) -> 0 | K6: =SUMIF($B$16:$R$515, B6, $K$16:$K$515) -> 0 | L6: =SUMIF($B$16:$R$515, B6, $L$16:$L$515) -> 0 | M6: =SUMIF($B$16:$R$515, B6, $M$16:$M$515) -> 0 | N6: =SUMIF($B$16:$R$515, B6, $N$16:$N$515) -> 0 | O6: =SUMIF($B$16:$R$515, B6, $O$16:$O$515) -> 0 | P6: =SUMIF($B$16:$R$515, B6, $P$16:$P$515) -> 0 | Q6: =SUMIF($B$16:$R$515, B6, $Q$16:$Q$515) -> 0 | R6: =SUMIF($B$16:$R$515, B6, $R$16:$R$515) -> 0 | T6: =SUMIF($B$16:$AB$515, $B$6, T16:T515) -> 0 | U6: =SUMIF($B$16:$AB$515, $B$6, U16:U515) -> 0 | V6: =SUMIF($B$16:$AB$515, $B$6, V16:V515) -> 0 | W6: =SUMIF($B$16:$AB$515, $B$6, W16:W515) -> 0 | X6: =SUMIF($B$16:$AB$515, $B$6, X16:X515) -> 0 | Y6: =SUMIF($B$16:$AB$515, $B$6, Y16:Y515) -> 0 | Z6: =SUMIF($B$16:$AB$515, $B$6, Z16:Z515) -> 0 | AA6: =SUMIF($B$16:$AB$515, $B$6, AA16:AA515) -> 0 | AB6: =SUMIF($B$16:$AB$515, $B$6, AB16:AB515) -> 0 | AD6: =SUMIF($B$16:$AL$515, $B$6, AD16:AD515) -> 0 | AE6: =SUMIF($B$16:$AL$515, $B$6, AE16:AE515) -> 0 | AF6: =SUMIF($B$16:$AL$515, $B$6, AF16:AF515) -> 0 | AG6: =SUMIF($B$16:$AL$515, $B$6, AG16:AG515) -> 0 | AH6: =SUMIF($B$16:$AL$515, $B$6, AH16:AH515) -> 0 | AI6: =SUMIF($B$16:$AL$515, $B$6, AI16:AI515) -> 0 | AJ6: =SUMIF($B$16:$AL$515, $B$6, AJ16:AJ515) -> 0 | AK6: =SUMIF($B$16:$AL$515, $B$6, AK16:AK515) -> 0 | AL6: =SUMIF($B$16:$AL$515, $B$6, AL16:AL515) -> 0
B7: Direct Incomes | J7: =SUMIF($B$16:$R$515, B7, $J$16:$J$515) -> 0 | K7: =SUMIF($B$16:$R$515, B7, $K$16:$K$515) -> 0 | L7: =SUMIF($B$16:$R$515, B7, $L$16:$L$515) -> 0 | M7: =SUMIF($B$16:$R$515, B7, $M$16:$M$515) -> 0 | N7: =SUMIF($B$16:$R$515, B7, $N$16:$N$515) -> 0 | O7: =SUMIF($B$16:$R$515, B7, $O$16:$O$515) -> 0 | P7: =SUMIF($B$16:$R$515, B7, $P$16:$P$515) -> 0 | Q7: =SUMIF($B$16:$R$515, B7, $Q$16:$Q$515) -> 0 | R7: =SUMIF($B$16:$R$515, B7, $R$16:$R$515) -> 0 | T7: =SUMIF($B$16:$AB$515, $B$7, T16:T515) -> 0 | U7: =SUMIF($B$16:$AB$515, $B$7, U16:U515) -> 0 | V7: =SUMIF($B$16:$AB$515, $B$7, V16:V515) -> 0 | W7: =SUMIF($B$16:$AB$515, $B$7, W16:W515) -> 0 | X7: =SUMIF($B$16:$AB$515, $B$7, X16:X515) -> 0 | Y7: =SUMIF($B$16:$AB$515, $B$7, Y16:Y515) -> 0 | Z7: =SUMIF($B$16:$AB$515, $B$7, Z16:Z515) -> 0 | AA7: =SUMIF($B$16:$AB$515, $B$7, AA16:AA515) -> 0 | AB7: =SUMIF($B$16:$AB$515, $B$7, AB16:AB515) -> 0 | AD7: =SUMIF($B$16:$AL$515, $B$7, AD16:AD515) -> 0 | AE7: =SUMIF($B$16:$AL$515, $B$7, AE16:AE515) -> 0 | AF7: =SUMIF($B$16:$AL$515, $B$7, AF16:AF515) -> 0 | AG7: =SUMIF($B$16:$AL$515, $B$7, AG16:AG515) -> 0 | AH7: =SUMIF($B$16:$AL$515, $B$7, AH16:AH515) -> 0 | AI7: =SUMIF($B$16:$AL$515, $B$7, AI16:AI515) -> 0 | AJ7: =SUMIF($B$16:$AL$515, $B$7, AJ16:AJ515) -> 0 | AK7: =SUMIF($B$16:$AL$515, $B$7, AK16:AK515) -> 0 | AL7: =SUMIF($B$16:$AL$515, $B$7, AL16:AL515) -> 0
B8: Indirect Incomes | C8: YEAR = | D8: 2017-18 | J8: =SUMIF($B$16:$R$515, B8, $J$16:$J$515) -> 0 | K8: =SUMIF($B$16:$R$515, B8, $K$16:$K$515) -> 0 | L8: =SUMIF($B$16:$R$515, B8, $L$16:$L$515) -> 0 | M8: =SUMIF($B$16:$R$515, B8, $M$16:$M$515) -> 0 | N8: =SUMIF($B$16:$R$515, B8, $N$16:$N$515) -> 0 | O8: =SUMIF($B$16:$R$515, B8, $O$16:$O$515) -> 0 | P8: =SUMIF($B$16:$R$515, B8, $P$16:$P$515) -> 0 | Q8: =SUMIF($B$16:$R$515, B8, $Q$16:$Q$515) -> 0 | R8: =SUMIF($B$16:$R$515, B8, $R$16:$R$515) -> 0 | T8: =SUMIF($B$16:$AB$515, $B$8, T16:T515) -> 0 | U8: =SUMIF($B$16:$AB$515, $B$8, U16:U515) -> 0 | V8: =SUMIF($B$16:$AB$515, $B$8, V16:V515) -> 0 | W8: =SUMIF($B$16:$AB$515, $B$8, W16:W515) -> 0 | X8: =SUMIF($B$16:$AB$515, $B$8, X16:X515) -> 0 | Y8: =SUMIF($B$16:$AB$515, $B$8, Y16:Y515) -> 0 | Z8: =SUMIF($B$16:$AB$515, $B$8, Z16:Z515) -> 0 | AA8: =SUMIF($B$16:$AB$515, $B$8, AA16:AA515) -> 0 | AB8: =SUMIF($B$16:$AB$515, $B$8, AB16:AB515) -> 0 | AD8: =SUMIF($B$16:$AL$515, $B$8, AD16:AD515) -> 0 | AE8: =SUMIF($B$16:$AL$515, $B$8, AE16:AE515) -> 0 | AF8: =SUMIF($B$16:$AL$515, $B$8, AF16:AF515) -> 0 | AG8: =SUMIF($B$16:$AL$515, $B$8, AG16:AG515) -> 0 | AH8: =SUMIF($B$16:$AL$515, $B$8, AH16:AH515) -> 0 | AI8: =SUMIF($B$16:$AL$515, $B$8, AI16:AI515) -> 0 | AJ8: =SUMIF($B$16:$AL$515, $B$8, AJ16:AJ515) -> 0 | AK8: =SUMIF($B$16:$AL$515, $B$8, AK16:AK515) -> 0 | AL8: =SUMIF($B$16:$AL$515, $B$8, AL16:AL515) -> 0
B9: Purchases | J9: =SUMIF($B$16:$R$515, B9, $J$16:$J$515) -> 0 | K9: =SUMIF($B$16:$R$515, B9, $K$16:$K$515) -> 0 | L9: =SUMIF($B$16:$R$515, B9, $L$16:$L$515) -> 0 | M9: =SUMIF($B$16:$R$515, B9, $M$16:$M$515) -> 0 | N9: =SUMIF($B$16:$R$515, B9, $N$16:$N$515) -> 0 | O9: =SUMIF($B$16:$R$515, B9, $O$16:$O$515) -> 0 | P9: =SUMIF($B$16:$R$515, B9, $P$16:$P$515) -> 0 | Q9: =SUMIF($B$16:$R$515, B9, $Q$16:$Q$515) -> 0 | R9: =SUMIF($B$16:$R$515, B9, $R$16:$R$515) -> 0 | T9: =SUMIF($B$16:$AB$515, $B$9, T16:T515) -> 0 | U9: =SUMIF($B$16:$AB$515, $B$9, U16:U515) -> 0 | V9: =SUMIF($B$16:$AB$515, $B$9, V16:V515) -> 0 | W9: =SUMIF($B$16:$AB$515, $B$9, W16:W515) -> 0 | X9: =SUMIF($B$16:$AB$515, $B$9, X16:X515) -> 0 | Y9: =SUMIF($B$16:$AB$515, $B$9, Y16:Y515) -> 0 | Z9: =SUMIF($B$16:$AB$515, $B$9, Z16:Z515) -> 0 | AA9: =SUMIF($B$16:$AB$515, $B$9, AA16:AA515) -> 0 | AB9: =SUMIF($B$16:$AB$515, $B$9, AB16:AB515) -> 0 | AD9: =SUMIF($B$16:$AL$515, $B$9, AD16:AD515) -> 0 | AE9: =SUMIF($B$16:$AL$515, $B$9, AE16:AE515) -> 0 | AF9: =SUMIF($B$16:$AL$515, $B$9, AF16:AF515) -> 0 | AG9: =SUMIF($B$16:$AL$515, $B$9, AG16:AG515) -> 0 | AH9: =SUMIF($B$16:$AL$515, $B$9, AH16:AH515) -> 0 | AI9: =SUMIF($B$16:$AL$515, $B$9, AI16:AI515) -> 0 | AJ9: =SUMIF($B$16:$AL$515, $B$9, AJ16:AJ515) -> 0 | AK9: =SUMIF($B$16:$AL$515, $B$9, AK16:AK515) -> 0 | AL9: =SUMIF($B$16:$AL$515, $B$9, AL16:AL515) -> 0
B10: Direct Expenses | J10: =SUMIF($B$16:$R$515, B10, $J$16:$J$515) -> 0 | K10: =SUMIF($B$16:$R$515, B10, $K$16:$K$515) -> 0 | L10: =SUMIF($B$16:$R$515, B10, $L$16:$L$515) -> 0 | M10: =SUMIF($B$16:$R$515, B10, $M$16:$M$515) -> 0 | N10: =SUMIF($B$16:$R$515, B10, $N$16:$N$515) -> 0 | O10: =SUMIF($B$16:$R$515, B10, $O$16:$O$515) -> 0 | P10: =SUMIF($B$16:$R$515, B10, $P$16:$P$515) -> 0 | Q10: =SUMIF($B$16:$R$515, B10, $Q$16:$Q$515) -> 0 | R10: =SUMIF($B$16:$R$515, B10, $R$16:$R$515) -> 0 | T10: =SUMIF($B$16:$AB$515, $B$10, T16:T515) -> 0 | U10: =SUMIF($B$16:$AB$515, $B$10, U16:U515) -> 0 | V10: =SUMIF($B$16:$AB$515, $B$10, V16:V515) -> 0 | W10: =SUMIF($B$16:$AB$515, $B$10, W16:W515) -> 0 | X10: =SUMIF($B$16:$AB$515, $B$10, X16:X515) -> 0 | Y10: =SUMIF($B$16:$AB$515, $B$10, Y16:Y515) -> 0 | Z10: =SUMIF($B$16:$AB$515, $B$10, Z16:Z515) -> 0 | AA10: =SUMIF($B$16:$AB$515, $B$10, AA16:AA515) -> 0 | AB10: =SUMIF($B$16:$AB$515, $B$10, AB16:AB515) -> 0 | AD10: =SUMIF($B$16:$AL$515, $B$10, AD16:AD515) -> 0 | AE10: =SUMIF($B$16:$AL$515, $B$10, AE16:AE515) -> 0 | AF10: =SUMIF($B$16:$AL$515, $B$10, AF16:AF515) -> 0 | AG10: =SUMIF($B$16:$AL$515, $B$10, AG16:AG515) -> 0 | AH10: =SUMIF($B$16:$AL$515, $B$10, AH16:AH515) -> 0 | AI10: =SUMIF($B$16:$AL$515, $B$10, AI16:AI515) -> 0 | AJ10: =SUMIF($B$16:$AL$515, $B$10, AJ16:AJ515) -> 0 | AK10: =SUMIF($B$16:$AL$515, $B$10, AK16:AK515) -> 0 | AL10: =SUMIF($B$16:$AL$515, $B$10, AL16:AL515) -> 0
B11: Indirect Expenses | C11: MONTH = | D11: APRIL TO MARCH | J11: =SUMIF($B$16:$R$515, B11, $J$16:$J$515) -> 0 | K11: =SUMIF($B$16:$R$515, B11, $K$16:$K$515) -> 0 | L11: =SUMIF($B$16:$R$515, B11, $L$16:$L$515) -> 0 | M11: =SUMIF($B$16:$R$515, B11, $M$16:$M$515) -> 0 | N11: =SUMIF($B$16:$R$515, B11, $N$16:$N$515) -> 0 | O11: =SUMIF($B$16:$R$515, B11, $O$16:$O$515) -> 0 | P11: =SUMIF($B$16:$R$515, B11, $P$16:$P$515) -> 0 | Q11: =SUMIF($B$16:$R$515, B11, $Q$16:$Q$515) -> 0 | R11: =SUMIF($B$16:$R$515, B11, $R$16:$R$515) -> 0 | T11: =SUMIF($B$16:$AB$515, $B$11, T16:T515) -> 0 | U11: =SUMIF($B$16:$AB$515, $B$11, U16:U515) -> 0 | V11: =SUMIF($B$16:$AB$515, $B$11, V16:V515) -> 0 | W11: =SUMIF($B$16:$AB$515, $B$11, W16:W515) -> 0 | X11: =SUMIF($B$16:$AB$515, $B$11, X16:X515) -> 0 | Y11: =SUMIF($B$16:$AB$515, $B$11, Y16:Y515) -> 0 | Z11: =SUMIF($B$16:$AB$515, $B$11, Z16:Z515) -> 0 | AA11: =SUMIF($B$16:$AB$515, $B$11, AA16:AA515) -> 0 | AB11: =SUMIF($B$16:$AB$515, $B$11, AB16:AB515) -> 0 | AD11: =SUMIF($B$16:$AL$515, $B$11, AD16:AD515) -> 0 | AE11: =SUMIF($B$16:$AL$515, $B$11, AE16:AE515) -> 0 | AF11: =SUMIF($B$16:$AL$515, $B$11, AF16:AF515) -> 0 | AG11: =SUMIF($B$16:$AL$515, $B$11, AG16:AG515) -> 0 | AH11: =SUMIF($B$16:$AL$515, $B$11, AH16:AH515) -> 0 | AI11: =SUMIF($B$16:$AL$515, $B$11, AI16:AI515) -> 0 | AJ11: =SUMIF($B$16:$AL$515, $B$11, AJ16:AJ515) -> 0 | AK11: =SUMIF($B$16:$AL$515, $B$11, AK16:AK515) -> 0 | AL11: =SUMIF($B$16:$AL$515, $B$11, AL16:AL515) -> 0
B12: Capital Assets | J12: =SUMIF($B$16:$R$515, B12, $J$16:$J$515) -> 0 | K12: =SUMIF($B$16:$R$515, B12, $K$16:$K$515) -> 0 | L12: =SUMIF($B$16:$R$515, B12, $L$16:$L$515) -> 0 | M12: =SUMIF($B$16:$R$515, B12, $M$16:$M$515) -> 0 | N12: =SUMIF($B$16:$R$515, B12, $N$16:$N$515) -> 0 | O12: =SUMIF($B$16:$R$515, B12, $O$16:$O$515) -> 0 | P12: =SUMIF($B$16:$R$515, B12, $P$16:$P$515) -> 0 | Q12: =SUMIF($B$16:$R$515, B12, $Q$16:$Q$515) -> 0 | R12: =SUMIF($B$16:$R$515, B12, $R$16:$R$515) -> 0 | T12: =SUMIF($B$16:$AB$515, $B$12, T16:T515) -> 0 | U12: =SUMIF($B$16:$AB$515, $B$12, U16:U515) -> 0 | V12: =SUMIF($B$16:$AB$515, $B$12, V16:V515) -> 0 | W12: =SUMIF($B$16:$AB$515, $B$12, W16:W515) -> 0 | X12: =SUMIF($B$16:$AB$515, $B$12, X16:X515) -> 0 | Y12: =SUMIF($B$16:$AB$515, $B$12, Y16:Y515) -> 0 | Z12: =SUMIF($B$16:$AB$515, $B$12, Z16:Z515) -> 0 | AA12: =SUMIF($B$16:$AB$515, $B$12, AA16:AA515) -> 0 | AB12: =SUMIF($B$16:$AB$515, $B$12, AB16:AB515) -> 0 | AD12: =SUMIF($B$16:$AL$515, $B$12, AD16:AD515) -> 0 | AE12: =SUMIF($B$16:$AL$515, $B$12, AE16:AE515) -> 0 | AF12: =SUMIF($B$16:$AL$515, $B$12, AF16:AF515) -> 0 | AG12: =SUMIF($B$16:$AL$515, $B$12, AG16:AG515) -> 0 | AH12: =SUMIF($B$16:$AL$515, $B$12, AH16:AH515) -> 0 | AI12: =SUMIF($B$16:$AL$515, $B$12, AI16:AI515) -> 0 | AJ12: =SUMIF($B$16:$AL$515, $B$12, AJ16:AJ515) -> 0 | AK12: =SUMIF($B$16:$AL$515, $B$12, AK16:AK515) -> 0 | AL12: =SUMIF($B$16:$AL$515, $B$12, AL16:AL515) -> 0
B13: Others | J13: =SUMIF($B$16:$R$515, B13, $J$16:$J$515) -> 0 | K13: =SUMIF($B$16:$R$515, B13, $K$16:$K$515) -> 0 | L13: =SUMIF($B$16:$R$515, B13, $L$16:$L$515) -> 0 | M13: =SUMIF($B$16:$R$515, B13, $M$16:$M$515) -> 0 | N13: =SUMIF($B$16:$R$515, B13, $N$16:$N$515) -> 0 | O13: =SUMIF($B$16:$R$515, B13, $O$16:$O$515) -> 0 | P13: =SUMIF($B$16:$R$515, B13, $P$16:$P$515) -> 0 | Q13: =SUMIF($B$16:$R$515, B13, $Q$16:$Q$515) -> 0 | R13: =SUMIF($B$16:$R$515, B13, $R$16:$R$515) -> 0 | T13: =SUMIF($B$16:$AB$515, $B$13, T16:T515) -> 0 | U13: =SUMIF($B$16:$AB$515, $B$13, U16:U515) -> 0 | V13: =SUMIF($B$16:$AB$515, $B$13, V16:V515) -> 0 | W13: =SUMIF($B$16:$AB$515, $B$13, W16:W515) -> 0 | X13: =SUMIF($B$16:$AB$515, $B$13, X16:X515) -> 0 | Y13: =SUMIF($B$16:$AB$515, $B$13, Y16:Y515) -> 0 | Z13: =SUMIF($B$16:$AB$515, $B$13, Z16:Z515) -> 0 | AA13: =SUMIF($B$16:$AB$515, $B$13, AA16:AA515) -> 0 | AB13: =SUMIF($B$16:$AB$515, $B$13, AB16:AB515) -> 0 | AD13: =SUMIF($B$16:$AL$515, $B$13, AD16:AD515) -> 0 | AE13: =SUMIF($B$16:$AL$515, $B$13, AE16:AE515) -> 0 | AF13: =SUMIF($B$16:$AL$515, $B$13, AF16:AF515) -> 0 | AG13: =SUMIF($B$16:$AL$515, $B$13, AG16:AG515) -> 0 | AH13: =SUMIF($B$16:$AL$515, $B$13, AH16:AH515) -> 0 | AI13: =SUMIF($B$16:$AL$515, $B$13, AI16:AI515) -> 0 | AJ13: =SUMIF($B$16:$AL$515, $B$13, AJ16:AJ515) -> 0 | AK13: =SUMIF($B$16:$AL$515, $B$13, AK16:AK515) -> 0 | AL13: =SUMIF($B$16:$AL$515, $B$13, AL16:AL515) -> 0
A15: Sr. No. | B15: Nature of Transaction | C15: Head as per Financial Statements | D15: Type of Item | E15: Type of Dealer | F15: Document | G15: HSN | H15: Tax Rate | J15: Taxable Value | K15: CGST | L15: SGST | M15: IGST | N15: Cess | O15: Total GST | P15: Non-GST | Q15: Invoice Value | R15: Validation | T15: Taxable Value | U15: CGST | V15: SGST | W15: IGST | X15: Cess | Y15: Total GST | Z15: Non-GST | AA15: Invoice Value | AB15: Validation | AD15: Taxable Value | AE15: CGST | AF15: SGST | AG15: IGST | AH15: Cess | AI15: Total GST | AJ15: Non-GST | AK15: Invoice Value | AL15: Validation
A16: 1 | J16: =Apr!J16+May!J16+Jun!J16+Jul!J16+Aug!J16+Sep!J16+Oct!J16+Nov!J16+Dec!J16+Jan!J16+Feb!J16+Mar!J16 -> 0 | K16: =Apr!K16+May!K16+Jun!K16+Jul!K16+Aug!K16+Sep!K16+Oct!K16+Nov!K16+Dec!K16+Jan!K16+Feb!K16+Mar!K16 -> 0 | L16: =Apr!L16+May!L16+Jun!L16+Jul!L16+Aug!L16+Sep!L16+Oct!L16+Nov!L16+Dec!L16+Jan!L16+Feb!L16+Mar!L16 -> 0 | M16: =Apr!M16+May!M16+Jun!M16+Jul!M16+Aug!M16+Sep!M16+Oct!M16+Nov!M16+Dec!M16+Jan!M16+Feb!M16+Mar!M16 -> 0 | N16: =Apr!N16+May!N16+Jun!N16+Jul!N16+Aug!N16+Sep!N16+Oct!N16+Nov!N16+Dec!N16+Jan!N16+Feb!N16+Mar!N16 -> 0 | O16: =SUM(K16:N16) -> 0 | P16: =Apr!P16+May!P16+Jun!P16+Jul!P16+Aug!P16+Sep!P16+Oct!P16+Nov!P16+Dec!P16+Jan!P16+Feb!P16+Mar!P16 -> 0 | Q16: =J16+O16+P16 -> 0 | R16: =IF(H16="Exempt",0,ROUND((J16*H16/100)-SUM(K16:M16),2)) -> 0 | T16: =Apr!T16+May!T16+Jun!T16+Jul!T16+Aug!T16+Sep!T16+Oct!T16+Nov!T16+Dec!T16+Jan!T16+Feb!T16+Mar!T16 -> 0 | U16: =Apr!U16+May!U16+Jun!U16+Jul!U16+Aug!U16+Sep!U16+Oct!U16+Nov!U16+Dec!U16+Jan!U16+Feb!U16+Mar!U16 -> 0 | V16: =Apr!V16+May!V16+Jun!V16+Jul!V16+Aug!V16+Sep!V16+Oct!V16+Nov!V16+Dec!V16+Jan!V16+Feb!V16+Mar!V16 -> 0 | W16: =Apr!W16+May!W16+Jun!W16+Jul!W16+Aug!W16+Sep!W16+Oct!W16+Nov!W16+Dec!W16+Jan!W16+Feb!W16+Mar!W16 -> 0 | X16: =Apr!X16+May!X16+Jun!X16+Jul!X16+Aug!X16+Sep!X16+Oct!X16+Nov!X16+Dec!X16+Jan!X16+Feb!X16+Mar!X16 -> 0 | Y16: =SUM(U16:X16) -> 0 | Z16: =Apr!Z16+May!Z16+Jun!Z16+Jul!Z16+Aug!Z16+Sep!Z16+Oct!Z16+Nov!Z16+Dec!Z16+Jan!Z16+Feb!Z16+Mar!Z16 -> 0 | AA16: =T16+Y16+Z16 -> 0 | AB16: =IF(H16="Exempt",0,ROUND((T16*H16/100)-SUM(U16:W16),2)) -> 0 | AD16: =Apr!AD16+May!AD16+Jun!AD16+Jul!AD16+Aug!AD16+Sep!AD16+Oct!AD16+Nov!AD16+Dec!AD16+Jan!AD16+Feb!AD16+Mar!AD16 -> 0 | AE16: =Apr!AE16+May!AE16+Jun!AE16+Jul!AE16+Aug!AE16+Sep!AE16+Oct!AE16+Nov!AE16+Dec!AE16+Jan!AE16+Feb!AE16+Mar!AE16 -> 0 | AF16: =Apr!AF16+May!AF16+Jun!AF16+Jul!AF16+Aug!AF16+Sep!AF16+Oct!AF16+Nov!AF16+Dec!AF16+Jan!AF16+Feb!AF16+Mar!AF16 -> 0 | AG16: =Apr!AG16+May!AG16+Jun!AG16+Jul!AG16+Aug!AG16+Sep!AG16+Oct!AG16+Nov!AG16+Dec!AG16+Jan!AG16+Feb!AG16+Mar!AG16 -> 0 | AI16: =SUM(AE16:AH16) -> 0 | AJ16: =Apr!AJ16+May!AJ16+Jun!AJ16+Jul!AJ16+Aug!AJ16+Sep!AJ16+Oct!AJ16+Nov!AJ16+Dec!AJ16+Jan!AJ16+Feb!AJ16+Mar!AJ16 -> 0 | AK16: =AD16+AI16+AJ16 -> 0 | AL16: =IF(H16="Exempt",0,ROUND((AD16*H16/100)-SUM(AE16:AG16),2)) -> 0 | AO16: Goods | AP16: Registered | AQ16: Tax Invoice | AR16: 28
A17: =+A16+1 -> 2 | J17: =Apr!J17+May!J17+Jun!J17+Jul!J17+Aug!J17+Sep!J17+Oct!J17+Nov!J17+Dec!J17+Jan!J17+Feb!J17+Mar!J17 -> 0 | K17: =Apr!K17+May!K17+Jun!K17+Jul!K17+Aug!K17+Sep!K17+Oct!K17+Nov!K17+Dec!K17+Jan!K17+Feb!K17+Mar!K17 -> 0 | L17: =Apr!L17+May!L17+Jun!L17+Jul!L17+Aug!L17+Sep!L17+Oct!L17+Nov!L17+Dec!L17+Jan!L17+Feb!L17+Mar!L17 -> 0 | M17: =Apr!M17+May!M17+Jun!M17+Jul!M17+Aug!M17+Sep!M17+Oct!M17+Nov!M17+Dec!M17+Jan!M17+Feb!M17+Mar!M17 -> 0 | N17: =Apr!N17+May!N17+Jun!N17+Jul!N17+Aug!N17+Sep!N17+Oct!N17+Nov!N17+Dec!N17+Jan!N17+Feb!N17+Mar!N17 -> 0 | O17: =SUM(K17:N17) -> 0 | P17: =Apr!P17+May!P17+Jun!P17+Jul!P17+Aug!P17+Sep!P17+Oct!P17+Nov!P17+Dec!P17+Jan!P17+Feb!P17+Mar!P17 -> 0 | Q17: =J17+O17+P17 -> 0 | R17: =IF(H17="Exempt",0,ROUND((J17*H17/100)-SUM(K17:M17),2)) -> 0 | T17: =Apr!T17+May!T17+Jun!T17+Jul!T17+Aug!T17+Sep!T17+Oct!T17+Nov!T17+Dec!T17+Jan!T17+Feb!T17+Mar!T17 -> 0 | U17: =Apr!U17+May!U17+Jun!U17+Jul!U17+Aug!U17+Sep!U17+Oct!U17+Nov!U17+Dec!U17+Jan!U17+Feb!U17+Mar!U17 -> 0 | V17: =Apr!V17+May!V17+Jun!V17+Jul!V17+Aug!V17+Sep!V17+Oct!V17+Nov!V17+Dec!V17+Jan!V17+Feb!V17+Mar!V17 -> 0 | W17: =Apr!W17+May!W17+Jun!W17+Jul!W17+Aug!W17+Sep!W17+Oct!W17+Nov!W17+Dec!W17+Jan!W17+Feb!W17+Mar!W17 -> 0 | X17: =Apr!X17+May!X17+Jun!X17+Jul!X17+Aug!X17+Sep!X17+Oct!X17+Nov!X17+Dec!X17+Jan!X17+Feb!X17+Mar!X17 -> 0 | Y17: =SUM(U17:X17) -> 0 | Z17: =Apr!Z17+May!Z17+Jun!Z17+Jul!Z17+Aug!Z17+Sep!Z17+Oct!Z17+Nov!Z17+Dec!Z17+Jan!Z17+Feb!Z17+Mar!Z17 -> 0 | AA17: =T17+Y17+Z17 -> 0 | AB17: =IF(H17="Exempt",0,ROUND((T17*H17/100)-SUM(U17:W17),2)) -> 0 | AD17: =Apr!AD17+May!AD17+Jun!AD17+Jul!AD17+Aug!AD17+Sep!AD17+Oct!AD17+Nov!AD17+Dec!AD17+Jan!AD17+Feb!AD17+Mar!AD17 -> 0 | AE17: =Apr!AE17+May!AE17+Jun!AE17+Jul!AE17+Aug!AE17+Sep!AE17+Oct!AE17+Nov!AE17+Dec!AE17+Jan!AE17+Feb!AE17+Mar!AE17 -> 0 | AF17: =Apr!AF17+May!AF17+Jun!AF17+Jul!AF17+Aug!AF17+Sep!AF17+Oct!AF17+Nov!AF17+Dec!AF17+Jan!AF17+Feb!AF17+Mar!AF17 -> 0 | AG17: =Apr!AG17+May!AG17+Jun!AG17+Jul!AG17+Aug!AG17+Sep!AG17+Oct!AG17+Nov!AG17+Dec!AG17+Jan!AG17+Feb!AG17+Mar!AG17 -> 0 | AI17: =SUM(AE17:AH17) -> 0 | AJ17: =Apr!AJ17+May!AJ17+Jun!AJ17+Jul!AJ17+Aug!AJ17+Sep!AJ17+Oct!AJ17+Nov!AJ17+Dec!AJ17+Jan!AJ17+Feb!AJ17+Mar!AJ17 -> 0 | AK17: =AD17+AI17+AJ17 -> 0 | AL17: =IF(H17="Exempt",0,ROUND((AD17*H17/100)-SUM(AE17:AG17),2)) -> 0 | AO17: Services | AP17: Unregistered | AQ17: Debit Note | AR17: 18
A18: =+A17+1 -> 3 | J18: =Apr!J18+May!J18+Jun!J18+Jul!J18+Aug!J18+Sep!J18+Oct!J18+Nov!J18+Dec!J18+Jan!J18+Feb!J18+Mar!J18 -> 0 | K18: =Apr!K18+May!K18+Jun!K18+Jul!K18+Aug!K18+Sep!K18+Oct!K18+Nov!K18+Dec!K18+Jan!K18+Feb!K18+Mar!K18 -> 0 | L18: =Apr!L18+May!L18+Jun!L18+Jul!L18+Aug!L18+Sep!L18+Oct!L18+Nov!L18+Dec!L18+Jan!L18+Feb!L18+Mar!L18 -> 0 | M18: =Apr!M18+May!M18+Jun!M18+Jul!M18+Aug!M18+Sep!M18+Oct!M18+Nov!M18+Dec!M18+Jan!M18+Feb!M18+Mar!M18 -> 0 | N18: =Apr!N18+May!N18+Jun!N18+Jul!N18+Aug!N18+Sep!N18+Oct!N18+Nov!N18+Dec!N18+Jan!N18+Feb!N18+Mar!N18 -> 0 | O18: =SUM(K18:N18) -> 0 | P18: =Apr!P18+May!P18+Jun!P18+Jul!P18+Aug!P18+Sep!P18+Oct!P18+Nov!P18+Dec!P18+Jan!P18+Feb!P18+Mar!P18 -> 0 | Q18: =J18+O18+P18 -> 0 | R18: =IF(H18="Exempt",0,ROUND((J18*H18/100)-SUM(K18:M18),2)) -> 0 | T18: =Apr!T18+May!T18+Jun!T18+Jul!T18+Aug!T18+Sep!T18+Oct!T18+Nov!T18+Dec!T18+Jan!T18+Feb!T18+Mar!T18 -> 0 | U18: =Apr!U18+May!U18+Jun!U18+Jul!U18+Aug!U18+Sep!U18+Oct!U18+Nov!U18+Dec!U18+Jan!U18+Feb!U18+Mar!U18 -> 0 | V18: =Apr!V18+May!V18+Jun!V18+Jul!V18+Aug!V18+Sep!V18+Oct!V18+Nov!V18+Dec!V18+Jan!V18+Feb!V18+Mar!V18 -> 0 | W18: =Apr!W18+May!W18+Jun!W18+Jul!W18+Aug!W18+Sep!W18+Oct!W18+Nov!W18+Dec!W18+Jan!W18+Feb!W18+Mar!W18 -> 0 | X18: =Apr!X18+May!X18+Jun!X18+Jul!X18+Aug!X18+Sep!X18+Oct!X18+Nov!X18+Dec!X18+Jan!X18+Feb!X18+Mar!X18 -> 0 | Y18: =SUM(U18:X18) -> 0 | Z18: =Apr!Z18+May!Z18+Jun!Z18+Jul!Z18+Aug!Z18+Sep!Z18+Oct!Z18+Nov!Z18+Dec!Z18+Jan!Z18+Feb!Z18+Mar!Z18 -> 0 | AA18: =T18+Y18+Z18 -> 0 | AB18: =IF(H18="Exempt",0,ROUND((T18*H18/100)-SUM(U18:W18),2)) -> 0 | AD18: =Apr!AD18+May!AD18+Jun!AD18+Jul!AD18+Aug!AD18+Sep!AD18+Oct!AD18+Nov!AD18+Dec!AD18+Jan!AD18+Feb!AD18+Mar!AD18 -> 0 | AE18: =Apr!AE18+May!AE18+Jun!AE18+Jul!AE18+Aug!AE18+Sep!AE18+Oct!AE18+Nov!AE18+Dec!AE18+Jan!AE18+Feb!AE18+Mar!AE18 -> 0 | AF18: =Apr!AF18+May!AF18+Jun!AF18+Jul!AF18+Aug!AF18+Sep!AF18+Oct!AF18+Nov!AF18+Dec!AF18+Jan!AF18+Feb!AF18+Mar!AF18 -> 0 | AG18: =Apr!AG18+May!AG18+Jun!AG18+Jul!AG18+Aug!AG18+Sep!AG18+Oct!AG18+Nov!AG18+Dec!AG18+Jan!AG18+Feb!AG18+Mar!AG18 -> 0 | AI18: =SUM(AE18:AH18) -> 0 | AJ18: =Apr!AJ18+May!AJ18+Jun!AJ18+Jul!AJ18+Aug!AJ18+Sep!AJ18+Oct!AJ18+Nov!AJ18+Dec!AJ18+Jan!AJ18+Feb!AJ18+Mar!AJ18 -> 0 | AK18: =AD18+AI18+AJ18 -> 0 | AL18: =IF(H18="Exempt",0,ROUND((AD18*H18/100)-SUM(AE18:AG18),2)) -> 0 | AO18: Capital Assets | AP18: Composition | AQ18: Credit Note | AR18: 12
A19: =+A18+1 -> 4 | J19: =Apr!J19+May!J19+Jun!J19+Jul!J19+Aug!J19+Sep!J19+Oct!J19+Nov!J19+Dec!J19+Jan!J19+Feb!J19+Mar!J19 -> 0 | K19: =Apr!K19+May!K19+Jun!K19+Jul!K19+Aug!K19+Sep!K19+Oct!K19+Nov!K19+Dec!K19+Jan!K19+Feb!K19+Mar!K19 -> 0 | L19: =Apr!L19+May!L19+Jun!L19+Jul!L19+Aug!L19+Sep!L19+Oct!L19+Nov!L19+Dec!L19+Jan!L19+Feb!L19+Mar!L19 -> 0 | M19: =Apr!M19+May!M19+Jun!M19+Jul!M19+Aug!M19+Sep!M19+Oct!M19+Nov!M19+Dec!M19+Jan!M19+Feb!M19+Mar!M19 -> 0 | N19: =Apr!N19+May!N19+Jun!N19+Jul!N19+Aug!N19+Sep!N19+Oct!N19+Nov!N19+Dec!N19+Jan!N19+Feb!N19+Mar!N19 -> 0 | O19: =SUM(K19:N19) -> 0 | P19: =Apr!P19+May!P19+Jun!P19+Jul!P19+Aug!P19+Sep!P19+Oct!P19+Nov!P19+Dec!P19+Jan!P19+Feb!P19+Mar!P19 -> 0 | Q19: =J19+O19+P19 -> 0 | R19: =IF(H19="Exempt",0,ROUND((J19*H19/100)-SUM(K19:M19),2)) -> 0 | T19: =Apr!T19+May!T19+Jun!T19+Jul!T19+Aug!T19+Sep!T19+Oct!T19+Nov!T19+Dec!T19+Jan!T19+Feb!T19+Mar!T19 -> 0 | U19: =Apr!U19+May!U19+Jun!U19+Jul!U19+Aug!U19+Sep!U19+Oct!U19+Nov!U19+Dec!U19+Jan!U19+Feb!U19+Mar!U19 -> 0 | V19: =Apr!V19+May!V19+Jun!V19+Jul!V19+Aug!V19+Sep!V19+Oct!V19+Nov!V19+Dec!V19+Jan!V19+Feb!V19+Mar!V19 -> 0 | W19: =Apr!W19+May!W19+Jun!W19+Jul!W19+Aug!W19+Sep!W19+Oct!W19+Nov!W19+Dec!W19+Jan!W19+Feb!W19+Mar!W19 -> 0 | X19: =Apr!X19+May!X19+Jun!X19+Jul!X19+Aug!X19+Sep!X19+Oct!X19+Nov!X19+Dec!X19+Jan!X19+Feb!X19+Mar!X19 -> 0 | Y19: =SUM(U19:X19) -> 0 | Z19: =Apr!Z19+May!Z19+Jun!Z19+Jul!Z19+Aug!Z19+Sep!Z19+Oct!Z19+Nov!Z19+Dec!Z19+Jan!Z19+Feb!Z19+Mar!Z19 -> 0 | AA19: =T19+Y19+Z19 -> 0 | AB19: =IF(H19="Exempt",0,ROUND((T19*H19/100)-SUM(U19:W19),2)) -> 0 | AD19: =Apr!AD19+May!AD19+Jun!AD19+Jul!AD19+Aug!AD19+Sep!AD19+Oct!AD19+Nov!AD19+Dec!AD19+Jan!AD19+Feb!AD19+Mar!AD19 -> 0 | AE19: =Apr!AE19+May!AE19+Jun!AE19+Jul!AE19+Aug!AE19+Sep!AE19+Oct!AE19+Nov!AE19+Dec!AE19+Jan!AE19+Feb!AE19+Mar!AE19 -> 0 | AF19: =Apr!AF19+May!AF19+Jun!AF19+Jul!AF19+Aug!AF19+Sep!AF19+Oct!AF19+Nov!AF19+Dec!AF19+Jan!AF19+Feb!AF19+Mar!AF19 -> 0 | AG19: =Apr!AG19+May!AG19+Jun!AG19+Jul!AG19+Aug!AG19+Sep!AG19+Oct!AG19+Nov!AG19+Dec!AG19+Jan!AG19+Feb!AG19+Mar!AG19 -> 0 | AI19: =SUM(AE19:AH19) -> 0 | AJ19: =Apr!AJ19+May!AJ19+Jun!AJ19+Jul!AJ19+Aug!AJ19+Sep!AJ19+Oct!AJ19+Nov!AJ19+Dec!AJ19+Jan!AJ19+Feb!AJ19+Mar!AJ19 -> 0 | AK19: =AD19+AI19+AJ19 -> 0 | AL19: =IF(H19="Exempt",0,ROUND((AD19*H19/100)-SUM(AE19:AG19),2)) -> 0 | AO19: Others | AP19: Others | AQ19: RCM Invoice | AR19: 5
A20: =+A19+1 -> 5 | J20: =Apr!J20+May!J20+Jun!J20+Jul!J20+Aug!J20+Sep!J20+Oct!J20+Nov!J20+Dec!J20+Jan!J20+Feb!J20+Mar!J20 -> 0 | K20: =Apr!K20+May!K20+Jun!K20+Jul!K20+Aug!K20+Sep!K20+Oct!K20+Nov!K20+Dec!K20+Jan!K20+Feb!K20+Mar!K20 -> 0 | L20: =Apr!L20+May!L20+Jun!L20+Jul!L20+Aug!L20+Sep!L20+Oct!L20+Nov!L20+Dec!L20+Jan!L20+Feb!L20+Mar!L20 -> 0 | M20: =Apr!M20+May!M20+Jun!M20+Jul!M20+Aug!M20+Sep!M20+Oct!M20+Nov!M20+Dec!M20+Jan!M20+Feb!M20+Mar!M20 -> 0 | N20: =Apr!N20+May!N20+Jun!N20+Jul!N20+Aug!N20+Sep!N20+Oct!N20+Nov!N20+Dec!N20+Jan!N20+Feb!N20+Mar!N20 -> 0 | O20: =SUM(K20:N20) -> 0 | P20: =Apr!P20+May!P20+Jun!P20+Jul!P20+Aug!P20+Sep!P20+Oct!P20+Nov!P20+Dec!P20+Jan!P20+Feb!P20+Mar!P20 -> 0 | Q20: =J20+O20+P20 -> 0 | R20: =IF(H20="Exempt",0,ROUND((J20*H20/100)-SUM(K20:M20),2)) -> 0 | T20: =Apr!T20+May!T20+Jun!T20+Jul!T20+Aug!T20+Sep!T20+Oct!T20+Nov!T20+Dec!T20+Jan!T20+Feb!T20+Mar!T20 -> 0 | U20: =Apr!U20+May!U20+Jun!U20+Jul!U20+Aug!U20+Sep!U20+Oct!U20+Nov!U20+Dec!U20+Jan!U20+Feb!U20+Mar!U20 -> 0 | V20: =Apr!V20+May!V20+Jun!V20+Jul!V20+Aug!V20+Sep!V20+Oct!V20+Nov!V20+Dec!V20+Jan!V20+Feb!V20+Mar!V20 -> 0 | W20: =Apr!W20+May!W20+Jun!W20+Jul!W20+Aug!W20+Sep!W20+Oct!W20+Nov!W20+Dec!W20+Jan!W20+Feb!W20+Mar!W20 -> 0 | X20: =Apr!X20+May!X20+Jun!X20+Jul!X20+Aug!X20+Sep!X20+Oct!X20+Nov!X20+Dec!X20+Jan!X20+Feb!X20+Mar!X20 -> 0 | Y20: =SUM(U20:X20) -> 0 | Z20: =Apr!Z20+May!Z20+Jun!Z20+Jul!Z20+Aug!Z20+Sep!Z20+Oct!Z20+Nov!Z20+Dec!Z20+Jan!Z20+Feb!Z20+Mar!Z20 -> 0 | AA20: =T20+Y20+Z20 -> 0 | AB20: =IF(H20="Exempt",0,ROUND((T20*H20/100)-SUM(U20:W20),2)) -> 0 | AD20: =Apr!AD20+May!AD20+Jun!AD20+Jul!AD20+Aug!AD20+Sep!AD20+Oct!AD20+Nov!AD20+Dec!AD20+Jan!AD20+Feb!AD20+Mar!AD20 -> 0 | AE20: =Apr!AE20+May!AE20+Jun!AE20+Jul!AE20+Aug!AE20+Sep!AE20+Oct!AE20+Nov!AE20+Dec!AE20+Jan!AE20+Feb!AE20+Mar!AE20 -> 0 | AF20: =Apr!AF20+May!AF20+Jun!AF20+Jul!AF20+Aug!AF20+Sep!AF20+Oct!AF20+Nov!AF20+Dec!AF20+Jan!AF20+Feb!AF20+Mar!AF20 -> 0 | AG20: =Apr!AG20+May!AG20+Jun!AG20+Jul!AG20+Aug!AG20+Sep!AG20+Oct!AG20+Nov!AG20+Dec!AG20+Jan!AG20+Feb!AG20+Mar!AG20 -> 0 | AI20: =SUM(AE20:AH20) -> 0 | AJ20: =Apr!AJ20+May!AJ20+Jun!AJ20+Jul!AJ20+Aug!AJ20+Sep!AJ20+Oct!AJ20+Nov!AJ20+Dec!AJ20+Jan!AJ20+Feb!AJ20+Mar!AJ20 -> 0 | AK20: =AD20+AI20+AJ20 -> 0 | AL20: =IF(H20="Exempt",0,ROUND((AD20*H20/100)-SUM(AE20:AG20),2)) -> 0 | AQ20: Challan | AR20: 3
A21: =+A20+1 -> 6 | J21: =Apr!J21+May!J21+Jun!J21+Jul!J21+Aug!J21+Sep!J21+Oct!J21+Nov!J21+Dec!J21+Jan!J21+Feb!J21+Mar!J21 -> 0 | K21: =Apr!K21+May!K21+Jun!K21+Jul!K21+Aug!K21+Sep!K21+Oct!K21+Nov!K21+Dec!K21+Jan!K21+Feb!K21+Mar!K21 -> 0 | L21: =Apr!L21+May!L21+Jun!L21+Jul!L21+Aug!L21+Sep!L21+Oct!L21+Nov!L21+Dec!L21+Jan!L21+Feb!L21+Mar!L21 -> 0 | M21: =Apr!M21+May!M21+Jun!M21+Jul!M21+Aug!M21+Sep!M21+Oct!M21+Nov!M21+Dec!M21+Jan!M21+Feb!M21+Mar!M21 -> 0 | N21: =Apr!N21+May!N21+Jun!N21+Jul!N21+Aug!N21+Sep!N21+Oct!N21+Nov!N21+Dec!N21+Jan!N21+Feb!N21+Mar!N21 -> 0 | O21: =SUM(K21:N21) -> 0 | P21: =Apr!P21+May!P21+Jun!P21+Jul!P21+Aug!P21+Sep!P21+Oct!P21+Nov!P21+Dec!P21+Jan!P21+Feb!P21+Mar!P21 -> 0 | Q21: =J21+O21+P21 -> 0 | R21: =IF(H21="Exempt",0,ROUND((J21*H21/100)-SUM(K21:M21),2)) -> 0 | T21: =Apr!T21+May!T21+Jun!T21+Jul!T21+Aug!T21+Sep!T21+Oct!T21+Nov!T21+Dec!T21+Jan!T21+Feb!T21+Mar!T21 -> 0 | U21: =Apr!U21+May!U21+Jun!U21+Jul!U21+Aug!U21+Sep!U21+Oct!U21+Nov!U21+Dec!U21+Jan!U21+Feb!U21+Mar!U21 -> 0 | V21: =Apr!V21+May!V21+Jun!V21+Jul!V21+Aug!V21+Sep!V21+Oct!V21+Nov!V21+Dec!V21+Jan!V21+Feb!V21+Mar!V21 -> 0 | W21: =Apr!W21+May!W21+Jun!W21+Jul!W21+Aug!W21+Sep!W21+Oct!W21+Nov!W21+Dec!W21+Jan!W21+Feb!W21+Mar!W21 -> 0 | X21: =Apr!X21+May!X21+Jun!X21+Jul!X21+Aug!X21+Sep!X21+Oct!X21+Nov!X21+Dec!X21+Jan!X21+Feb!X21+Mar!X21 -> 0 | Y21: =SUM(U21:X21) -> 0 | Z21: =Apr!Z21+May!Z21+Jun!Z21+Jul!Z21+Aug!Z21+Sep!Z21+Oct!Z21+Nov!Z21+Dec!Z21+Jan!Z21+Feb!Z21+Mar!Z21 -> 0 | AA21: =T21+Y21+Z21 -> 0 | AB21: =IF(H21="Exempt",0,ROUND((T21*H21/100)-SUM(U21:W21),2)) -> 0 | AD21: =Apr!AD21+May!AD21+Jun!AD21+Jul!AD21+Aug!AD21+Sep!AD21+Oct!AD21+Nov!AD21+Dec!AD21+Jan!AD21+Feb!AD21+Mar!AD21 -> 0 | AE21: =Apr!AE21+May!AE21+Jun!AE21+Jul!AE21+Aug!AE21+Sep!AE21+Oct!AE21+Nov!AE21+Dec!AE21+Jan!AE21+Feb!AE21+Mar!AE21 -> 0 | AF21: =Apr!AF21+May!AF21+Jun!AF21+Jul!AF21+Aug!AF21+Sep!AF21+Oct!AF21+Nov!AF21+Dec!AF21+Jan!AF21+Feb!AF21+Mar!AF21 -> 0 | AG21: =Apr!AG21+May!AG21+Jun!AG21+Jul!AG21+Aug!AG21+Sep!AG21+Oct!AG21+Nov!AG21+Dec!AG21+Jan!AG21+Feb!AG21+Mar!AG21 -> 0 | AI21: =SUM(AE21:AH21) -> 0 | AJ21: =Apr!AJ21+May!AJ21+Jun!AJ21+Jul!AJ21+Aug!AJ21+Sep!AJ21+Oct!AJ21+Nov!AJ21+Dec!AJ21+Jan!AJ21+Feb!AJ21+Mar!AJ21 -> 0 | AK21: =AD21+AI21+AJ21 -> 0 | AL21: =IF(H21="Exempt",0,ROUND((AD21*H21/100)-SUM(AE21:AG21),2)) -> 0 | AQ21: Others | AR21: 0.25
A22: =+A21+1 -> 7 | J22: =Apr!J22+May!J22+Jun!J22+Jul!J22+Aug!J22+Sep!J22+Oct!J22+Nov!J22+Dec!J22+Jan!J22+Feb!J22+Mar!J22 -> 0 | K22: =Apr!K22+May!K22+Jun!K22+Jul!K22+Aug!K22+Sep!K22+Oct!K22+Nov!K22+Dec!K22+Jan!K22+Feb!K22+Mar!K22 -> 0 | L22: =Apr!L22+May!L22+Jun!L22+Jul!L22+Aug!L22+Sep!L22+Oct!L22+Nov!L22+Dec!L22+Jan!L22+Feb!L22+Mar!L22 -> 0 | M22: =Apr!M22+May!M22+Jun!M22+Jul!M22+Aug!M22+Sep!M22+Oct!M22+Nov!M22+Dec!M22+Jan!M22+Feb!M22+Mar!M22 -> 0 | N22: =Apr!N22+May!N22+Jun!N22+Jul!N22+Aug!N22+Sep!N22+Oct!N22+Nov!N22+Dec!N22+Jan!N22+Feb!N22+Mar!N22 -> 0 | O22: =SUM(K22:N22) -> 0 | P22: =Apr!P22+May!P22+Jun!P22+Jul!P22+Aug!P22+Sep!P22+Oct!P22+Nov!P22+Dec!P22+Jan!P22+Feb!P22+Mar!P22 -> 0 | Q22: =J22+O22+P22 -> 0 | R22: =IF(H22="Exempt",0,ROUND((J22*H22/100)-SUM(K22:M22),2)) -> 0 | T22: =Apr!T22+May!T22+Jun!T22+Jul!T22+Aug!T22+Sep!T22+Oct!T22+Nov!T22+Dec!T22+Jan!T22+Feb!T22+Mar!T22 -> 0 | U22: =Apr!U22+May!U22+Jun!U22+Jul!U22+Aug!U22+Sep!U22+Oct!U22+Nov!U22+Dec!U22+Jan!U22+Feb!U22+Mar!U22 -> 0 | V22: =Apr!V22+May!V22+Jun!V22+Jul!V22+Aug!V22+Sep!V22+Oct!V22+Nov!V22+Dec!V22+Jan!V22+Feb!V22+Mar!V22 -> 0 | W22: =Apr!W22+May!W22+Jun!W22+Jul!W22+Aug!W22+Sep!W22+Oct!W22+Nov!W22+Dec!W22+Jan!W22+Feb!W22+Mar!W22 -> 0 | X22: =Apr!X22+May!X22+Jun!X22+Jul!X22+Aug!X22+Sep!X22+Oct!X22+Nov!X22+Dec!X22+Jan!X22+Feb!X22+Mar!X22 -> 0 | Y22: =SUM(U22:X22) -> 0 | Z22: =Apr!Z22+May!Z22+Jun!Z22+Jul!Z22+Aug!Z22+Sep!Z22+Oct!Z22+Nov!Z22+Dec!Z22+Jan!Z22+Feb!Z22+Mar!Z22 -> 0 | AA22: =T22+Y22+Z22 -> 0 | AB22: =IF(H22="Exempt",0,ROUND((T22*H22/100)-SUM(U22:W22),2)) -> 0 | AD22: =Apr!AD22+May!AD22+Jun!AD22+Jul!AD22+Aug!AD22+Sep!AD22+Oct!AD22+Nov!AD22+Dec!AD22+Jan!AD22+Feb!AD22+Mar!AD22 -> 0 | AE22: =Apr!AE22+May!AE22+Jun!AE22+Jul!AE22+Aug!AE22+Sep!AE22+Oct!AE22+Nov!AE22+Dec!AE22+Jan!AE22+Feb!AE22+Mar!AE22 -> 0 | AF22: =Apr!AF22+May!AF22+Jun!AF22+Jul!AF22+Aug!AF22+Sep!AF22+Oct!AF22+Nov!AF22+Dec!AF22+Jan!AF22+Feb!AF22+Mar!AF22 -> 0 | AG22: =Apr!AG22+May!AG22+Jun!AG22+Jul!AG22+Aug!AG22+Sep!AG22+Oct!AG22+Nov!AG22+Dec!AG22+Jan!AG22+Feb!AG22+Mar!AG22 -> 0 | AI22: =SUM(AE22:AH22) -> 0 | AJ22: =Apr!AJ22+May!AJ22+Jun!AJ22+Jul!AJ22+Aug!AJ22+Sep!AJ22+Oct!AJ22+Nov!AJ22+Dec!AJ22+Jan!AJ22+Feb!AJ22+Mar!AJ22 -> 0 | AK22: =AD22+AI22+AJ22 -> 0 | AL22: =IF(H22="Exempt",0,ROUND((AD22*H22/100)-SUM(AE22:AG22),2)) -> 0 | AR22: 0.1
A23: =+A22+1 -> 8 | J23: =Apr!J23+May!J23+Jun!J23+Jul!J23+Aug!J23+Sep!J23+Oct!J23+Nov!J23+Dec!J23+Jan!J23+Feb!J23+Mar!J23 -> 0 | K23: =Apr!K23+May!K23+Jun!K23+Jul!K23+Aug!K23+Sep!K23+Oct!K23+Nov!K23+Dec!K23+Jan!K23+Feb!K23+Mar!K23 -> 0 | L23: =Apr!L23+May!L23+Jun!L23+Jul!L23+Aug!L23+Sep!L23+Oct!L23+Nov!L23+Dec!L23+Jan!L23+Feb!L23+Mar!L23 -> 0 | M23: =Apr!M23+May!M23+Jun!M23+Jul!M23+Aug!M23+Sep!M23+Oct!M23+Nov!M23+Dec!M23+Jan!M23+Feb!M23+Mar!M23 -> 0 | N23: =Apr!N23+May!N23+Jun!N23+Jul!N23+Aug!N23+Sep!N23+Oct!N23+Nov!N23+Dec!N23+Jan!N23+Feb!N23+Mar!N23 -> 0 | O23: =SUM(K23:N23) -> 0 | P23: =Apr!P23+May!P23+Jun!P23+Jul!P23+Aug!P23+Sep!P23+Oct!P23+Nov!P23+Dec!P23+Jan!P23+Feb!P23+Mar!P23 -> 0 | Q23: =J23+O23+P23 -> 0 | R23: =IF(H23="Exempt",0,ROUND((J23*H23/100)-SUM(K23:M23),2)) -> 0 | T23: =Apr!T23+May!T23+Jun!T23+Jul!T23+Aug!T23+Sep!T23+Oct!T23+Nov!T23+Dec!T23+Jan!T23+Feb!T23+Mar!T23 -> 0 | U23: =Apr!U23+May!U23+Jun!U23+Jul!U23+Aug!U23+Sep!U23+Oct!U23+Nov!U23+Dec!U23+Jan!U23+Feb!U23+Mar!U23 -> 0 | V23: =Apr!V23+May!V23+Jun!V23+Jul!V23+Aug!V23+Sep!V23+Oct!V23+Nov!V23+Dec!V23+Jan!V23+Feb!V23+Mar!V23 -> 0 | W23: =Apr!W23+May!W23+Jun!W23+Jul!W23+Aug!W23+Sep!W23+Oct!W23+Nov!W23+Dec!W23+Jan!W23+Feb!W23+Mar!W23 -> 0 | X23: =Apr!X23+May!X23+Jun!X23+Jul!X23+Aug!X23+Sep!X23+Oct!X23+Nov!X23+Dec!X23+Jan!X23+Feb!X23+Mar!X23 -> 0 | Y23: =SUM(U23:X23) -> 0 | Z23: =Apr!Z23+May!Z23+Jun!Z23+Jul!Z23+Aug!Z23+Sep!Z23+Oct!Z23+Nov!Z23+Dec!Z23+Jan!Z23+Feb!Z23+Mar!Z23 -> 0 | AA23: =T23+Y23+Z23 -> 0 | AB23: =IF(H23="Exempt",0,ROUND((T23*H23/100)-SUM(U23:W23),2)) -> 0 | AD23: =Apr!AD23+May!AD23+Jun!AD23+Jul!AD23+Aug!AD23+Sep!AD23+Oct!AD23+Nov!AD23+Dec!AD23+Jan!AD23+Feb!AD23+Mar!AD23 -> 0 | AE23: =Apr!AE23+May!AE23+Jun!AE23+Jul!AE23+Aug!AE23+Sep!AE23+Oct!AE23+Nov!AE23+Dec!AE23+Jan!AE23+Feb!AE23+Mar!AE23 -> 0 | AF23: =Apr!AF23+May!AF23+Jun!AF23+Jul!AF23+Aug!AF23+Sep!AF23+Oct!AF23+Nov!AF23+Dec!AF23+Jan!AF23+Feb!AF23+Mar!AF23 -> 0 | AG23: =Apr!AG23+May!AG23+Jun!AG23+Jul!AG23+Aug!AG23+Sep!AG23+Oct!AG23+Nov!AG23+Dec!AG23+Jan!AG23+Feb!AG23+Mar!AG23 -> 0 | AI23: =SUM(AE23:AH23) -> 0 | AJ23: =Apr!AJ23+May!AJ23+Jun!AJ23+Jul!AJ23+Aug!AJ23+Sep!AJ23+Oct!AJ23+Nov!AJ23+Dec!AJ23+Jan!AJ23+Feb!AJ23+Mar!AJ23 -> 0 | AK23: =AD23+AI23+AJ23 -> 0 | AL23: =IF(H23="Exempt",0,ROUND((AD23*H23/100)-SUM(AE23:AG23),2)) -> 0 | AR23: 0
A24: =+A23+1 -> 9 | J24: =Apr!J24+May!J24+Jun!J24+Jul!J24+Aug!J24+Sep!J24+Oct!J24+Nov!J24+Dec!J24+Jan!J24+Feb!J24+Mar!J24 -> 0 | K24: =Apr!K24+May!K24+Jun!K24+Jul!K24+Aug!K24+Sep!K24+Oct!K24+Nov!K24+Dec!K24+Jan!K24+Feb!K24+Mar!K24 -> 0 | L24: =Apr!L24+May!L24+Jun!L24+Jul!L24+Aug!L24+Sep!L24+Oct!L24+Nov!L24+Dec!L24+Jan!L24+Feb!L24+Mar!L24 -> 0 | M24: =Apr!M24+May!M24+Jun!M24+Jul!M24+Aug!M24+Sep!M24+Oct!M24+Nov!M24+Dec!M24+Jan!M24+Feb!M24+Mar!M24 -> 0 | N24: =Apr!N24+May!N24+Jun!N24+Jul!N24+Aug!N24+Sep!N24+Oct!N24+Nov!N24+Dec!N24+Jan!N24+Feb!N24+Mar!N24 -> 0 | O24: =SUM(K24:N24) -> 0 | P24: =Apr!P24+May!P24+Jun!P24+Jul!P24+Aug!P24+Sep!P24+Oct!P24+Nov!P24+Dec!P24+Jan!P24+Feb!P24+Mar!P24 -> 0 | Q24: =J24+O24+P24 -> 0 | R24: =IF(H24="Exempt",0,ROUND((J24*H24/100)-SUM(K24:M24),2)) -> 0 | T24: =Apr!T24+May!T24+Jun!T24+Jul!T24+Aug!T24+Sep!T24+Oct!T24+Nov!T24+Dec!T24+Jan!T24+Feb!T24+Mar!T24 -> 0 | U24: =Apr!U24+May!U24+Jun!U24+Jul!U24+Aug!U24+Sep!U24+Oct!U24+Nov!U24+Dec!U24+Jan!U24+Feb!U24+Mar!U24 -> 0 | V24: =Apr!V24+May!V24+Jun!V24+Jul!V24+Aug!V24+Sep!V24+Oct!V24+Nov!V24+Dec!V24+Jan!V24+Feb!V24+Mar!V24 -> 0 | W24: =Apr!W24+May!W24+Jun!W24+Jul!W24+Aug!W24+Sep!W24+Oct!W24+Nov!W24+Dec!W24+Jan!W24+Feb!W24+Mar!W24 -> 0 | X24: =Apr!X24+May!X24+Jun!X24+Jul!X24+Aug!X24+Sep!X24+Oct!X24+Nov!X24+Dec!X24+Jan!X24+Feb!X24+Mar!X24 -> 0 | Y24: =SUM(U24:X24) -> 0 | Z24: =Apr!Z24+May!Z24+Jun!Z24+Jul!Z24+Aug!Z24+Sep!Z24+Oct!Z24+Nov!Z24+Dec!Z24+Jan!Z24+Feb!Z24+Mar!Z24 -> 0 | AA24: =T24+Y24+Z24 -> 0 | AB24: =IF(H24="Exempt",0,ROUND((T24*H24/100)-SUM(U24:W24),2)) -> 0 | AD24: =Apr!AD24+May!AD24+Jun!AD24+Jul!AD24+Aug!AD24+Sep!AD24+Oct!AD24+Nov!AD24+Dec!AD24+Jan!AD24+Feb!AD24+Mar!AD24 -> 0 | AE24: =Apr!AE24+May!AE24+Jun!AE24+Jul!AE24+Aug!AE24+Sep!AE24+Oct!AE24+Nov!AE24+Dec!AE24+Jan!AE24+Feb!AE24+Mar!AE24 -> 0 | AF24: =Apr!AF24+May!AF24+Jun!AF24+Jul!AF24+Aug!AF24+Sep!AF24+Oct!AF24+Nov!AF24+Dec!AF24+Jan!AF24+Feb!AF24+Mar!AF24 -> 0 | AG24: =Apr!AG24+May!AG24+Jun!AG24+Jul!AG24+Aug!AG24+Sep!AG24+Oct!AG24+Nov!AG24+Dec!AG24+Jan!AG24+Feb!AG24+Mar!AG24 -> 0 | AI24: =SUM(AE24:AH24) -> 0 | AJ24: =Apr!AJ24+May!AJ24+Jun!AJ24+Jul!AJ24+Aug!AJ24+Sep!AJ24+Oct!AJ24+Nov!AJ24+Dec!AJ24+Jan!AJ24+Feb!AJ24+Mar!AJ24 -> 0 | AK24: =AD24+AI24+AJ24 -> 0 | AL24: =IF(H24="Exempt",0,ROUND((AD24*H24/100)-SUM(AE24:AG24),2)) -> 0 | AR24: Exempt
A25: =+A24+1 -> 10 | J25: =Apr!J25+May!J25+Jun!J25+Jul!J25+Aug!J25+Sep!J25+Oct!J25+Nov!J25+Dec!J25+Jan!J25+Feb!J25+Mar!J25 -> 0 | K25: =Apr!K25+May!K25+Jun!K25+Jul!K25+Aug!K25+Sep!K25+Oct!K25+Nov!K25+Dec!K25+Jan!K25+Feb!K25+Mar!K25 -> 0 | L25: =Apr!L25+May!L25+Jun!L25+Jul!L25+Aug!L25+Sep!L25+Oct!L25+Nov!L25+Dec!L25+Jan!L25+Feb!L25+Mar!L25 -> 0 | M25: =Apr!M25+May!M25+Jun!M25+Jul!M25+Aug!M25+Sep!M25+Oct!M25+Nov!M25+Dec!M25+Jan!M25+Feb!M25+Mar!M25 -> 0 | N25: =Apr!N25+May!N25+Jun!N25+Jul!N25+Aug!N25+Sep!N25+Oct!N25+Nov!N25+Dec!N25+Jan!N25+Feb!N25+Mar!N25 -> 0 | O25: =SUM(K25:N25) -> 0 | P25: =Apr!P25+May!P25+Jun!P25+Jul!P25+Aug!P25+Sep!P25+Oct!P25+Nov!P25+Dec!P25+Jan!P25+Feb!P25+Mar!P25 -> 0 | Q25: =J25+O25+P25 -> 0 | R25: =IF(H25="Exempt",0,ROUND((J25*H25/100)-SUM(K25:M25),2)) -> 0 | T25: =Apr!T25+May!T25+Jun!T25+Jul!T25+Aug!T25+Sep!T25+Oct!T25+Nov!T25+Dec!T25+Jan!T25+Feb!T25+Mar!T25 -> 0 | U25: =Apr!U25+May!U25+Jun!U25+Jul!U25+Aug!U25+Sep!U25+Oct!U25+Nov!U25+Dec!U25+Jan!U25+Feb!U25+Mar!U25 -> 0 | V25: =Apr!V25+May!V25+Jun!V25+Jul!V25+Aug!V25+Sep!V25+Oct!V25+Nov!V25+Dec!V25+Jan!V25+Feb!V25+Mar!V25 -> 0 | W25: =Apr!W25+May!W25+Jun!W25+Jul!W25+Aug!W25+Sep!W25+Oct!W25+Nov!W25+Dec!W25+Jan!W25+Feb!W25+Mar!W25 -> 0 | X25: =Apr!X25+May!X25+Jun!X25+Jul!X25+Aug!X25+Sep!X25+Oct!X25+Nov!X25+Dec!X25+Jan!X25+Feb!X25+Mar!X25 -> 0 | Y25: =SUM(U25:X25) -> 0 | Z25: =Apr!Z25+May!Z25+Jun!Z25+Jul!Z25+Aug!Z25+Sep!Z25+Oct!Z25+Nov!Z25+Dec!Z25+Jan!Z25+Feb!Z25+Mar!Z25 -> 0 | AA25: =T25+Y25+Z25 -> 0 | AB25: =IF(H25="Exempt",0,ROUND((T25*H25/100)-SUM(U25:W25),2)) -> 0 | AD25: =Apr!AD25+May!AD25+Jun!AD25+Jul!AD25+Aug!AD25+Sep!AD25+Oct!AD25+Nov!AD25+Dec!AD25+Jan!AD25+Feb!AD25+Mar!AD25 -> 0 | AE25: =Apr!AE25+May!AE25+Jun!AE25+Jul!AE25+Aug!AE25+Sep!AE25+Oct!AE25+Nov!AE25+Dec!AE25+Jan!AE25+Feb!AE25+Mar!AE25 -> 0 | AF25: =Apr!AF25+May!AF25+Jun!AF25+Jul!AF25+Aug!AF25+Sep!AF25+Oct!AF25+Nov!AF25+Dec!AF25+Jan!AF25+Feb!AF25+Mar!AF25 -> 0 | AG25: =Apr!AG25+May!AG25+Jun!AG25+Jul!AG25+Aug!AG25+Sep!AG25+Oct!AG25+Nov!AG25+Dec!AG25+Jan!AG25+Feb!AG25+Mar!AG25 -> 0 | AI25: =SUM(AE25:AH25) -> 0 | AJ25: =Apr!AJ25+May!AJ25+Jun!AJ25+Jul!AJ25+Aug!AJ25+Sep!AJ25+Oct!AJ25+Nov!AJ25+Dec!AJ25+Jan!AJ25+Feb!AJ25+Mar!AJ25 -> 0 | AK25: =AD25+AI25+AJ25 -> 0 | AL25: =IF(H25="Exempt",0,ROUND((AD25*H25/100)-SUM(AE25:AG25),2)) -> 0
A26: =+A25+1 -> 11 | J26: =Apr!J26+May!J26+Jun!J26+Jul!J26+Aug!J26+Sep!J26+Oct!J26+Nov!J26+Dec!J26+Jan!J26+Feb!J26+Mar!J26 -> 0 | K26: =Apr!K26+May!K26+Jun!K26+Jul!K26+Aug!K26+Sep!K26+Oct!K26+Nov!K26+Dec!K26+Jan!K26+Feb!K26+Mar!K26 -> 0 | L26: =Apr!L26+May!L26+Jun!L26+Jul!L26+Aug!L26+Sep!L26+Oct!L26+Nov!L26+Dec!L26+Jan!L26+Feb!L26+Mar!L26 -> 0 | M26: =Apr!M26+May!M26+Jun!M26+Jul!M26+Aug!M26+Sep!M26+Oct!M26+Nov!M26+Dec!M26+Jan!M26+Feb!M26+Mar!M26 -> 0 | N26: =Apr!N26+May!N26+Jun!N26+Jul!N26+Aug!N26+Sep!N26+Oct!N26+Nov!N26+Dec!N26+Jan!N26+Feb!N26+Mar!N26 -> 0 | O26: =SUM(K26:N26) -> 0 | P26: =Apr!P26+May!P26+Jun!P26+Jul!P26+Aug!P26+Sep!P26+Oct!P26+Nov!P26+Dec!P26+Jan!P26+Feb!P26+Mar!P26 -> 0 | Q26: =J26+O26+P26 -> 0 | R26: =IF(H26="Exempt",0,ROUND((J26*H26/100)-SUM(K26:M26),2)) -> 0 | T26: =Apr!T26+May!T26+Jun!T26+Jul!T26+Aug!T26+Sep!T26+Oct!T26+Nov!T26+Dec!T26+Jan!T26+Feb!T26+Mar!T26 -> 0 | U26: =Apr!U26+May!U26+Jun!U26+Jul!U26+Aug!U26+Sep!U26+Oct!U26+Nov!U26+Dec!U26+Jan!U26+Feb!U26+Mar!U26 -> 0 | V26: =Apr!V26+May!V26+Jun!V26+Jul!V26+Aug!V26+Sep!V26+Oct!V26+Nov!V26+Dec!V26+Jan!V26+Feb!V26+Mar!V26 -> 0 | W26: =Apr!W26+May!W26+Jun!W26+Jul!W26+Aug!W26+Sep!W26+Oct!W26+Nov!W26+Dec!W26+Jan!W26+Feb!W26+Mar!W26 -> 0 | X26: =Apr!X26+May!X26+Jun!X26+Jul!X26+Aug!X26+Sep!X26+Oct!X26+Nov!X26+Dec!X26+Jan!X26+Feb!X26+Mar!X26 -> 0 | Y26: =SUM(U26:X26) -> 0 | Z26: =Apr!Z26+May!Z26+Jun!Z26+Jul!Z26+Aug!Z26+Sep!Z26+Oct!Z26+Nov!Z26+Dec!Z26+Jan!Z26+Feb!Z26+Mar!Z26 -> 0 | AA26: =T26+Y26+Z26 -> 0 | AB26: =IF(H26="Exempt",0,ROUND((T26*H26/100)-SUM(U26:W26),2)) -> 0 | AD26: =Apr!AD26+May!AD26+Jun!AD26+Jul!AD26+Aug!AD26+Sep!AD26+Oct!AD26+Nov!AD26+Dec!AD26+Jan!AD26+Feb!AD26+Mar!AD26 -> 0 | AE26: =Apr!AE26+May!AE26+Jun!AE26+Jul!AE26+Aug!AE26+Sep!AE26+Oct!AE26+Nov!AE26+Dec!AE26+Jan!AE26+Feb!AE26+Mar!AE26 -> 0 | AF26: =Apr!AF26+May!AF26+Jun!AF26+Jul!AF26+Aug!AF26+Sep!AF26+Oct!AF26+Nov!AF26+Dec!AF26+Jan!AF26+Feb!AF26+Mar!AF26 -> 0 | AG26: =Apr!AG26+May!AG26+Jun!AG26+Jul!AG26+Aug!AG26+Sep!AG26+Oct!AG26+Nov!AG26+Dec!AG26+Jan!AG26+Feb!AG26+Mar!AG26 -> 0 | AI26: =SUM(AE26:AH26) -> 0 | AJ26: =Apr!AJ26+May!AJ26+Jun!AJ26+Jul!AJ26+Aug!AJ26+Sep!AJ26+Oct!AJ26+Nov!AJ26+Dec!AJ26+Jan!AJ26+Feb!AJ26+Mar!AJ26 -> 0 | AK26: =AD26+AI26+AJ26 -> 0 | AL26: =IF(H26="Exempt",0,ROUND((AD26*H26/100)-SUM(AE26:AG26),2)) -> 0
A27: =+A26+1 -> 12 | J27: =Apr!J27+May!J27+Jun!J27+Jul!J27+Aug!J27+Sep!J27+Oct!J27+Nov!J27+Dec!J27+Jan!J27+Feb!J27+Mar!J27 -> 0 | K27: =Apr!K27+May!K27+Jun!K27+Jul!K27+Aug!K27+Sep!K27+Oct!K27+Nov!K27+Dec!K27+Jan!K27+Feb!K27+Mar!K27 -> 0 | L27: =Apr!L27+May!L27+Jun!L27+Jul!L27+Aug!L27+Sep!L27+Oct!L27+Nov!L27+Dec!L27+Jan!L27+Feb!L27+Mar!L27 -> 0 | M27: =Apr!M27+May!M27+Jun!M27+Jul!M27+Aug!M27+Sep!M27+Oct!M27+Nov!M27+Dec!M27+Jan!M27+Feb!M27+Mar!M27 -> 0 | N27: =Apr!N27+May!N27+Jun!N27+Jul!N27+Aug!N27+Sep!N27+Oct!N27+Nov!N27+Dec!N27+Jan!N27+Feb!N27+Mar!N27 -> 0 | O27: =SUM(K27:N27) -> 0 | P27: =Apr!P27+May!P27+Jun!P27+Jul!P27+Aug!P27+Sep!P27+Oct!P27+Nov!P27+Dec!P27+Jan!P27+Feb!P27+Mar!P27 -> 0 | Q27: =J27+O27+P27 -> 0 | R27: =IF(H27="Exempt",0,ROUND((J27*H27/100)-SUM(K27:M27),2)) -> 0 | T27: =Apr!T27+May!T27+Jun!T27+Jul!T27+Aug!T27+Sep!T27+Oct!T27+Nov!T27+Dec!T27+Jan!T27+Feb!T27+Mar!T27 -> 0 | U27: =Apr!U27+May!U27+Jun!U27+Jul!U27+Aug!U27+Sep!U27+Oct!U27+Nov!U27+Dec!U27+Jan!U27+Feb!U27+Mar!U27 -> 0 | V27: =Apr!V27+May!V27+Jun!V27+Jul!V27+Aug!V27+Sep!V27+Oct!V27+Nov!V27+Dec!V27+Jan!V27+Feb!V27+Mar!V27 -> 0 | W27: =Apr!W27+May!W27+Jun!W27+Jul!W27+Aug!W27+Sep!W27+Oct!W27+Nov!W27+Dec!W27+Jan!W27+Feb!W27+Mar!W27 -> 0 | X27: =Apr!X27+May!X27+Jun!X27+Jul!X27+Aug!X27+Sep!X27+Oct!X27+Nov!X27+Dec!X27+Jan!X27+Feb!X27+Mar!X27 -> 0 | Y27: =SUM(U27:X27) -> 0 | Z27: =Apr!Z27+May!Z27+Jun!Z27+Jul!Z27+Aug!Z27+Sep!Z27+Oct!Z27+Nov!Z27+Dec!Z27+Jan!Z27+Feb!Z27+Mar!Z27 -> 0 | AA27: =T27+Y27+Z27 -> 0 | AB27: =IF(H27="Exempt",0,ROUND((T27*H27/100)-SUM(U27:W27),2)) -> 0 | AD27: =Apr!AD27+May!AD27+Jun!AD27+Jul!AD27+Aug!AD27+Sep!AD27+Oct!AD27+Nov!AD27+Dec!AD27+Jan!AD27+Feb!AD27+Mar!AD27 -> 0 | AE27: =Apr!AE27+May!AE27+Jun!AE27+Jul!AE27+Aug!AE27+Sep!AE27+Oct!AE27+Nov!AE27+Dec!AE27+Jan!AE27+Feb!AE27+Mar!AE27 -> 0 | AF27: =Apr!AF27+May!AF27+Jun!AF27+Jul!AF27+Aug!AF27+Sep!AF27+Oct!AF27+Nov!AF27+Dec!AF27+Jan!AF27+Feb!AF27+Mar!AF27 -> 0 | AG27: =Apr!AG27+May!AG27+Jun!AG27+Jul!AG27+Aug!AG27+Sep!AG27+Oct!AG27+Nov!AG27+Dec!AG27+Jan!AG27+Feb!AG27+Mar!AG27 -> 0 | AI27: =SUM(AE27:AH27) -> 0 | AJ27: =Apr!AJ27+May!AJ27+Jun!AJ27+Jul!AJ27+Aug!AJ27+Sep!AJ27+Oct!AJ27+Nov!AJ27+Dec!AJ27+Jan!AJ27+Feb!AJ27+Mar!AJ27 -> 0 | AK27: =AD27+AI27+AJ27 -> 0 | AL27: =IF(H27="Exempt",0,ROUND((AD27*H27/100)-SUM(AE27:AG27),2)) -> 0
A28: =+A27+1 -> 13 | J28: =Apr!J28+May!J28+Jun!J28+Jul!J28+Aug!J28+Sep!J28+Oct!J28+Nov!J28+Dec!J28+Jan!J28+Feb!J28+Mar!J28 -> 0 | K28: =Apr!K28+May!K28+Jun!K28+Jul!K28+Aug!K28+Sep!K28+Oct!K28+Nov!K28+Dec!K28+Jan!K28+Feb!K28+Mar!K28 -> 0 | L28: =Apr!L28+May!L28+Jun!L28+Jul!L28+Aug!L28+Sep!L28+Oct!L28+Nov!L28+Dec!L28+Jan!L28+Feb!L28+Mar!L28 -> 0 | M28: =Apr!M28+May!M28+Jun!M28+Jul!M28+Aug!M28+Sep!M28+Oct!M28+Nov!M28+Dec!M28+Jan!M28+Feb!M28+Mar!M28 -> 0 | N28: =Apr!N28+May!N28+Jun!N28+Jul!N28+Aug!N28+Sep!N28+Oct!N28+Nov!N28+Dec!N28+Jan!N28+Feb!N28+Mar!N28 -> 0 | O28: =SUM(K28:N28) -> 0 | P28: =Apr!P28+May!P28+Jun!P28+Jul!P28+Aug!P28+Sep!P28+Oct!P28+Nov!P28+Dec!P28+Jan!P28+Feb!P28+Mar!P28 -> 0 | Q28: =J28+O28+P28 -> 0 | R28: =IF(H28="Exempt",0,ROUND((J28*H28/100)-SUM(K28:M28),2)) -> 0 | T28: =Apr!T28+May!T28+Jun!T28+Jul!T28+Aug!T28+Sep!T28+Oct!T28+Nov!T28+Dec!T28+Jan!T28+Feb!T28+Mar!T28 -> 0 | U28: =Apr!U28+May!U28+Jun!U28+Jul!U28+Aug!U28+Sep!U28+Oct!U28+Nov!U28+Dec!U28+Jan!U28+Feb!U28+Mar!U28 -> 0 | V28: =Apr!V28+May!V28+Jun!V28+Jul!V28+Aug!V28+Sep!V28+Oct!V28+Nov!V28+Dec!V28+Jan!V28+Feb!V28+Mar!V28 -> 0 | W28: =Apr!W28+May!W28+Jun!W28+Jul!W28+Aug!W28+Sep!W28+Oct!W28+Nov!W28+Dec!W28+Jan!W28+Feb!W28+Mar!W28 -> 0 | X28: =Apr!X28+May!X28+Jun!X28+Jul!X28+Aug!X28+Sep!X28+Oct!X28+Nov!X28+Dec!X28+Jan!X28+Feb!X28+Mar!X28 -> 0 | Y28: =SUM(U28:X28) -> 0 | Z28: =Apr!Z28+May!Z28+Jun!Z28+Jul!Z28+Aug!Z28+Sep!Z28+Oct!Z28+Nov!Z28+Dec!Z28+Jan!Z28+Feb!Z28+Mar!Z28 -> 0 | AA28: =T28+Y28+Z28 -> 0 | AB28: =IF(H28="Exempt",0,ROUND((T28*H28/100)-SUM(U28:W28),2)) -> 0 | AD28: =Apr!AD28+May!AD28+Jun!AD28+Jul!AD28+Aug!AD28+Sep!AD28+Oct!AD28+Nov!AD28+Dec!AD28+Jan!AD28+Feb!AD28+Mar!AD28 -> 0 | AE28: =Apr!AE28+May!AE28+Jun!AE28+Jul!AE28+Aug!AE28+Sep!AE28+Oct!AE28+Nov!AE28+Dec!AE28+Jan!AE28+Feb!AE28+Mar!AE28 -> 0 | AF28: =Apr!AF28+May!AF28+Jun!AF28+Jul!AF28+Aug!AF28+Sep!AF28+Oct!AF28+Nov!AF28+Dec!AF28+Jan!AF28+Feb!AF28+Mar!AF28 -> 0 | AG28: =Apr!AG28+May!AG28+Jun!AG28+Jul!AG28+Aug!AG28+Sep!AG28+Oct!AG28+Nov!AG28+Dec!AG28+Jan!AG28+Feb!AG28+Mar!AG28 -> 0 | AI28: =SUM(AE28:AH28) -> 0 | AJ28: =Apr!AJ28+May!AJ28+Jun!AJ28+Jul!AJ28+Aug!AJ28+Sep!AJ28+Oct!AJ28+Nov!AJ28+Dec!AJ28+Jan!AJ28+Feb!AJ28+Mar!AJ28 -> 0 | AK28: =AD28+AI28+AJ28 -> 0 | AL28: =IF(H28="Exempt",0,ROUND((AD28*H28/100)-SUM(AE28:AG28),2)) -> 0
A29: =+A28+1 -> 14 | J29: =Apr!J29+May!J29+Jun!J29+Jul!J29+Aug!J29+Sep!J29+Oct!J29+Nov!J29+Dec!J29+Jan!J29+Feb!J29+Mar!J29 -> 0 | K29: =Apr!K29+May!K29+Jun!K29+Jul!K29+Aug!K29+Sep!K29+Oct!K29+Nov!K29+Dec!K29+Jan!K29+Feb!K29+Mar!K29 -> 0 | L29: =Apr!L29+May!L29+Jun!L29+Jul!L29+Aug!L29+Sep!L29+Oct!L29+Nov!L29+Dec!L29+Jan!L29+Feb!L29+Mar!L29 -> 0 | M29: =Apr!M29+May!M29+Jun!M29+Jul!M29+Aug!M29+Sep!M29+Oct!M29+Nov!M29+Dec!M29+Jan!M29+Feb!M29+Mar!M29 -> 0 | N29: =Apr!N29+May!N29+Jun!N29+Jul!N29+Aug!N29+Sep!N29+Oct!N29+Nov!N29+Dec!N29+Jan!N29+Feb!N29+Mar!N29 -> 0 | O29: =SUM(K29:N29) -> 0 | P29: =Apr!P29+May!P29+Jun!P29+Jul!P29+Aug!P29+Sep!P29+Oct!P29+Nov!P29+Dec!P29+Jan!P29+Feb!P29+Mar!P29 -> 0 | Q29: =J29+O29+P29 -> 0 | R29: =IF(H29="Exempt",0,ROUND((J29*H29/100)-SUM(K29:M29),2)) -> 0 | T29: =Apr!T29+May!T29+Jun!T29+Jul!T29+Aug!T29+Sep!T29+Oct!T29+Nov!T29+Dec!T29+Jan!T29+Feb!T29+Mar!T29 -> 0 | U29: =Apr!U29+May!U29+Jun!U29+Jul!U29+Aug!U29+Sep!U29+Oct!U29+Nov!U29+Dec!U29+Jan!U29+Feb!U29+Mar!U29 -> 0 | V29: =Apr!V29+May!V29+Jun!V29+Jul!V29+Aug!V29+Sep!V29+Oct!V29+Nov!V29+Dec!V29+Jan!V29+Feb!V29+Mar!V29 -> 0 | W29: =Apr!W29+May!W29+Jun!W29+Jul!W29+Aug!W29+Sep!W29+Oct!W29+Nov!W29+Dec!W29+Jan!W29+Feb!W29+Mar!W29 -> 0 | X29: =Apr!X29+May!X29+Jun!X29+Jul!X29+Aug!X29+Sep!X29+Oct!X29+Nov!X29+Dec!X29+Jan!X29+Feb!X29+Mar!X29 -> 0 | Y29: =SUM(U29:X29) -> 0 | Z29: =Apr!Z29+May!Z29+Jun!Z29+Jul!Z29+Aug!Z29+Sep!Z29+Oct!Z29+Nov!Z29+Dec!Z29+Jan!Z29+Feb!Z29+Mar!Z29 -> 0 | AA29: =T29+Y29+Z29 -> 0 | AB29: =IF(H29="Exempt",0,ROUND((T29*H29/100)-SUM(U29:W29),2)) -> 0 | AD29: =Apr!AD29+May!AD29+Jun!AD29+Jul!AD29+Aug!AD29+Sep!AD29+Oct!AD29+Nov!AD29+Dec!AD29+Jan!AD29+Feb!AD29+Mar!AD29 -> 0 | AE29: =Apr!AE29+May!AE29+Jun!AE29+Jul!AE29+Aug!AE29+Sep!AE29+Oct!AE29+Nov!AE29+Dec!AE29+Jan!AE29+Feb!AE29+Mar!AE29 -> 0 | AF29: =Apr!AF29+May!AF29+Jun!AF29+Jul!AF29+Aug!AF29+Sep!AF29+Oct!AF29+Nov!AF29+Dec!AF29+Jan!AF29+Feb!AF29+Mar!AF29 -> 0 | AG29: =Apr!AG29+May!AG29+Jun!AG29+Jul!AG29+Aug!AG29+Sep!AG29+Oct!AG29+Nov!AG29+Dec!AG29+Jan!AG29+Feb!AG29+Mar!AG29 -> 0 | AI29: =SUM(AE29:AH29) -> 0 | AJ29: =Apr!AJ29+May!AJ29+Jun!AJ29+Jul!AJ29+Aug!AJ29+Sep!AJ29+Oct!AJ29+Nov!AJ29+Dec!AJ29+Jan!AJ29+Feb!AJ29+Mar!AJ29 -> 0 | AK29: =AD29+AI29+AJ29 -> 0 | AL29: =IF(H29="Exempt",0,ROUND((AD29*H29/100)-SUM(AE29:AG29),2)) -> 0
A30: =+A29+1 -> 15 | J30: =Apr!J30+May!J30+Jun!J30+Jul!J30+Aug!J30+Sep!J30+Oct!J30+Nov!J30+Dec!J30+Jan!J30+Feb!J30+Mar!J30 -> 0 | K30: =Apr!K30+May!K30+Jun!K30+Jul!K30+Aug!K30+Sep!K30+Oct!K30+Nov!K30+Dec!K30+Jan!K30+Feb!K30+Mar!K30 -> 0 | L30: =Apr!L30+May!L30+Jun!L30+Jul!L30+Aug!L30+Sep!L30+Oct!L30+Nov!L30+Dec!L30+Jan!L30+Feb!L30+Mar!L30 -> 0 | M30: =Apr!M30+May!M30+Jun!M30+Jul!M30+Aug!M30+Sep!M30+Oct!M30+Nov!M30+Dec!M30+Jan!M30+Feb!M30+Mar!M30 -> 0 | N30: =Apr!N30+May!N30+Jun!N30+Jul!N30+Aug!N30+Sep!N30+Oct!N30+Nov!N30+Dec!N30+Jan!N30+Feb!N30+Mar!N30 -> 0 | O30: =SUM(K30:N30) -> 0 | P30: =Apr!P30+May!P30+Jun!P30+Jul!P30+Aug!P30+Sep!P30+Oct!P30+Nov!P30+Dec!P30+Jan!P30+Feb!P30+Mar!P30 -> 0 | Q30: =J30+O30+P30 -> 0 | R30: =IF(H30="Exempt",0,ROUND((J30*H30/100)-SUM(K30:M30),2)) -> 0 | T30: =Apr!T30+May!T30+Jun!T30+Jul!T30+Aug!T30+Sep!T30+Oct!T30+Nov!T30+Dec!T30+Jan!T30+Feb!T30+Mar!T30 -> 0 | U30: =Apr!U30+May!U30+Jun!U30+Jul!U30+Aug!U30+Sep!U30+Oct!U30+Nov!U30+Dec!U30+Jan!U30+Feb!U30+Mar!U30 -> 0 | V30: =Apr!V30+May!V30+Jun!V30+Jul!V30+Aug!V30+Sep!V30+Oct!V30+Nov!V30+Dec!V30+Jan!V30+Feb!V30+Mar!V30 -> 0 | W30: =Apr!W30+May!W30+Jun!W30+Jul!W30+Aug!W30+Sep!W30+Oct!W30+Nov!W30+Dec!W30+Jan!W30+Feb!W30+Mar!W30 -> 0 | X30: =Apr!X30+May!X30+Jun!X30+Jul!X30+Aug!X30+Sep!X30+Oct!X30+Nov!X30+Dec!X30+Jan!X30+Feb!X30+Mar!X30 -> 0 | Y30: =SUM(U30:X30) -> 0 | Z30: =Apr!Z30+May!Z30+Jun!Z30+Jul!Z30+Aug!Z30+Sep!Z30+Oct!Z30+Nov!Z30+Dec!Z30+Jan!Z30+Feb!Z30+Mar!Z30 -> 0 | AA30: =T30+Y30+Z30 -> 0 | AB30: =IF(H30="Exempt",0,ROUND((T30*H30/100)-SUM(U30:W30),2)) -> 0 | AD30: =Apr!AD30+May!AD30+Jun!AD30+Jul!AD30+Aug!AD30+Sep!AD30+Oct!AD30+Nov!AD30+Dec!AD30+Jan!AD30+Feb!AD30+Mar!AD30 -> 0 | AE30: =Apr!AE30+May!AE30+Jun!AE30+Jul!AE30+Aug!AE30+Sep!AE30+Oct!AE30+Nov!AE30+Dec!AE30+Jan!AE30+Feb!AE30+Mar!AE30 -> 0 | AF30: =Apr!AF30+May!AF30+Jun!AF30+Jul!AF30+Aug!AF30+Sep!AF30+Oct!AF30+Nov!AF30+Dec!AF30+Jan!AF30+Feb!AF30+Mar!AF30 -> 0 | AG30: =Apr!AG30+May!AG30+Jun!AG30+Jul!AG30+Aug!AG30+Sep!AG30+Oct!AG30+Nov!AG30+Dec!AG30+Jan!AG30+Feb!AG30+Mar!AG30 -> 0 | AI30: =SUM(AE30:AH30) -> 0 | AJ30: =Apr!AJ30+May!AJ30+Jun!AJ30+Jul!AJ30+Aug!AJ30+Sep!AJ30+Oct!AJ30+Nov!AJ30+Dec!AJ30+Jan!AJ30+Feb!AJ30+Mar!AJ30 -> 0 | AK30: =AD30+AI30+AJ30 -> 0 | AL30: =IF(H30="Exempt",0,ROUND((AD30*H30/100)-SUM(AE30:AG30),2)) -> 0
A31: =+A30+1 -> 16 | J31: =Apr!J31+May!J31+Jun!J31+Jul!J31+Aug!J31+Sep!J31+Oct!J31+Nov!J31+Dec!J31+Jan!J31+Feb!J31+Mar!J31 -> 0 | K31: =Apr!K31+May!K31+Jun!K31+Jul!K31+Aug!K31+Sep!K31+Oct!K31+Nov!K31+Dec!K31+Jan!K31+Feb!K31+Mar!K31 -> 0 | L31: =Apr!L31+May!L31+Jun!L31+Jul!L31+Aug!L31+Sep!L31+Oct!L31+Nov!L31+Dec!L31+Jan!L31+Feb!L31+Mar!L31 -> 0 | M31: =Apr!M31+May!M31+Jun!M31+Jul!M31+Aug!M31+Sep!M31+Oct!M31+Nov!M31+Dec!M31+Jan!M31+Feb!M31+Mar!M31 -> 0 | N31: =Apr!N31+May!N31+Jun!N31+Jul!N31+Aug!N31+Sep!N31+Oct!N31+Nov!N31+Dec!N31+Jan!N31+Feb!N31+Mar!N31 -> 0 | O31: =SUM(K31:N31) -> 0 | P31: =Apr!P31+May!P31+Jun!P31+Jul!P31+Aug!P31+Sep!P31+Oct!P31+Nov!P31+Dec!P31+Jan!P31+Feb!P31+Mar!P31 -> 0 | Q31: =J31+O31+P31 -> 0 | R31: =IF(H31="Exempt",0,ROUND((J31*H31/100)-SUM(K31:M31),2)) -> 0 | T31: =Apr!T31+May!T31+Jun!T31+Jul!T31+Aug!T31+Sep!T31+Oct!T31+Nov!T31+Dec!T31+Jan!T31+Feb!T31+Mar!T31 -> 0 | U31: =Apr!U31+May!U31+Jun!U31+Jul!U31+Aug!U31+Sep!U31+Oct!U31+Nov!U31+Dec!U31+Jan!U31+Feb!U31+Mar!U31 -> 0 | V31: =Apr!V31+May!V31+Jun!V31+Jul!V31+Aug!V31+Sep!V31+Oct!V31+Nov!V31+Dec!V31+Jan!V31+Feb!V31+Mar!V31 -> 0 | W31: =Apr!W31+May!W31+Jun!W31+Jul!W31+Aug!W31+Sep!W31+Oct!W31+Nov!W31+Dec!W31+Jan!W31+Feb!W31+Mar!W31 -> 0 | X31: =Apr!X31+May!X31+Jun!X31+Jul!X31+Aug!X31+Sep!X31+Oct!X31+Nov!X31+Dec!X31+Jan!X31+Feb!X31+Mar!X31 -> 0 | Y31: =SUM(U31:X31) -> 0 | Z31: =Apr!Z31+May!Z31+Jun!Z31+Jul!Z31+Aug!Z31+Sep!Z31+Oct!Z31+Nov!Z31+Dec!Z31+Jan!Z31+Feb!Z31+Mar!Z31 -> 0 | AA31: =T31+Y31+Z31 -> 0 | AB31: =IF(H31="Exempt",0,ROUND((T31*H31/100)-SUM(U31:W31),2)) -> 0 | AD31: =Apr!AD31+May!AD31+Jun!AD31+Jul!AD31+Aug!AD31+Sep!AD31+Oct!AD31+Nov!AD31+Dec!AD31+Jan!AD31+Feb!AD31+Mar!AD31 -> 0 | AE31: =Apr!AE31+May!AE31+Jun!AE31+Jul!AE31+Aug!AE31+Sep!AE31+Oct!AE31+Nov!AE31+Dec!AE31+Jan!AE31+Feb!AE31+Mar!AE31 -> 0 | AF31: =Apr!AF31+May!AF31+Jun!AF31+Jul!AF31+Aug!AF31+Sep!AF31+Oct!AF31+Nov!AF31+Dec!AF31+Jan!AF31+Feb!AF31+Mar!AF31 -> 0 | AG31: =Apr!AG31+May!AG31+Jun!AG31+Jul!AG31+Aug!AG31+Sep!AG31+Oct!AG31+Nov!AG31+Dec!AG31+Jan!AG31+Feb!AG31+Mar!AG31 -> 0 | AI31: =SUM(AE31:AH31) -> 0 | AJ31: =Apr!AJ31+May!AJ31+Jun!AJ31+Jul!AJ31+Aug!AJ31+Sep!AJ31+Oct!AJ31+Nov!AJ31+Dec!AJ31+Jan!AJ31+Feb!AJ31+Mar!AJ31 -> 0 | AK31: =AD31+AI31+AJ31 -> 0 | AL31: =IF(H31="Exempt",0,ROUND((AD31*H31/100)-SUM(AE31:AG31),2)) -> 0
A32: =+A31+1 -> 17 | J32: =Apr!J32+May!J32+Jun!J32+Jul!J32+Aug!J32+Sep!J32+Oct!J32+Nov!J32+Dec!J32+Jan!J32+Feb!J32+Mar!J32 -> 0 | K32: =Apr!K32+May!K32+Jun!K32+Jul!K32+Aug!K32+Sep!K32+Oct!K32+Nov!K32+Dec!K32+Jan!K32+Feb!K32+Mar!K32 -> 0 | L32: =Apr!L32+May!L32+Jun!L32+Jul!L32+Aug!L32+Sep!L32+Oct!L32+Nov!L32+Dec!L32+Jan!L32+Feb!L32+Mar!L32 -> 0 | M32: =Apr!M32+May!M32+Jun!M32+Jul!M32+Aug!M32+Sep!M32+Oct!M32+Nov!M32+Dec!M32+Jan!M32+Feb!M32+Mar!M32 -> 0 | N32: =Apr!N32+May!N32+Jun!N32+Jul!N32+Aug!N32+Sep!N32+Oct!N32+Nov!N32+Dec!N32+Jan!N32+Feb!N32+Mar!N32 -> 0 | O32: =SUM(K32:N32) -> 0 | P32: =Apr!P32+May!P32+Jun!P32+Jul!P32+Aug!P32+Sep!P32+Oct!P32+Nov!P32+Dec!P32+Jan!P32+Feb!P32+Mar!P32 -> 0 | Q32: =J32+O32+P32 -> 0 | R32: =IF(H32="Exempt",0,ROUND((J32*H32/100)-SUM(K32:M32),2)) -> 0 | T32: =Apr!T32+May!T32+Jun!T32+Jul!T32+Aug!T32+Sep!T32+Oct!T32+Nov!T32+Dec!T32+Jan!T32+Feb!T32+Mar!T32 -> 0 | U32: =Apr!U32+May!U32+Jun!U32+Jul!U32+Aug!U32+Sep!U32+Oct!U32+Nov!U32+Dec!U32+Jan!U32+Feb!U32+Mar!U32 -> 0 | V32: =Apr!V32+May!V32+Jun!V32+Jul!V32+Aug!V32+Sep!V32+Oct!V32+Nov!V32+Dec!V32+Jan!V32+Feb!V32+Mar!V32 -> 0 | W32: =Apr!W32+May!W32+Jun!W32+Jul!W32+Aug!W32+Sep!W32+Oct!W32+Nov!W32+Dec!W32+Jan!W32+Feb!W32+Mar!W32 -> 0 | X32: =Apr!X32+May!X32+Jun!X32+Jul!X32+Aug!X32+Sep!X32+Oct!X32+Nov!X32+Dec!X32+Jan!X32+Feb!X32+Mar!X32 -> 0 | Y32: =SUM(U32:X32) -> 0 | Z32: =Apr!Z32+May!Z32+Jun!Z32+Jul!Z32+Aug!Z32+Sep!Z32+Oct!Z32+Nov!Z32+Dec!Z32+Jan!Z32+Feb!Z32+Mar!Z32 -> 0 | AA32: =T32+Y32+Z32 -> 0 | AB32: =IF(H32="Exempt",0,ROUND((T32*H32/100)-SUM(U32:W32),2)) -> 0 | AD32: =Apr!AD32+May!AD32+Jun!AD32+Jul!AD32+Aug!AD32+Sep!AD32+Oct!AD32+Nov!AD32+Dec!AD32+Jan!AD32+Feb!AD32+Mar!AD32 -> 0 | AE32: =Apr!AE32+May!AE32+Jun!AE32+Jul!AE32+Aug!AE32+Sep!AE32+Oct!AE32+Nov!AE32+Dec!AE32+Jan!AE32+Feb!AE32+Mar!AE32 -> 0 | AF32: =Apr!AF32+May!AF32+Jun!AF32+Jul!AF32+Aug!AF32+Sep!AF32+Oct!AF32+Nov!AF32+Dec!AF32+Jan!AF32+Feb!AF32+Mar!AF32 -> 0 | AG32: =Apr!AG32+May!AG32+Jun!AG32+Jul!AG32+Aug!AG32+Sep!AG32+Oct!AG32+Nov!AG32+Dec!AG32+Jan!AG32+Feb!AG32+Mar!AG32 -> 0 | AI32: =SUM(AE32:AH32) -> 0 | AJ32: =Apr!AJ32+May!AJ32+Jun!AJ32+Jul!AJ32+Aug!AJ32+Sep!AJ32+Oct!AJ32+Nov!AJ32+Dec!AJ32+Jan!AJ32+Feb!AJ32+Mar!AJ32 -> 0 | AK32: =AD32+AI32+AJ32 -> 0 | AL32: =IF(H32="Exempt",0,ROUND((AD32*H32/100)-SUM(AE32:AG32),2)) -> 0
A33: =+A32+1 -> 18 | J33: =Apr!J33+May!J33+Jun!J33+Jul!J33+Aug!J33+Sep!J33+Oct!J33+Nov!J33+Dec!J33+Jan!J33+Feb!J33+Mar!J33 -> 0 | K33: =Apr!K33+May!K33+Jun!K33+Jul!K33+Aug!K33+Sep!K33+Oct!K33+Nov!K33+Dec!K33+Jan!K33+Feb!K33+Mar!K33 -> 0 | L33: =Apr!L33+May!L33+Jun!L33+Jul!L33+Aug!L33+Sep!L33+Oct!L33+Nov!L33+Dec!L33+Jan!L33+Feb!L33+Mar!L33 -> 0 | M33: =Apr!M33+May!M33+Jun!M33+Jul!M33+Aug!M33+Sep!M33+Oct!M33+Nov!M33+Dec!M33+Jan!M33+Feb!M33+Mar!M33 -> 0 | N33: =Apr!N33+May!N33+Jun!N33+Jul!N33+Aug!N33+Sep!N33+Oct!N33+Nov!N33+Dec!N33+Jan!N33+Feb!N33+Mar!N33 -> 0 | O33: =SUM(K33:N33) -> 0 | P33: =Apr!P33+May!P33+Jun!P33+Jul!P33+Aug!P33+Sep!P33+Oct!P33+Nov!P33+Dec!P33+Jan!P33+Feb!P33+Mar!P33 -> 0 | Q33: =J33+O33+P33 -> 0 | R33: =IF(H33="Exempt",0,ROUND((J33*H33/100)-SUM(K33:M33),2)) -> 0 | T33: =Apr!T33+May!T33+Jun!T33+Jul!T33+Aug!T33+Sep!T33+Oct!T33+Nov!T33+Dec!T33+Jan!T33+Feb!T33+Mar!T33 -> 0 | U33: =Apr!U33+May!U33+Jun!U33+Jul!U33+Aug!U33+Sep!U33+Oct!U33+Nov!U33+Dec!U33+Jan!U33+Feb!U33+Mar!U33 -> 0 | V33: =Apr!V33+May!V33+Jun!V33+Jul!V33+Aug!V33+Sep!V33+Oct!V33+Nov!V33+Dec!V33+Jan!V33+Feb!V33+Mar!V33 -> 0 | W33: =Apr!W33+May!W33+Jun!W33+Jul!W33+Aug!W33+Sep!W33+Oct!W33+Nov!W33+Dec!W33+Jan!W33+Feb!W33+Mar!W33 -> 0 | X33: =Apr!X33+May!X33+Jun!X33+Jul!X33+Aug!X33+Sep!X33+Oct!X33+Nov!X33+Dec!X33+Jan!X33+Feb!X33+Mar!X33 -> 0 | Y33: =SUM(U33:X33) -> 0 | Z33: =Apr!Z33+May!Z33+Jun!Z33+Jul!Z33+Aug!Z33+Sep!Z33+Oct!Z33+Nov!Z33+Dec!Z33+Jan!Z33+Feb!Z33+Mar!Z33 -> 0 | AA33: =T33+Y33+Z33 -> 0 | AB33: =IF(H33="Exempt",0,ROUND((T33*H33/100)-SUM(U33:W33),2)) -> 0 | AD33: =Apr!AD33+May!AD33+Jun!AD33+Jul!AD33+Aug!AD33+Sep!AD33+Oct!AD33+Nov!AD33+Dec!AD33+Jan!AD33+Feb!AD33+Mar!AD33 -> 0 | AE33: =Apr!AE33+May!AE33+Jun!AE33+Jul!AE33+Aug!AE33+Sep!AE33+Oct!AE33+Nov!AE33+Dec!AE33+Jan!AE33+Feb!AE33+Mar!AE33 -> 0 | AF33: =Apr!AF33+May!AF33+Jun!AF33+Jul!AF33+Aug!AF33+Sep!AF33+Oct!AF33+Nov!AF33+Dec!AF33+Jan!AF33+Feb!AF33+Mar!AF33 -> 0 | AG33: =Apr!AG33+May!AG33+Jun!AG33+Jul!AG33+Aug!AG33+Sep!AG33+Oct!AG33+Nov!AG33+Dec!AG33+Jan!AG33+Feb!AG33+Mar!AG33 -> 0 | AI33: =SUM(AE33:AH33) -> 0 | AJ33: =Apr!AJ33+May!AJ33+Jun!AJ33+Jul!AJ33+Aug!AJ33+Sep!AJ33+Oct!AJ33+Nov!AJ33+Dec!AJ33+Jan!AJ33+Feb!AJ33+Mar!AJ33 -> 0 | AK33: =AD33+AI33+AJ33 -> 0 | AL33: =IF(H33="Exempt",0,ROUND((AD33*H33/100)-SUM(AE33:AG33),2)) -> 0
A34: =+A33+1 -> 19 | J34: =Apr!J34+May!J34+Jun!J34+Jul!J34+Aug!J34+Sep!J34+Oct!J34+Nov!J34+Dec!J34+Jan!J34+Feb!J34+Mar!J34 -> 0 | K34: =Apr!K34+May!K34+Jun!K34+Jul!K34+Aug!K34+Sep!K34+Oct!K34+Nov!K34+Dec!K34+Jan!K34+Feb!K34+Mar!K34 -> 0 | L34: =Apr!L34+May!L34+Jun!L34+Jul!L34+Aug!L34+Sep!L34+Oct!L34+Nov!L34+Dec!L34+Jan!L34+Feb!L34+Mar!L34 -> 0 | M34: =Apr!M34+May!M34+Jun!M34+Jul!M34+Aug!M34+Sep!M34+Oct!M34+Nov!M34+Dec!M34+Jan!M34+Feb!M34+Mar!M34 -> 0 | N34: =Apr!N34+May!N34+Jun!N34+Jul!N34+Aug!N34+Sep!N34+Oct!N34+Nov!N34+Dec!N34+Jan!N34+Feb!N34+Mar!N34 -> 0 | O34: =SUM(K34:N34) -> 0 | P34: =Apr!P34+May!P34+Jun!P34+Jul!P34+Aug!P34+Sep!P34+Oct!P34+Nov!P34+Dec!P34+Jan!P34+Feb!P34+Mar!P34 -> 0 | Q34: =J34+O34+P34 -> 0 | R34: =IF(H34="Exempt",0,ROUND((J34*H34/100)-SUM(K34:M34),2)) -> 0 | T34: =Apr!T34+May!T34+Jun!T34+Jul!T34+Aug!T34+Sep!T34+Oct!T34+Nov!T34+Dec!T34+Jan!T34+Feb!T34+Mar!T34 -> 0 | U34: =Apr!U34+May!U34+Jun!U34+Jul!U34+Aug!U34+Sep!U34+Oct!U34+Nov!U34+Dec!U34+Jan!U34+Feb!U34+Mar!U34 -> 0 | V34: =Apr!V34+May!V34+Jun!V34+Jul!V34+Aug!V34+Sep!V34+Oct!V34+Nov!V34+Dec!V34+Jan!V34+Feb!V34+Mar!V34 -> 0 | W34: =Apr!W34+May!W34+Jun!W34+Jul!W34+Aug!W34+Sep!W34+Oct!W34+Nov!W34+Dec!W34+Jan!W34+Feb!W34+Mar!W34 -> 0 | X34: =Apr!X34+May!X34+Jun!X34+Jul!X34+Aug!X34+Sep!X34+Oct!X34+Nov!X34+Dec!X34+Jan!X34+Feb!X34+Mar!X34 -> 0 | Y34: =SUM(U34:X34) -> 0 | Z34: =Apr!Z34+May!Z34+Jun!Z34+Jul!Z34+Aug!Z34+Sep!Z34+Oct!Z34+Nov!Z34+Dec!Z34+Jan!Z34+Feb!Z34+Mar!Z34 -> 0 | AA34: =T34+Y34+Z34 -> 0 | AB34: =IF(H34="Exempt",0,ROUND((T34*H34/100)-SUM(U34:W34),2)) -> 0 | AD34: =Apr!AD34+May!AD34+Jun!AD34+Jul!AD34+Aug!AD34+Sep!AD34+Oct!AD34+Nov!AD34+Dec!AD34+Jan!AD34+Feb!AD34+Mar!AD34 -> 0 | AE34: =Apr!AE34+May!AE34+Jun!AE34+Jul!AE34+Aug!AE34+Sep!AE34+Oct!AE34+Nov!AE34+Dec!AE34+Jan!AE34+Feb!AE34+Mar!AE34 -> 0 | AF34: =Apr!AF34+May!AF34+Jun!AF34+Jul!AF34+Aug!AF34+Sep!AF34+Oct!AF34+Nov!AF34+Dec!AF34+Jan!AF34+Feb!AF34+Mar!AF34 -> 0 | AG34: =Apr!AG34+May!AG34+Jun!AG34+Jul!AG34+Aug!AG34+Sep!AG34+Oct!AG34+Nov!AG34+Dec!AG34+Jan!AG34+Feb!AG34+Mar!AG34 -> 0 | AI34: =SUM(AE34:AH34) -> 0 | AJ34: =Apr!AJ34+May!AJ34+Jun!AJ34+Jul!AJ34+Aug!AJ34+Sep!AJ34+Oct!AJ34+Nov!AJ34+Dec!AJ34+Jan!AJ34+Feb!AJ34+Mar!AJ34 -> 0 | AK34: =AD34+AI34+AJ34 -> 0 | AL34: =IF(H34="Exempt",0,ROUND((AD34*H34/100)-SUM(AE34:AG34),2)) -> 0
A35: =+A34+1 -> 20 | B35: Sales | C35: TRANSPORTER SALES | D35: Services | E35: Registered | F35: RCM Invoice | H35: 5 | J35: =Apr!J35+May!J35+Jun!J35+Jul!J35+Aug!J35+Sep!J35+Oct!J35+Nov!J35+Dec!J35+Jan!J35+Feb!J35+Mar!J35 -> 0 | K35: =Apr!K35+May!K35+Jun!K35+Jul!K35+Aug!K35+Sep!K35+Oct!K35+Nov!K35+Dec!K35+Jan!K35+Feb!K35+Mar!K35 -> 0 | L35: =Apr!L35+May!L35+Jun!L35+Jul!L35+Aug!L35+Sep!L35+Oct!L35+Nov!L35+Dec!L35+Jan!L35+Feb!L35+Mar!L35 -> 0 | M35: =Apr!M35+May!M35+Jun!M35+Jul!M35+Aug!M35+Sep!M35+Oct!M35+Nov!M35+Dec!M35+Jan!M35+Feb!M35+Mar!M35 -> 0 | N35: =Apr!N35+May!N35+Jun!N35+Jul!N35+Aug!N35+Sep!N35+Oct!N35+Nov!N35+Dec!N35+Jan!N35+Feb!N35+Mar!N35 -> 0 | O35: =SUM(K35:N35) -> 0 | P35: =Apr!P35+May!P35+Jun!P35+Jul!P35+Aug!P35+Sep!P35+Oct!P35+Nov!P35+Dec!P35+Jan!P35+Feb!P35+Mar!P35 -> 0 | Q35: =J35+O35+P35 -> 0 | R35: =IF(H35="Exempt",0,ROUND((J35*H35/100)-SUM(K35:M35),2)) -> 0 | T35: =Apr!T35+May!T35+Jun!T35+Jul!T35+Aug!T35+Sep!T35+Oct!T35+Nov!T35+Dec!T35+Jan!T35+Feb!T35+Mar!T35 -> 0 | U35: =Apr!U35+May!U35+Jun!U35+Jul!U35+Aug!U35+Sep!U35+Oct!U35+Nov!U35+Dec!U35+Jan!U35+Feb!U35+Mar!U35 -> 0 | V35: =Apr!V35+May!V35+Jun!V35+Jul!V35+Aug!V35+Sep!V35+Oct!V35+Nov!V35+Dec!V35+Jan!V35+Feb!V35+Mar!V35 -> 0 | W35: =Apr!W35+May!W35+Jun!W35+Jul!W35+Aug!W35+Sep!W35+Oct!W35+Nov!W35+Dec!W35+Jan!W35+Feb!W35+Mar!W35 -> 0 | X35: =Apr!X35+May!X35+Jun!X35+Jul!X35+Aug!X35+Sep!X35+Oct!X35+Nov!X35+Dec!X35+Jan!X35+Feb!X35+Mar!X35 -> 0 | Y35: =SUM(U35:X35) -> 0 | Z35: =Apr!Z35+May!Z35+Jun!Z35+Jul!Z35+Aug!Z35+Sep!Z35+Oct!Z35+Nov!Z35+Dec!Z35+Jan!Z35+Feb!Z35+Mar!Z35 -> 0 | AA35: =T35+Y35+Z35 -> 0 | AB35: =IF(H35="Exempt",0,ROUND((T35*H35/100)-SUM(U35:W35),2)) -> 0 | AD35: =Apr!AD35+May!AD35+Jun!AD35+Jul!AD35+Aug!AD35+Sep!AD35+Oct!AD35+Nov!AD35+Dec!AD35+Jan!AD35+Feb!AD35+Mar!AD35 -> 0 | AE35: =Apr!AE35+May!AE35+Jun!AE35+Jul!AE35+Aug!AE35+Sep!AE35+Oct!AE35+Nov!AE35+Dec!AE35+Jan!AE35+Feb!AE35+Mar!AE35 -> 0 | AF35: =Apr!AF35+May!AF35+Jun!AF35+Jul!AF35+Aug!AF35+Sep!AF35+Oct!AF35+Nov!AF35+Dec!AF35+Jan!AF35+Feb!AF35+Mar!AF35 -> 0 | AG35: =Apr!AG35+May!AG35+Jun!AG35+Jul!AG35+Aug!AG35+Sep!AG35+Oct!AG35+Nov!AG35+Dec!AG35+Jan!AG35+Feb!AG35+Mar!AG35 -> 0 | AI35: =SUM(AE35:AH35) -> 0 | AJ35: =Apr!AJ35+May!AJ35+Jun!AJ35+Jul!AJ35+Aug!AJ35+Sep!AJ35+Oct!AJ35+Nov!AJ35+Dec!AJ35+Jan!AJ35+Feb!AJ35+Mar!AJ35 -> 0 | AK35: =AD35+AI35+AJ35 -> 0 | AL35: =IF(H35="Exempt",0,ROUND((AD35*H35/100)-SUM(AE35:AG35),2)) -> 0
A36: =+A35+1 -> 21 | B36: Sales | C36: TRANSPORTER SALES | D36: Services | E36: Un-registered | F36: RCM Invoice | H36: 5 | J36: =Apr!J36+May!J36+Jun!J36+Jul!J36+Aug!J36+Sep!J36+Oct!J36+Nov!J36+Dec!J36+Jan!J36+Feb!J36+Mar!J36 -> 0 | K36: =Apr!K36+May!K36+Jun!K36+Jul!K36+Aug!K36+Sep!K36+Oct!K36+Nov!K36+Dec!K36+Jan!K36+Feb!K36+Mar!K36 -> 0 | L36: =Apr!L36+May!L36+Jun!L36+Jul!L36+Aug!L36+Sep!L36+Oct!L36+Nov!L36+Dec!L36+Jan!L36+Feb!L36+Mar!L36 -> 0 | M36: =Apr!M36+May!M36+Jun!M36+Jul!M36+Aug!M36+Sep!M36+Oct!M36+Nov!M36+Dec!M36+Jan!M36+Feb!M36+Mar!M36 -> 0 | N36: =Apr!N36+May!N36+Jun!N36+Jul!N36+Aug!N36+Sep!N36+Oct!N36+Nov!N36+Dec!N36+Jan!N36+Feb!N36+Mar!N36 -> 0 | O36: =SUM(K36:N36) -> 0 | P36: =Apr!P36+May!P36+Jun!P36+Jul!P36+Aug!P36+Sep!P36+Oct!P36+Nov!P36+Dec!P36+Jan!P36+Feb!P36+Mar!P36 -> 0 | Q36: =J36+O36+P36 -> 0 | R36: =IF(H36="Exempt",0,ROUND((J36*H36/100)-SUM(K36:M36),2)) -> 0 | T36: =Apr!T36+May!T36+Jun!T36+Jul!T36+Aug!T36+Sep!T36+Oct!T36+Nov!T36+Dec!T36+Jan!T36+Feb!T36+Mar!T36 -> 0 | U36: =Apr!U36+May!U36+Jun!U36+Jul!U36+Aug!U36+Sep!U36+Oct!U36+Nov!U36+Dec!U36+Jan!U36+Feb!U36+Mar!U36 -> 0 | V36: =Apr!V36+May!V36+Jun!V36+Jul!V36+Aug!V36+Sep!V36+Oct!V36+Nov!V36+Dec!V36+Jan!V36+Feb!V36+Mar!V36 -> 0 | W36: =Apr!W36+May!W36+Jun!W36+Jul!W36+Aug!W36+Sep!W36+Oct!W36+Nov!W36+Dec!W36+Jan!W36+Feb!W36+Mar!W36 -> 0 | X36: =Apr!X36+May!X36+Jun!X36+Jul!X36+Aug!X36+Sep!X36+Oct!X36+Nov!X36+Dec!X36+Jan!X36+Feb!X36+Mar!X36 -> 0 | Y36: =SUM(U36:X36) -> 0 | Z36: =Apr!Z36+May!Z36+Jun!Z36+Jul!Z36+Aug!Z36+Sep!Z36+Oct!Z36+Nov!Z36+Dec!Z36+Jan!Z36+Feb!Z36+Mar!Z36 -> 0 | AA36: =T36+Y36+Z36 -> 0 | AB36: =IF(H36="Exempt",0,ROUND((T36*H36/100)-SUM(U36:W36),2)) -> 0 | AD36: =Apr!AD36+May!AD36+Jun!AD36+Jul!AD36+Aug!AD36+Sep!AD36+Oct!AD36+Nov!AD36+Dec!AD36+Jan!AD36+Feb!AD36+Mar!AD36 -> 0 | AE36: =Apr!AE36+May!AE36+Jun!AE36+Jul!AE36+Aug!AE36+Sep!AE36+Oct!AE36+Nov!AE36+Dec!AE36+Jan!AE36+Feb!AE36+Mar!AE36 -> 0 | AF36: =Apr!AF36+May!AF36+Jun!AF36+Jul!AF36+Aug!AF36+Sep!AF36+Oct!AF36+Nov!AF36+Dec!AF36+Jan!AF36+Feb!AF36+Mar!AF36 -> 0 | AG36: =Apr!AG36+May!AG36+Jun!AG36+Jul!AG36+Aug!AG36+Sep!AG36+Oct!AG36+Nov!AG36+Dec!AG36+Jan!AG36+Feb!AG36+Mar!AG36 -> 0 | AI36: =SUM(AE36:AH36) -> 0 | AJ36: =Apr!AJ36+May!AJ36+Jun!AJ36+Jul!AJ36+Aug!AJ36+Sep!AJ36+Oct!AJ36+Nov!AJ36+Dec!AJ36+Jan!AJ36+Feb!AJ36+Mar!AJ36 -> 0 | AK36: =AD36+AI36+AJ36 -> 0 | AL36: =IF(H36="Exempt",0,ROUND((AD36*H36/100)-SUM(AE36:AG36),2)) -> 0
A37: =+A36+1 -> 22 | J37: =Apr!J37+May!J37+Jun!J37+Jul!J37+Aug!J37+Sep!J37+Oct!J37+Nov!J37+Dec!J37+Jan!J37+Feb!J37+Mar!J37 -> 0 | K37: =Apr!K37+May!K37+Jun!K37+Jul!K37+Aug!K37+Sep!K37+Oct!K37+Nov!K37+Dec!K37+Jan!K37+Feb!K37+Mar!K37 -> 0 | L37: =Apr!L37+May!L37+Jun!L37+Jul!L37+Aug!L37+Sep!L37+Oct!L37+Nov!L37+Dec!L37+Jan!L37+Feb!L37+Mar!L37 -> 0 | M37: =Apr!M37+May!M37+Jun!M37+Jul!M37+Aug!M37+Sep!M37+Oct!M37+Nov!M37+Dec!M37+Jan!M37+Feb!M37+Mar!M37 -> 0 | N37: =Apr!N37+May!N37+Jun!N37+Jul!N37+Aug!N37+Sep!N37+Oct!N37+Nov!N37+Dec!N37+Jan!N37+Feb!N37+Mar!N37 -> 0 | O37: =SUM(K37:N37) -> 0 | P37: =Apr!P37+May!P37+Jun!P37+Jul!P37+Aug!P37+Sep!P37+Oct!P37+Nov!P37+Dec!P37+Jan!P37+Feb!P37+Mar!P37 -> 0 | Q37: =J37+O37+P37 -> 0 | R37: =IF(H37="Exempt",0,ROUND((J37*H37/100)-SUM(K37:M37),2)) -> 0 | T37: =Apr!T37+May!T37+Jun!T37+Jul!T37+Aug!T37+Sep!T37+Oct!T37+Nov!T37+Dec!T37+Jan!T37+Feb!T37+Mar!T37 -> 0 | U37: =Apr!U37+May!U37+Jun!U37+Jul!U37+Aug!U37+Sep!U37+Oct!U37+Nov!U37+Dec!U37+Jan!U37+Feb!U37+Mar!U37 -> 0 | V37: =Apr!V37+May!V37+Jun!V37+Jul!V37+Aug!V37+Sep!V37+Oct!V37+Nov!V37+Dec!V37+Jan!V37+Feb!V37+Mar!V37 -> 0 | W37: =Apr!W37+May!W37+Jun!W37+Jul!W37+Aug!W37+Sep!W37+Oct!W37+Nov!W37+Dec!W37+Jan!W37+Feb!W37+Mar!W37 -> 0 | X37: =Apr!X37+May!X37+Jun!X37+Jul!X37+Aug!X37+Sep!X37+Oct!X37+Nov!X37+Dec!X37+Jan!X37+Feb!X37+Mar!X37 -> 0 | Y37: =SUM(U37:X37) -> 0 | Z37: =Apr!Z37+May!Z37+Jun!Z37+Jul!Z37+Aug!Z37+Sep!Z37+Oct!Z37+Nov!Z37+Dec!Z37+Jan!Z37+Feb!Z37+Mar!Z37 -> 0 | AA37: =T37+Y37+Z37 -> 0 | AB37: =IF(H37="Exempt",0,ROUND((T37*H37/100)-SUM(U37:W37),2)) -> 0 | AD37: =Apr!AD37+May!AD37+Jun!AD37+Jul!AD37+Aug!AD37+Sep!AD37+Oct!AD37+Nov!AD37+Dec!AD37+Jan!AD37+Feb!AD37+Mar!AD37 -> 0 | AE37: =Apr!AE37+May!AE37+Jun!AE37+Jul!AE37+Aug!AE37+Sep!AE37+Oct!AE37+Nov!AE37+Dec!AE37+Jan!AE37+Feb!AE37+Mar!AE37 -> 0 | AF37: =Apr!AF37+May!AF37+Jun!AF37+Jul!AF37+Aug!AF37+Sep!AF37+Oct!AF37+Nov!AF37+Dec!AF37+Jan!AF37+Feb!AF37+Mar!AF37 -> 0 | AG37: =Apr!AG37+May!AG37+Jun!AG37+Jul!AG37+Aug!AG37+Sep!AG37+Oct!AG37+Nov!AG37+Dec!AG37+Jan!AG37+Feb!AG37+Mar!AG37 -> 0 | AI37: =SUM(AE37:AH37) -> 0 | AJ37: =Apr!AJ37+May!AJ37+Jun!AJ37+Jul!AJ37+Aug!AJ37+Sep!AJ37+Oct!AJ37+Nov!AJ37+Dec!AJ37+Jan!AJ37+Feb!AJ37+Mar!AJ37 -> 0 | AK37: =AD37+AI37+AJ37 -> 0 | AL37: =IF(H37="Exempt",0,ROUND((AD37*H37/100)-SUM(AE37:AG37),2)) -> 0
A38: =+A37+1 -> 23 | J38: =Apr!J38+May!J38+Jun!J38+Jul!J38+Aug!J38+Sep!J38+Oct!J38+Nov!J38+Dec!J38+Jan!J38+Feb!J38+Mar!J38 -> 0 | K38: =Apr!K38+May!K38+Jun!K38+Jul!K38+Aug!K38+Sep!K38+Oct!K38+Nov!K38+Dec!K38+Jan!K38+Feb!K38+Mar!K38 -> 0 | L38: =Apr!L38+May!L38+Jun!L38+Jul!L38+Aug!L38+Sep!L38+Oct!L38+Nov!L38+Dec!L38+Jan!L38+Feb!L38+Mar!L38 -> 0 | M38: =Apr!M38+May!M38+Jun!M38+Jul!M38+Aug!M38+Sep!M38+Oct!M38+Nov!M38+Dec!M38+Jan!M38+Feb!M38+Mar!M38 -> 0 | N38: =Apr!N38+May!N38+Jun!N38+Jul!N38+Aug!N38+Sep!N38+Oct!N38+Nov!N38+Dec!N38+Jan!N38+Feb!N38+Mar!N38 -> 0 | O38: =SUM(K38:N38) -> 0 | P38: =Apr!P38+May!P38+Jun!P38+Jul!P38+Aug!P38+Sep!P38+Oct!P38+Nov!P38+Dec!P38+Jan!P38+Feb!P38+Mar!P38 -> 0 | Q38: =J38+O38+P38 -> 0 | R38: =IF(H38="Exempt",0,ROUND((J38*H38/100)-SUM(K38:M38),2)) -> 0 | T38: =Apr!T38+May!T38+Jun!T38+Jul!T38+Aug!T38+Sep!T38+Oct!T38+Nov!T38+Dec!T38+Jan!T38+Feb!T38+Mar!T38 -> 0 | U38: =Apr!U38+May!U38+Jun!U38+Jul!U38+Aug!U38+Sep!U38+Oct!U38+Nov!U38+Dec!U38+Jan!U38+Feb!U38+Mar!U38 -> 0 | V38: =Apr!V38+May!V38+Jun!V38+Jul!V38+Aug!V38+Sep!V38+Oct!V38+Nov!V38+Dec!V38+Jan!V38+Feb!V38+Mar!V38 -> 0 | W38: =Apr!W38+May!W38+Jun!W38+Jul!W38+Aug!W38+Sep!W38+Oct!W38+Nov!W38+Dec!W38+Jan!W38+Feb!W38+Mar!W38 -> 0 | X38: =Apr!X38+May!X38+Jun!X38+Jul!X38+Aug!X38+Sep!X38+Oct!X38+Nov!X38+Dec!X38+Jan!X38+Feb!X38+Mar!X38 -> 0 | Y38: =SUM(U38:X38) -> 0 | Z38: =Apr!Z38+May!Z38+Jun!Z38+Jul!Z38+Aug!Z38+Sep!Z38+Oct!Z38+Nov!Z38+Dec!Z38+Jan!Z38+Feb!Z38+Mar!Z38 -> 0 | AA38: =T38+Y38+Z38 -> 0 | AB38: =IF(H38="Exempt",0,ROUND((T38*H38/100)-SUM(U38:W38),2)) -> 0 | AD38: =Apr!AD38+May!AD38+Jun!AD38+Jul!AD38+Aug!AD38+Sep!AD38+Oct!AD38+Nov!AD38+Dec!AD38+Jan!AD38+Feb!AD38+Mar!AD38 -> 0 | AE38: =Apr!AE38+May!AE38+Jun!AE38+Jul!AE38+Aug!AE38+Sep!AE38+Oct!AE38+Nov!AE38+Dec!AE38+Jan!AE38+Feb!AE38+Mar!AE38 -> 0 | AF38: =Apr!AF38+May!AF38+Jun!AF38+Jul!AF38+Aug!AF38+Sep!AF38+Oct!AF38+Nov!AF38+Dec!AF38+Jan!AF38+Feb!AF38+Mar!AF38 -> 0 | AG38: =Apr!AG38+May!AG38+Jun!AG38+Jul!AG38+Aug!AG38+Sep!AG38+Oct!AG38+Nov!AG38+Dec!AG38+Jan!AG38+Feb!AG38+Mar!AG38 -> 0 | AI38: =SUM(AE38:AH38) -> 0 | AJ38: =Apr!AJ38+May!AJ38+Jun!AJ38+Jul!AJ38+Aug!AJ38+Sep!AJ38+Oct!AJ38+Nov!AJ38+Dec!AJ38+Jan!AJ38+Feb!AJ38+Mar!AJ38 -> 0 | AK38: =AD38+AI38+AJ38 -> 0 | AL38: =IF(H38="Exempt",0,ROUND((AD38*H38/100)-SUM(AE38:AG38),2)) -> 0
A39: =+A38+1 -> 24 | B39: Indirect Incomes | C39: INTEREST ON LATE PAYMENT | D39: Materials | E39: Registered | F39: Debit Note | H39: 5 | J39: =Apr!J39+May!J39+Jun!J39+Jul!J39+Aug!J39+Sep!J39+Oct!J39+Nov!J39+Dec!J39+Jan!J39+Feb!J39+Mar!J39 -> 0 | K39: =Apr!K39+May!K39+Jun!K39+Jul!K39+Aug!K39+Sep!K39+Oct!K39+Nov!K39+Dec!K39+Jan!K39+Feb!K39+Mar!K39 -> 0 | L39: =Apr!L39+May!L39+Jun!L39+Jul!L39+Aug!L39+Sep!L39+Oct!L39+Nov!L39+Dec!L39+Jan!L39+Feb!L39+Mar!L39 -> 0 | M39: =Apr!M39+May!M39+Jun!M39+Jul!M39+Aug!M39+Sep!M39+Oct!M39+Nov!M39+Dec!M39+Jan!M39+Feb!M39+Mar!M39 -> 0 | N39: =Apr!N39+May!N39+Jun!N39+Jul!N39+Aug!N39+Sep!N39+Oct!N39+Nov!N39+Dec!N39+Jan!N39+Feb!N39+Mar!N39 -> 0 | O39: =SUM(K39:N39) -> 0 | P39: =Apr!P39+May!P39+Jun!P39+Jul!P39+Aug!P39+Sep!P39+Oct!P39+Nov!P39+Dec!P39+Jan!P39+Feb!P39+Mar!P39 -> 0 | Q39: =J39+O39+P39 -> 0 | R39: =IF(H39="Exempt",0,ROUND((J39*H39/100)-SUM(K39:M39),2)) -> 0 | T39: =Apr!T39+May!T39+Jun!T39+Jul!T39+Aug!T39+Sep!T39+Oct!T39+Nov!T39+Dec!T39+Jan!T39+Feb!T39+Mar!T39 -> 0 | U39: =Apr!U39+May!U39+Jun!U39+Jul!U39+Aug!U39+Sep!U39+Oct!U39+Nov!U39+Dec!U39+Jan!U39+Feb!U39+Mar!U39 -> 0 | V39: =Apr!V39+May!V39+Jun!V39+Jul!V39+Aug!V39+Sep!V39+Oct!V39+Nov!V39+Dec!V39+Jan!V39+Feb!V39+Mar!V39 -> 0 | W39: =Apr!W39+May!W39+Jun!W39+Jul!W39+Aug!W39+Sep!W39+Oct!W39+Nov!W39+Dec!W39+Jan!W39+Feb!W39+Mar!W39 -> 0 | X39: =Apr!X39+May!X39+Jun!X39+Jul!X39+Aug!X39+Sep!X39+Oct!X39+Nov!X39+Dec!X39+Jan!X39+Feb!X39+Mar!X39 -> 0 | Y39: =SUM(U39:X39) -> 0 | Z39: =Apr!Z39+May!Z39+Jun!Z39+Jul!Z39+Aug!Z39+Sep!Z39+Oct!Z39+Nov!Z39+Dec!Z39+Jan!Z39+Feb!Z39+Mar!Z39 -> 0 | AA39: =T39+Y39+Z39 -> 0 | AB39: =IF(H39="Exempt",0,ROUND((T39*H39/100)-SUM(U39:W39),2)) -> 0 | AD39: =Apr!AD39+May!AD39+Jun!AD39+Jul!AD39+Aug!AD39+Sep!AD39+Oct!AD39+Nov!AD39+Dec!AD39+Jan!AD39+Feb!AD39+Mar!AD39 -> 0 | AE39: =Apr!AE39+May!AE39+Jun!AE39+Jul!AE39+Aug!AE39+Sep!AE39+Oct!AE39+Nov!AE39+Dec!AE39+Jan!AE39+Feb!AE39+Mar!AE39 -> 0 | AF39: =Apr!AF39+May!AF39+Jun!AF39+Jul!AF39+Aug!AF39+Sep!AF39+Oct!AF39+Nov!AF39+Dec!AF39+Jan!AF39+Feb!AF39+Mar!AF39 -> 0 | AG39: =Apr!AG39+May!AG39+Jun!AG39+Jul!AG39+Aug!AG39+Sep!AG39+Oct!AG39+Nov!AG39+Dec!AG39+Jan!AG39+Feb!AG39+Mar!AG39 -> 0 | AI39: =SUM(AE39:AH39) -> 0 | AJ39: =Apr!AJ39+May!AJ39+Jun!AJ39+Jul!AJ39+Aug!AJ39+Sep!AJ39+Oct!AJ39+Nov!AJ39+Dec!AJ39+Jan!AJ39+Feb!AJ39+Mar!AJ39 -> 0 | AK39: =AD39+AI39+AJ39 -> 0 | AL39: =IF(H39="Exempt",0,ROUND((AD39*H39/100)-SUM(AE39:AG39),2)) -> 0
A40: =+A39+1 -> 25 | B40: Indirect Incomes | C40: INTEREST ON LATE PAYMENT | D40: Materials | E40: Un-registered | F40: Debit Note | H40: 5 | J40: =Apr!J40+May!J40+Jun!J40+Jul!J40+Aug!J40+Sep!J40+Oct!J40+Nov!J40+Dec!J40+Jan!J40+Feb!J40+Mar!J40 -> 0 | K40: =Apr!K40+May!K40+Jun!K40+Jul!K40+Aug!K40+Sep!K40+Oct!K40+Nov!K40+Dec!K40+Jan!K40+Feb!K40+Mar!K40 -> 0 | L40: =Apr!L40+May!L40+Jun!L40+Jul!L40+Aug!L40+Sep!L40+Oct!L40+Nov!L40+Dec!L40+Jan!L40+Feb!L40+Mar!L40 -> 0 | M40: =Apr!M40+May!M40+Jun!M40+Jul!M40+Aug!M40+Sep!M40+Oct!M40+Nov!M40+Dec!M40+Jan!M40+Feb!M40+Mar!M40 -> 0 | N40: =Apr!N40+May!N40+Jun!N40+Jul!N40+Aug!N40+Sep!N40+Oct!N40+Nov!N40+Dec!N40+Jan!N40+Feb!N40+Mar!N40 -> 0 | O40: =SUM(K40:N40) -> 0 | P40: =Apr!P40+May!P40+Jun!P40+Jul!P40+Aug!P40+Sep!P40+Oct!P40+Nov!P40+Dec!P40+Jan!P40+Feb!P40+Mar!P40 -> 0 | Q40: =J40+O40+P40 -> 0 | R40: =IF(H40="Exempt",0,ROUND((J40*H40/100)-SUM(K40:M40),2)) -> 0 | T40: =Apr!T40+May!T40+Jun!T40+Jul!T40+Aug!T40+Sep!T40+Oct!T40+Nov!T40+Dec!T40+Jan!T40+Feb!T40+Mar!T40 -> 0 | U40: =Apr!U40+May!U40+Jun!U40+Jul!U40+Aug!U40+Sep!U40+Oct!U40+Nov!U40+Dec!U40+Jan!U40+Feb!U40+Mar!U40 -> 0 | V40: =Apr!V40+May!V40+Jun!V40+Jul!V40+Aug!V40+Sep!V40+Oct!V40+Nov!V40+Dec!V40+Jan!V40+Feb!V40+Mar!V40 -> 0 | W40: =Apr!W40+May!W40+Jun!W40+Jul!W40+Aug!W40+Sep!W40+Oct!W40+Nov!W40+Dec!W40+Jan!W40+Feb!W40+Mar!W40 -> 0 | X40: =Apr!X40+May!X40+Jun!X40+Jul!X40+Aug!X40+Sep!X40+Oct!X40+Nov!X40+Dec!X40+Jan!X40+Feb!X40+Mar!X40 -> 0 | Y40: =SUM(U40:X40) -> 0 | Z40: =Apr!Z40+May!Z40+Jun!Z40+Jul!Z40+Aug!Z40+Sep!Z40+Oct!Z40+Nov!Z40+Dec!Z40+Jan!Z40+Feb!Z40+Mar!Z40 -> 0 | AA40: =T40+Y40+Z40 -> 0 | AB40: =IF(H40="Exempt",0,ROUND((T40*H40/100)-SUM(U40:W40),2)) -> 0 | AD40: =Apr!AD40+May!AD40+Jun!AD40+Jul!AD40+Aug!AD40+Sep!AD40+Oct!AD40+Nov!AD40+Dec!AD40+Jan!AD40+Feb!AD40+Mar!AD40 -> 0 | AE40: =Apr!AE40+May!AE40+Jun!AE40+Jul!AE40+Aug!AE40+Sep!AE40+Oct!AE40+Nov!AE40+Dec!AE40+Jan!AE40+Feb!AE40+Mar!AE40 -> 0 | AF40: =Apr!AF40+May!AF40+Jun!AF40+Jul!AF40+Aug!AF40+Sep!AF40+Oct!AF40+Nov!AF40+Dec!AF40+Jan!AF40+Feb!AF40+Mar!AF40 -> 0 | AG40: =Apr!AG40+May!AG40+Jun!AG40+Jul!AG40+Aug!AG40+Sep!AG40+Oct!AG40+Nov!AG40+Dec!AG40+Jan!AG40+Feb!AG40+Mar!AG40 -> 0 | AI40: =SUM(AE40:AH40) -> 0 | AJ40: =Apr!AJ40+May!AJ40+Jun!AJ40+Jul!AJ40+Aug!AJ40+Sep!AJ40+Oct!AJ40+Nov!AJ40+Dec!AJ40+Jan!AJ40+Feb!AJ40+Mar!AJ40 -> 0 | AK40: =AD40+AI40+AJ40 -> 0 | AL40: =IF(H40="Exempt",0,ROUND((AD40*H40/100)-SUM(AE40:AG40),2)) -> 0
A41: =+A40+1 -> 26 | B41: Indirect Incomes | C41: INTEREST ON LATE PAYMENT | D41: Materials | E41: Registered | F41: Debit Note | H41: 12 | J41: =Apr!J41+May!J41+Jun!J41+Jul!J41+Aug!J41+Sep!J41+Oct!J41+Nov!J41+Dec!J41+Jan!J41+Feb!J41+Mar!J41 -> 0 | K41: =Apr!K41+May!K41+Jun!K41+Jul!K41+Aug!K41+Sep!K41+Oct!K41+Nov!K41+Dec!K41+Jan!K41+Feb!K41+Mar!K41 -> 0 | L41: =Apr!L41+May!L41+Jun!L41+Jul!L41+Aug!L41+Sep!L41+Oct!L41+Nov!L41+Dec!L41+Jan!L41+Feb!L41+Mar!L41 -> 0 | M41: =Apr!M41+May!M41+Jun!M41+Jul!M41+Aug!M41+Sep!M41+Oct!M41+Nov!M41+Dec!M41+Jan!M41+Feb!M41+Mar!M41 -> 0 | N41: =Apr!N41+May!N41+Jun!N41+Jul!N41+Aug!N41+Sep!N41+Oct!N41+Nov!N41+Dec!N41+Jan!N41+Feb!N41+Mar!N41 -> 0 | O41: =SUM(K41:N41) -> 0 | P41: =Apr!P41+May!P41+Jun!P41+Jul!P41+Aug!P41+Sep!P41+Oct!P41+Nov!P41+Dec!P41+Jan!P41+Feb!P41+Mar!P41 -> 0 | Q41: =J41+O41+P41 -> 0 | R41: =IF(H41="Exempt",0,ROUND((J41*H41/100)-SUM(K41:M41),2)) -> 0 | T41: =Apr!T41+May!T41+Jun!T41+Jul!T41+Aug!T41+Sep!T41+Oct!T41+Nov!T41+Dec!T41+Jan!T41+Feb!T41+Mar!T41 -> 0 | U41: =Apr!U41+May!U41+Jun!U41+Jul!U41+Aug!U41+Sep!U41+Oct!U41+Nov!U41+Dec!U41+Jan!U41+Feb!U41+Mar!U41 -> 0 | V41: =Apr!V41+May!V41+Jun!V41+Jul!V41+Aug!V41+Sep!V41+Oct!V41+Nov!V41+Dec!V41+Jan!V41+Feb!V41+Mar!V41 -> 0 | W41: =Apr!W41+May!W41+Jun!W41+Jul!W41+Aug!W41+Sep!W41+Oct!W41+Nov!W41+Dec!W41+Jan!W41+Feb!W41+Mar!W41 -> 0 | X41: =Apr!X41+May!X41+Jun!X41+Jul!X41+Aug!X41+Sep!X41+Oct!X41+Nov!X41+Dec!X41+Jan!X41+Feb!X41+Mar!X41 -> 0 | Y41: =SUM(U41:X41) -> 0 | Z41: =Apr!Z41+May!Z41+Jun!Z41+Jul!Z41+Aug!Z41+Sep!Z41+Oct!Z41+Nov!Z41+Dec!Z41+Jan!Z41+Feb!Z41+Mar!Z41 -> 0 | AA41: =T41+Y41+Z41 -> 0 | AB41: =IF(H41="Exempt",0,ROUND((T41*H41/100)-SUM(U41:W41),2)) -> 0 | AD41: =Apr!AD41+May!AD41+Jun!AD41+Jul!AD41+Aug!AD41+Sep!AD41+Oct!AD41+Nov!AD41+Dec!AD41+Jan!AD41+Feb!AD41+Mar!AD41 -> 0 | AE41: =Apr!AE41+May!AE41+Jun!AE41+Jul!AE41+Aug!AE41+Sep!AE41+Oct!AE41+Nov!AE41+Dec!AE41+Jan!AE41+Feb!AE41+Mar!AE41 -> 0 | AF41: =Apr!AF41+May!AF41+Jun!AF41+Jul!AF41+Aug!AF41+Sep!AF41+Oct!AF41+Nov!AF41+Dec!AF41+Jan!AF41+Feb!AF41+Mar!AF41 -> 0 | AG41: =Apr!AG41+May!AG41+Jun!AG41+Jul!AG41+Aug!AG41+Sep!AG41+Oct!AG41+Nov!AG41+Dec!AG41+Jan!AG41+Feb!AG41+Mar!AG41 -> 0 | AI41: =SUM(AE41:AH41) -> 0 | AJ41: =Apr!AJ41+May!AJ41+Jun!AJ41+Jul!AJ41+Aug!AJ41+Sep!AJ41+Oct!AJ41+Nov!AJ41+Dec!AJ41+Jan!AJ41+Feb!AJ41+Mar!AJ41 -> 0 | AK41: =AD41+AI41+AJ41 -> 0 | AL41: =IF(H41="Exempt",0,ROUND((AD41*H41/100)-SUM(AE41:AG41),2)) -> 0
A42: =+A41+1 -> 27 | B42: Indirect Incomes | C42: INTEREST ON LATE PAYMENT | D42: Materials | E42: Un-registered | F42: Debit Note | H42: 12 | J42: =Apr!J42+May!J42+Jun!J42+Jul!J42+Aug!J42+Sep!J42+Oct!J42+Nov!J42+Dec!J42+Jan!J42+Feb!J42+Mar!J42 -> 0 | K42: =Apr!K42+May!K42+Jun!K42+Jul!K42+Aug!K42+Sep!K42+Oct!K42+Nov!K42+Dec!K42+Jan!K42+Feb!K42+Mar!K42 -> 0 | L42: =Apr!L42+May!L42+Jun!L42+Jul!L42+Aug!L42+Sep!L42+Oct!L42+Nov!L42+Dec!L42+Jan!L42+Feb!L42+Mar!L42 -> 0 | M42: =Apr!M42+May!M42+Jun!M42+Jul!M42+Aug!M42+Sep!M42+Oct!M42+Nov!M42+Dec!M42+Jan!M42+Feb!M42+Mar!M42 -> 0 | N42: =Apr!N42+May!N42+Jun!N42+Jul!N42+Aug!N42+Sep!N42+Oct!N42+Nov!N42+Dec!N42+Jan!N42+Feb!N42+Mar!N42 -> 0 | O42: =SUM(K42:N42) -> 0 | P42: =Apr!P42+May!P42+Jun!P42+Jul!P42+Aug!P42+Sep!P42+Oct!P42+Nov!P42+Dec!P42+Jan!P42+Feb!P42+Mar!P42 -> 0 | Q42: =J42+O42+P42 -> 0 | R42: =IF(H42="Exempt",0,ROUND((J42*H42/100)-SUM(K42:M42),2)) -> 0 | T42: =Apr!T42+May!T42+Jun!T42+Jul!T42+Aug!T42+Sep!T42+Oct!T42+Nov!T42+Dec!T42+Jan!T42+Feb!T42+Mar!T42 -> 0 | U42: =Apr!U42+May!U42+Jun!U42+Jul!U42+Aug!U42+Sep!U42+Oct!U42+Nov!U42+Dec!U42+Jan!U42+Feb!U42+Mar!U42 -> 0 | V42: =Apr!V42+May!V42+Jun!V42+Jul!V42+Aug!V42+Sep!V42+Oct!V42+Nov!V42+Dec!V42+Jan!V42+Feb!V42+Mar!V42 -> 0 | W42: =Apr!W42+May!W42+Jun!W42+Jul!W42+Aug!W42+Sep!W42+Oct!W42+Nov!W42+Dec!W42+Jan!W42+Feb!W42+Mar!W42 -> 0 | X42: =Apr!X42+May!X42+Jun!X42+Jul!X42+Aug!X42+Sep!X42+Oct!X42+Nov!X42+Dec!X42+Jan!X42+Feb!X42+Mar!X42 -> 0 | Y42: =SUM(U42:X42) -> 0 | Z42: =Apr!Z42+May!Z42+Jun!Z42+Jul!Z42+Aug!Z42+Sep!Z42+Oct!Z42+Nov!Z42+Dec!Z42+Jan!Z42+Feb!Z42+Mar!Z42 -> 0 | AA42: =T42+Y42+Z42 -> 0 | AB42: =IF(H42="Exempt",0,ROUND((T42*H42/100)-SUM(U42:W42),2)) -> 0 | AD42: =Apr!AD42+May!AD42+Jun!AD42+Jul!AD42+Aug!AD42+Sep!AD42+Oct!AD42+Nov!AD42+Dec!AD42+Jan!AD42+Feb!AD42+Mar!AD42 -> 0 | AE42: =Apr!AE42+May!AE42+Jun!AE42+Jul!AE42+Aug!AE42+Sep!AE42+Oct!AE42+Nov!AE42+Dec!AE42+Jan!AE42+Feb!AE42+Mar!AE42 -> 0 | AF42: =Apr!AF42+May!AF42+Jun!AF42+Jul!AF42+Aug!AF42+Sep!AF42+Oct!AF42+Nov!AF42+Dec!AF42+Jan!AF42+Feb!AF42+Mar!AF42 -> 0 | AG42: =Apr!AG42+May!AG42+Jun!AG42+Jul!AG42+Aug!AG42+Sep!AG42+Oct!AG42+Nov!AG42+Dec!AG42+Jan!AG42+Feb!AG42+Mar!AG42 -> 0 | AI42: =SUM(AE42:AH42) -> 0 | AJ42: =Apr!AJ42+May!AJ42+Jun!AJ42+Jul!AJ42+Aug!AJ42+Sep!AJ42+Oct!AJ42+Nov!AJ42+Dec!AJ42+Jan!AJ42+Feb!AJ42+Mar!AJ42 -> 0 | AK42: =AD42+AI42+AJ42 -> 0 | AL42: =IF(H42="Exempt",0,ROUND((AD42*H42/100)-SUM(AE42:AG42),2)) -> 0
A43: =+A42+1 -> 28 | B43: Indirect Incomes | C43: INTEREST ON LATE PAYMENT | D43: Materials | E43: Registered | F43: Debit Note | H43: 18 | J43: =Apr!J43+May!J43+Jun!J43+Jul!J43+Aug!J43+Sep!J43+Oct!J43+Nov!J43+Dec!J43+Jan!J43+Feb!J43+Mar!J43 -> 0 | K43: =Apr!K43+May!K43+Jun!K43+Jul!K43+Aug!K43+Sep!K43+Oct!K43+Nov!K43+Dec!K43+Jan!K43+Feb!K43+Mar!K43 -> 0 | L43: =Apr!L43+May!L43+Jun!L43+Jul!L43+Aug!L43+Sep!L43+Oct!L43+Nov!L43+Dec!L43+Jan!L43+Feb!L43+Mar!L43 -> 0 | M43: =Apr!M43+May!M43+Jun!M43+Jul!M43+Aug!M43+Sep!M43+Oct!M43+Nov!M43+Dec!M43+Jan!M43+Feb!M43+Mar!M43 -> 0 | N43: =Apr!N43+May!N43+Jun!N43+Jul!N43+Aug!N43+Sep!N43+Oct!N43+Nov!N43+Dec!N43+Jan!N43+Feb!N43+Mar!N43 -> 0 | O43: =SUM(K43:N43) -> 0 | P43: =Apr!P43+May!P43+Jun!P43+Jul!P43+Aug!P43+Sep!P43+Oct!P43+Nov!P43+Dec!P43+Jan!P43+Feb!P43+Mar!P43 -> 0 | Q43: =J43+O43+P43 -> 0 | R43: =IF(H43="Exempt",0,ROUND((J43*H43/100)-SUM(K43:M43),2)) -> 0 | T43: =Apr!T43+May!T43+Jun!T43+Jul!T43+Aug!T43+Sep!T43+Oct!T43+Nov!T43+Dec!T43+Jan!T43+Feb!T43+Mar!T43 -> 0 | U43: =Apr!U43+May!U43+Jun!U43+Jul!U43+Aug!U43+Sep!U43+Oct!U43+Nov!U43+Dec!U43+Jan!U43+Feb!U43+Mar!U43 -> 0 | V43: =Apr!V43+May!V43+Jun!V43+Jul!V43+Aug!V43+Sep!V43+Oct!V43+Nov!V43+Dec!V43+Jan!V43+Feb!V43+Mar!V43 -> 0 | W43: =Apr!W43+May!W43+Jun!W43+Jul!W43+Aug!W43+Sep!W43+Oct!W43+Nov!W43+Dec!W43+Jan!W43+Feb!W43+Mar!W43 -> 0 | X43: =Apr!X43+May!X43+Jun!X43+Jul!X43+Aug!X43+Sep!X43+Oct!X43+Nov!X43+Dec!X43+Jan!X43+Feb!X43+Mar!X43 -> 0 | Y43: =SUM(U43:X43) -> 0 | Z43: =Apr!Z43+May!Z43+Jun!Z43+Jul!Z43+Aug!Z43+Sep!Z43+Oct!Z43+Nov!Z43+Dec!Z43+Jan!Z43+Feb!Z43+Mar!Z43 -> 0 | AA43: =T43+Y43+Z43 -> 0 | AB43: =IF(H43="Exempt",0,ROUND((T43*H43/100)-SUM(U43:W43),2)) -> 0 | AD43: =Apr!AD43+May!AD43+Jun!AD43+Jul!AD43+Aug!AD43+Sep!AD43+Oct!AD43+Nov!AD43+Dec!AD43+Jan!AD43+Feb!AD43+Mar!AD43 -> 0 | AE43: =Apr!AE43+May!AE43+Jun!AE43+Jul!AE43+Aug!AE43+Sep!AE43+Oct!AE43+Nov!AE43+Dec!AE43+Jan!AE43+Feb!AE43+Mar!AE43 -> 0 | AF43: =Apr!AF43+May!AF43+Jun!AF43+Jul!AF43+Aug!AF43+Sep!AF43+Oct!AF43+Nov!AF43+Dec!AF43+Jan!AF43+Feb!AF43+Mar!AF43 -> 0 | AG43: =Apr!AG43+May!AG43+Jun!AG43+Jul!AG43+Aug!AG43+Sep!AG43+Oct!AG43+Nov!AG43+Dec!AG43+Jan!AG43+Feb!AG43+Mar!AG43 -> 0 | AI43: =SUM(AE43:AH43) -> 0 | AJ43: =Apr!AJ43+May!AJ43+Jun!AJ43+Jul!AJ43+Aug!AJ43+Sep!AJ43+Oct!AJ43+Nov!AJ43+Dec!AJ43+Jan!AJ43+Feb!AJ43+Mar!AJ43 -> 0 | AK43: =AD43+AI43+AJ43 -> 0 | AL43: =IF(H43="Exempt",0,ROUND((AD43*H43/100)-SUM(AE43:AG43),2)) -> 0
A44: =+A43+1 -> 29 | B44: Indirect Incomes | C44: INTEREST ON LATE PAYMENT | D44: Materials | E44: Un-registered | F44: Debit Note | H44: 18 | J44: =Apr!J44+May!J44+Jun!J44+Jul!J44+Aug!J44+Sep!J44+Oct!J44+Nov!J44+Dec!J44+Jan!J44+Feb!J44+Mar!J44 -> 0 | K44: =Apr!K44+May!K44+Jun!K44+Jul!K44+Aug!K44+Sep!K44+Oct!K44+Nov!K44+Dec!K44+Jan!K44+Feb!K44+Mar!K44 -> 0 | L44: =Apr!L44+May!L44+Jun!L44+Jul!L44+Aug!L44+Sep!L44+Oct!L44+Nov!L44+Dec!L44+Jan!L44+Feb!L44+Mar!L44 -> 0 | M44: =Apr!M44+May!M44+Jun!M44+Jul!M44+Aug!M44+Sep!M44+Oct!M44+Nov!M44+Dec!M44+Jan!M44+Feb!M44+Mar!M44 -> 0 | N44: =Apr!N44+May!N44+Jun!N44+Jul!N44+Aug!N44+Sep!N44+Oct!N44+Nov!N44+Dec!N44+Jan!N44+Feb!N44+Mar!N44 -> 0 | O44: =SUM(K44:N44) -> 0 | P44: =Apr!P44+May!P44+Jun!P44+Jul!P44+Aug!P44+Sep!P44+Oct!P44+Nov!P44+Dec!P44+Jan!P44+Feb!P44+Mar!P44 -> 0 | Q44: =J44+O44+P44 -> 0 | R44: =IF(H44="Exempt",0,ROUND((J44*H44/100)-SUM(K44:M44),2)) -> 0 | T44: =Apr!T44+May!T44+Jun!T44+Jul!T44+Aug!T44+Sep!T44+Oct!T44+Nov!T44+Dec!T44+Jan!T44+Feb!T44+Mar!T44 -> 0 | U44: =Apr!U44+May!U44+Jun!U44+Jul!U44+Aug!U44+Sep!U44+Oct!U44+Nov!U44+Dec!U44+Jan!U44+Feb!U44+Mar!U44 -> 0 | V44: =Apr!V44+May!V44+Jun!V44+Jul!V44+Aug!V44+Sep!V44+Oct!V44+Nov!V44+Dec!V44+Jan!V44+Feb!V44+Mar!V44 -> 0 | W44: =Apr!W44+May!W44+Jun!W44+Jul!W44+Aug!W44+Sep!W44+Oct!W44+Nov!W44+Dec!W44+Jan!W44+Feb!W44+Mar!W44 -> 0 | X44: =Apr!X44+May!X44+Jun!X44+Jul!X44+Aug!X44+Sep!X44+Oct!X44+Nov!X44+Dec!X44+Jan!X44+Feb!X44+Mar!X44 -> 0 | Y44: =SUM(U44:X44) -> 0 | Z44: =Apr!Z44+May!Z44+Jun!Z44+Jul!Z44+Aug!Z44+Sep!Z44+Oct!Z44+Nov!Z44+Dec!Z44+Jan!Z44+Feb!Z44+Mar!Z44 -> 0 | AA44: =T44+Y44+Z44 -> 0 | AB44: =IF(H44="Exempt",0,ROUND((T44*H44/100)-SUM(U44:W44),2)) -> 0 | AD44: =Apr!AD44+May!AD44+Jun!AD44+Jul!AD44+Aug!AD44+Sep!AD44+Oct!AD44+Nov!AD44+Dec!AD44+Jan!AD44+Feb!AD44+Mar!AD44 -> 0 | AE44: =Apr!AE44+May!AE44+Jun!AE44+Jul!AE44+Aug!AE44+Sep!AE44+Oct!AE44+Nov!AE44+Dec!AE44+Jan!AE44+Feb!AE44+Mar!AE44 -> 0 | AF44: =Apr!AF44+May!AF44+Jun!AF44+Jul!AF44+Aug!AF44+Sep!AF44+Oct!AF44+Nov!AF44+Dec!AF44+Jan!AF44+Feb!AF44+Mar!AF44 -> 0 | AG44: =Apr!AG44+May!AG44+Jun!AG44+Jul!AG44+Aug!AG44+Sep!AG44+Oct!AG44+Nov!AG44+Dec!AG44+Jan!AG44+Feb!AG44+Mar!AG44 -> 0 | AI44: =SUM(AE44:AH44) -> 0 | AJ44: =Apr!AJ44+May!AJ44+Jun!AJ44+Jul!AJ44+Aug!AJ44+Sep!AJ44+Oct!AJ44+Nov!AJ44+Dec!AJ44+Jan!AJ44+Feb!AJ44+Mar!AJ44 -> 0 | AK44: =AD44+AI44+AJ44 -> 0 | AL44: =IF(H44="Exempt",0,ROUND((AD44*H44/100)-SUM(AE44:AG44),2)) -> 0
A45: =+A44+1 -> 30 | J45: =Apr!J45+May!J45+Jun!J45+Jul!J45+Aug!J45+Sep!J45+Oct!J45+Nov!J45+Dec!J45+Jan!J45+Feb!J45+Mar!J45 -> 0 | K45: =Apr!K45+May!K45+Jun!K45+Jul!K45+Aug!K45+Sep!K45+Oct!K45+Nov!K45+Dec!K45+Jan!K45+Feb!K45+Mar!K45 -> 0 | L45: =Apr!L45+May!L45+Jun!L45+Jul!L45+Aug!L45+Sep!L45+Oct!L45+Nov!L45+Dec!L45+Jan!L45+Feb!L45+Mar!L45 -> 0 | M45: =Apr!M45+May!M45+Jun!M45+Jul!M45+Aug!M45+Sep!M45+Oct!M45+Nov!M45+Dec!M45+Jan!M45+Feb!M45+Mar!M45 -> 0 | N45: =Apr!N45+May!N45+Jun!N45+Jul!N45+Aug!N45+Sep!N45+Oct!N45+Nov!N45+Dec!N45+Jan!N45+Feb!N45+Mar!N45 -> 0 | O45: =SUM(K45:N45) -> 0 | P45: =Apr!P45+May!P45+Jun!P45+Jul!P45+Aug!P45+Sep!P45+Oct!P45+Nov!P45+Dec!P45+Jan!P45+Feb!P45+Mar!P45 -> 0 | Q45: =J45+O45+P45 -> 0 | R45: =IF(H45="Exempt",0,ROUND((J45*H45/100)-SUM(K45:M45),2)) -> 0 | T45: =Apr!T45+May!T45+Jun!T45+Jul!T45+Aug!T45+Sep!T45+Oct!T45+Nov!T45+Dec!T45+Jan!T45+Feb!T45+Mar!T45 -> 0 | U45: =Apr!U45+May!U45+Jun!U45+Jul!U45+Aug!U45+Sep!U45+Oct!U45+Nov!U45+Dec!U45+Jan!U45+Feb!U45+Mar!U45 -> 0 | V45: =Apr!V45+May!V45+Jun!V45+Jul!V45+Aug!V45+Sep!V45+Oct!V45+Nov!V45+Dec!V45+Jan!V45+Feb!V45+Mar!V45 -> 0 | W45: =Apr!W45+May!W45+Jun!W45+Jul!W45+Aug!W45+Sep!W45+Oct!W45+Nov!W45+Dec!W45+Jan!W45+Feb!W45+Mar!W45 -> 0 | X45: =Apr!X45+May!X45+Jun!X45+Jul!X45+Aug!X45+Sep!X45+Oct!X45+Nov!X45+Dec!X45+Jan!X45+Feb!X45+Mar!X45 -> 0 | Y45: =SUM(U45:X45) -> 0 | Z45: =Apr!Z45+May!Z45+Jun!Z45+Jul!Z45+Aug!Z45+Sep!Z45+Oct!Z45+Nov!Z45+Dec!Z45+Jan!Z45+Feb!Z45+Mar!Z45 -> 0 | AA45: =T45+Y45+Z45 -> 0 | AB45: =IF(H45="Exempt",0,ROUND((T45*H45/100)-SUM(U45:W45),2)) -> 0 | AD45: =Apr!AD45+May!AD45+Jun!AD45+Jul!AD45+Aug!AD45+Sep!AD45+Oct!AD45+Nov!AD45+Dec!AD45+Jan!AD45+Feb!AD45+Mar!AD45 -> 0 | AE45: =Apr!AE45+May!AE45+Jun!AE45+Jul!AE45+Aug!AE45+Sep!AE45+Oct!AE45+Nov!AE45+Dec!AE45+Jan!AE45+Feb!AE45+Mar!AE45 -> 0 | AF45: =Apr!AF45+May!AF45+Jun!AF45+Jul!AF45+Aug!AF45+Sep!AF45+Oct!AF45+Nov!AF45+Dec!AF45+Jan!AF45+Feb!AF45+Mar!AF45 -> 0 | AG45: =Apr!AG45+May!AG45+Jun!AG45+Jul!AG45+Aug!AG45+Sep!AG45+Oct!AG45+Nov!AG45+Dec!AG45+Jan!AG45+Feb!AG45+Mar!AG45 -> 0 | AI45: =SUM(AE45:AH45) -> 0 | AJ45: =Apr!AJ45+May!AJ45+Jun!AJ45+Jul!AJ45+Aug!AJ45+Sep!AJ45+Oct!AJ45+Nov!AJ45+Dec!AJ45+Jan!AJ45+Feb!AJ45+Mar!AJ45 -> 0 | AK45: =AD45+AI45+AJ45 -> 0 | AL45: =IF(H45="Exempt",0,ROUND((AD45*H45/100)-SUM(AE45:AG45),2)) -> 0
A46: =+A45+1 -> 31 | J46: =Apr!J46+May!J46+Jun!J46+Jul!J46+Aug!J46+Sep!J46+Oct!J46+Nov!J46+Dec!J46+Jan!J46+Feb!J46+Mar!J46 -> 0 | K46: =Apr!K46+May!K46+Jun!K46+Jul!K46+Aug!K46+Sep!K46+Oct!K46+Nov!K46+Dec!K46+Jan!K46+Feb!K46+Mar!K46 -> 0 | L46: =Apr!L46+May!L46+Jun!L46+Jul!L46+Aug!L46+Sep!L46+Oct!L46+Nov!L46+Dec!L46+Jan!L46+Feb!L46+Mar!L46 -> 0 | M46: =Apr!M46+May!M46+Jun!M46+Jul!M46+Aug!M46+Sep!M46+Oct!M46+Nov!M46+Dec!M46+Jan!M46+Feb!M46+Mar!M46 -> 0 | N46: =Apr!N46+May!N46+Jun!N46+Jul!N46+Aug!N46+Sep!N46+Oct!N46+Nov!N46+Dec!N46+Jan!N46+Feb!N46+Mar!N46 -> 0 | O46: =SUM(K46:N46) -> 0 | P46: =Apr!P46+May!P46+Jun!P46+Jul!P46+Aug!P46+Sep!P46+Oct!P46+Nov!P46+Dec!P46+Jan!P46+Feb!P46+Mar!P46 -> 0 | Q46: =J46+O46+P46 -> 0 | R46: =IF(H46="Exempt",0,ROUND((J46*H46/100)-SUM(K46:M46),2)) -> 0 | T46: =Apr!T46+May!T46+Jun!T46+Jul!T46+Aug!T46+Sep!T46+Oct!T46+Nov!T46+Dec!T46+Jan!T46+Feb!T46+Mar!T46 -> 0 | U46: =Apr!U46+May!U46+Jun!U46+Jul!U46+Aug!U46+Sep!U46+Oct!U46+Nov!U46+Dec!U46+Jan!U46+Feb!U46+Mar!U46 -> 0 | V46: =Apr!V46+May!V46+Jun!V46+Jul!V46+Aug!V46+Sep!V46+Oct!V46+Nov!V46+Dec!V46+Jan!V46+Feb!V46+Mar!V46 -> 0 | W46: =Apr!W46+May!W46+Jun!W46+Jul!W46+Aug!W46+Sep!W46+Oct!W46+Nov!W46+Dec!W46+Jan!W46+Feb!W46+Mar!W46 -> 0 | X46: =Apr!X46+May!X46+Jun!X46+Jul!X46+Aug!X46+Sep!X46+Oct!X46+Nov!X46+Dec!X46+Jan!X46+Feb!X46+Mar!X46 -> 0 | Y46: =SUM(U46:X46) -> 0 | Z46: =Apr!Z46+May!Z46+Jun!Z46+Jul!Z46+Aug!Z46+Sep!Z46+Oct!Z46+Nov!Z46+Dec!Z46+Jan!Z46+Feb!Z46+Mar!Z46 -> 0 | AA46: =T46+Y46+Z46 -> 0 | AB46: =IF(H46="Exempt",0,ROUND((T46*H46/100)-SUM(U46:W46),2)) -> 0 | AD46: =Apr!AD46+May!AD46+Jun!AD46+Jul!AD46+Aug!AD46+Sep!AD46+Oct!AD46+Nov!AD46+Dec!AD46+Jan!AD46+Feb!AD46+Mar!AD46 -> 0 | AE46: =Apr!AE46+May!AE46+Jun!AE46+Jul!AE46+Aug!AE46+Sep!AE46+Oct!AE46+Nov!AE46+Dec!AE46+Jan!AE46+Feb!AE46+Mar!AE46 -> 0 | AF46: =Apr!AF46+May!AF46+Jun!AF46+Jul!AF46+Aug!AF46+Sep!AF46+Oct!AF46+Nov!AF46+Dec!AF46+Jan!AF46+Feb!AF46+Mar!AF46 -> 0 | AG46: =Apr!AG46+May!AG46+Jun!AG46+Jul!AG46+Aug!AG46+Sep!AG46+Oct!AG46+Nov!AG46+Dec!AG46+Jan!AG46+Feb!AG46+Mar!AG46 -> 0 | AI46: =SUM(AE46:AH46) -> 0 | AJ46: =Apr!AJ46+May!AJ46+Jun!AJ46+Jul!AJ46+Aug!AJ46+Sep!AJ46+Oct!AJ46+Nov!AJ46+Dec!AJ46+Jan!AJ46+Feb!AJ46+Mar!AJ46 -> 0 | AK46: =AD46+AI46+AJ46 -> 0 | AL46: =IF(H46="Exempt",0,ROUND((AD46*H46/100)-SUM(AE46:AG46),2)) -> 0
A47: =+A46+1 -> 32 | J47: =Apr!J47+May!J47+Jun!J47+Jul!J47+Aug!J47+Sep!J47+Oct!J47+Nov!J47+Dec!J47+Jan!J47+Feb!J47+Mar!J47 -> 0 | K47: =Apr!K47+May!K47+Jun!K47+Jul!K47+Aug!K47+Sep!K47+Oct!K47+Nov!K47+Dec!K47+Jan!K47+Feb!K47+Mar!K47 -> 0 | L47: =Apr!L47+May!L47+Jun!L47+Jul!L47+Aug!L47+Sep!L47+Oct!L47+Nov!L47+Dec!L47+Jan!L47+Feb!L47+Mar!L47 -> 0 | M47: =Apr!M47+May!M47+Jun!M47+Jul!M47+Aug!M47+Sep!M47+Oct!M47+Nov!M47+Dec!M47+Jan!M47+Feb!M47+Mar!M47 -> 0 | N47: =Apr!N47+May!N47+Jun!N47+Jul!N47+Aug!N47+Sep!N47+Oct!N47+Nov!N47+Dec!N47+Jan!N47+Feb!N47+Mar!N47 -> 0 | O47: =SUM(K47:N47) -> 0 | P47: =Apr!P47+May!P47+Jun!P47+Jul!P47+Aug!P47+Sep!P47+Oct!P47+Nov!P47+Dec!P47+Jan!P47+Feb!P47+Mar!P47 -> 0 | Q47: =J47+O47+P47 -> 0 | R47: =IF(H47="Exempt",0,ROUND((J47*H47/100)-SUM(K47:M47),2)) -> 0 | T47: =Apr!T47+May!T47+Jun!T47+Jul!T47+Aug!T47+Sep!T47+Oct!T47+Nov!T47+Dec!T47+Jan!T47+Feb!T47+Mar!T47 -> 0 | U47: =Apr!U47+May!U47+Jun!U47+Jul!U47+Aug!U47+Sep!U47+Oct!U47+Nov!U47+Dec!U47+Jan!U47+Feb!U47+Mar!U47 -> 0 | V47: =Apr!V47+May!V47+Jun!V47+Jul!V47+Aug!V47+Sep!V47+Oct!V47+Nov!V47+Dec!V47+Jan!V47+Feb!V47+Mar!V47 -> 0 | W47: =Apr!W47+May!W47+Jun!W47+Jul!W47+Aug!W47+Sep!W47+Oct!W47+Nov!W47+Dec!W47+Jan!W47+Feb!W47+Mar!W47 -> 0 | X47: =Apr!X47+May!X47+Jun!X47+Jul!X47+Aug!X47+Sep!X47+Oct!X47+Nov!X47+Dec!X47+Jan!X47+Feb!X47+Mar!X47 -> 0 | Y47: =SUM(U47:X47) -> 0 | Z47: =Apr!Z47+May!Z47+Jun!Z47+Jul!Z47+Aug!Z47+Sep!Z47+Oct!Z47+Nov!Z47+Dec!Z47+Jan!Z47+Feb!Z47+Mar!Z47 -> 0 | AA47: =T47+Y47+Z47 -> 0 | AB47: =IF(H47="Exempt",0,ROUND((T47*H47/100)-SUM(U47:W47),2)) -> 0 | AD47: =Apr!AD47+May!AD47+Jun!AD47+Jul!AD47+Aug!AD47+Sep!AD47+Oct!AD47+Nov!AD47+Dec!AD47+Jan!AD47+Feb!AD47+Mar!AD47 -> 0 | AE47: =Apr!AE47+May!AE47+Jun!AE47+Jul!AE47+Aug!AE47+Sep!AE47+Oct!AE47+Nov!AE47+Dec!AE47+Jan!AE47+Feb!AE47+Mar!AE47 -> 0 | AF47: =Apr!AF47+May!AF47+Jun!AF47+Jul!AF47+Aug!AF47+Sep!AF47+Oct!AF47+Nov!AF47+Dec!AF47+Jan!AF47+Feb!AF47+Mar!AF47 -> 0 | AG47: =Apr!AG47+May!AG47+Jun!AG47+Jul!AG47+Aug!AG47+Sep!AG47+Oct!AG47+Nov!AG47+Dec!AG47+Jan!AG47+Feb!AG47+Mar!AG47 -> 0 | AI47: =SUM(AE47:AH47) -> 0 | AJ47: =Apr!AJ47+May!AJ47+Jun!AJ47+Jul!AJ47+Aug!AJ47+Sep!AJ47+Oct!AJ47+Nov!AJ47+Dec!AJ47+Jan!AJ47+Feb!AJ47+Mar!AJ47 -> 0 | AK47: =AD47+AI47+AJ47 -> 0 | AL47: =IF(H47="Exempt",0,ROUND((AD47*H47/100)-SUM(AE47:AG47),2)) -> 0
A48: =+A47+1 -> 33 | J48: =Apr!J48+May!J48+Jun!J48+Jul!J48+Aug!J48+Sep!J48+Oct!J48+Nov!J48+Dec!J48+Jan!J48+Feb!J48+Mar!J48 -> 0 | K48: =Apr!K48+May!K48+Jun!K48+Jul!K48+Aug!K48+Sep!K48+Oct!K48+Nov!K48+Dec!K48+Jan!K48+Feb!K48+Mar!K48 -> 0 | L48: =Apr!L48+May!L48+Jun!L48+Jul!L48+Aug!L48+Sep!L48+Oct!L48+Nov!L48+Dec!L48+Jan!L48+Feb!L48+Mar!L48 -> 0 | M48: =Apr!M48+May!M48+Jun!M48+Jul!M48+Aug!M48+Sep!M48+Oct!M48+Nov!M48+Dec!M48+Jan!M48+Feb!M48+Mar!M48 -> 0 | N48: =Apr!N48+May!N48+Jun!N48+Jul!N48+Aug!N48+Sep!N48+Oct!N48+Nov!N48+Dec!N48+Jan!N48+Feb!N48+Mar!N48 -> 0 | O48: =SUM(K48:N48) -> 0 | P48: =Apr!P48+May!P48+Jun!P48+Jul!P48+Aug!P48+Sep!P48+Oct!P48+Nov!P48+Dec!P48+Jan!P48+Feb!P48+Mar!P48 -> 0 | Q48: =J48+O48+P48 -> 0 | R48: =IF(H48="Exempt",0,ROUND((J48*H48/100)-SUM(K48:M48),2)) -> 0 | T48: =Apr!T48+May!T48+Jun!T48+Jul!T48+Aug!T48+Sep!T48+Oct!T48+Nov!T48+Dec!T48+Jan!T48+Feb!T48+Mar!T48 -> 0 | U48: =Apr!U48+May!U48+Jun!U48+Jul!U48+Aug!U48+Sep!U48+Oct!U48+Nov!U48+Dec!U48+Jan!U48+Feb!U48+Mar!U48 -> 0 | V48: =Apr!V48+May!V48+Jun!V48+Jul!V48+Aug!V48+Sep!V48+Oct!V48+Nov!V48+Dec!V48+Jan!V48+Feb!V48+Mar!V48 -> 0 | W48: =Apr!W48+May!W48+Jun!W48+Jul!W48+Aug!W48+Sep!W48+Oct!W48+Nov!W48+Dec!W48+Jan!W48+Feb!W48+Mar!W48 -> 0 | X48: =Apr!X48+May!X48+Jun!X48+Jul!X48+Aug!X48+Sep!X48+Oct!X48+Nov!X48+Dec!X48+Jan!X48+Feb!X48+Mar!X48 -> 0 | Y48: =SUM(U48:X48) -> 0 | Z48: =Apr!Z48+May!Z48+Jun!Z48+Jul!Z48+Aug!Z48+Sep!Z48+Oct!Z48+Nov!Z48+Dec!Z48+Jan!Z48+Feb!Z48+Mar!Z48 -> 0 | AA48: =T48+Y48+Z48 -> 0 | AB48: =IF(H48="Exempt",0,ROUND((T48*H48/100)-SUM(U48:W48),2)) -> 0 | AD48: =Apr!AD48+May!AD48+Jun!AD48+Jul!AD48+Aug!AD48+Sep!AD48+Oct!AD48+Nov!AD48+Dec!AD48+Jan!AD48+Feb!AD48+Mar!AD48 -> 0 | AE48: =Apr!AE48+May!AE48+Jun!AE48+Jul!AE48+Aug!AE48+Sep!AE48+Oct!AE48+Nov!AE48+Dec!AE48+Jan!AE48+Feb!AE48+Mar!AE48 -> 0 | AF48: =Apr!AF48+May!AF48+Jun!AF48+Jul!AF48+Aug!AF48+Sep!AF48+Oct!AF48+Nov!AF48+Dec!AF48+Jan!AF48+Feb!AF48+Mar!AF48 -> 0 | AG48: =Apr!AG48+May!AG48+Jun!AG48+Jul!AG48+Aug!AG48+Sep!AG48+Oct!AG48+Nov!AG48+Dec!AG48+Jan!AG48+Feb!AG48+Mar!AG48 -> 0 | AI48: =SUM(AE48:AH48) -> 0 | AJ48: =Apr!AJ48+May!AJ48+Jun!AJ48+Jul!AJ48+Aug!AJ48+Sep!AJ48+Oct!AJ48+Nov!AJ48+Dec!AJ48+Jan!AJ48+Feb!AJ48+Mar!AJ48 -> 0 | AK48: =AD48+AI48+AJ48 -> 0 | AL48: =IF(H48="Exempt",0,ROUND((AD48*H48/100)-SUM(AE48:AG48),2)) -> 0
A49: =+A48+1 -> 34 | J49: =Apr!J49+May!J49+Jun!J49+Jul!J49+Aug!J49+Sep!J49+Oct!J49+Nov!J49+Dec!J49+Jan!J49+Feb!J49+Mar!J49 -> 0 | K49: =Apr!K49+May!K49+Jun!K49+Jul!K49+Aug!K49+Sep!K49+Oct!K49+Nov!K49+Dec!K49+Jan!K49+Feb!K49+Mar!K49 -> 0 | L49: =Apr!L49+May!L49+Jun!L49+Jul!L49+Aug!L49+Sep!L49+Oct!L49+Nov!L49+Dec!L49+Jan!L49+Feb!L49+Mar!L49 -> 0 | M49: =Apr!M49+May!M49+Jun!M49+Jul!M49+Aug!M49+Sep!M49+Oct!M49+Nov!M49+Dec!M49+Jan!M49+Feb!M49+Mar!M49 -> 0 | N49: =Apr!N49+May!N49+Jun!N49+Jul!N49+Aug!N49+Sep!N49+Oct!N49+Nov!N49+Dec!N49+Jan!N49+Feb!N49+Mar!N49 -> 0 | O49: =SUM(K49:N49) -> 0 | P49: =Apr!P49+May!P49+Jun!P49+Jul!P49+Aug!P49+Sep!P49+Oct!P49+Nov!P49+Dec!P49+Jan!P49+Feb!P49+Mar!P49 -> 0 | Q49: =J49+O49+P49 -> 0 | R49: =IF(H49="Exempt",0,ROUND((J49*H49/100)-SUM(K49:M49),2)) -> 0 | T49: =Apr!T49+May!T49+Jun!T49+Jul!T49+Aug!T49+Sep!T49+Oct!T49+Nov!T49+Dec!T49+Jan!T49+Feb!T49+Mar!T49 -> 0 | U49: =Apr!U49+May!U49+Jun!U49+Jul!U49+Aug!U49+Sep!U49+Oct!U49+Nov!U49+Dec!U49+Jan!U49+Feb!U49+Mar!U49 -> 0 | V49: =Apr!V49+May!V49+Jun!V49+Jul!V49+Aug!V49+Sep!V49+Oct!V49+Nov!V49+Dec!V49+Jan!V49+Feb!V49+Mar!V49 -> 0 | W49: =Apr!W49+May!W49+Jun!W49+Jul!W49+Aug!W49+Sep!W49+Oct!W49+Nov!W49+Dec!W49+Jan!W49+Feb!W49+Mar!W49 -> 0 | X49: =Apr!X49+May!X49+Jun!X49+Jul!X49+Aug!X49+Sep!X49+Oct!X49+Nov!X49+Dec!X49+Jan!X49+Feb!X49+Mar!X49 -> 0 | Y49: =SUM(U49:X49) -> 0 | Z49: =Apr!Z49+May!Z49+Jun!Z49+Jul!Z49+Aug!Z49+Sep!Z49+Oct!Z49+Nov!Z49+Dec!Z49+Jan!Z49+Feb!Z49+Mar!Z49 -> 0 | AA49: =T49+Y49+Z49 -> 0 | AB49: =IF(H49="Exempt",0,ROUND((T49*H49/100)-SUM(U49:W49),2)) -> 0 | AD49: =Apr!AD49+May!AD49+Jun!AD49+Jul!AD49+Aug!AD49+Sep!AD49+Oct!AD49+Nov!AD49+Dec!AD49+Jan!AD49+Feb!AD49+Mar!AD49 -> 0 | AE49: =Apr!AE49+May!AE49+Jun!AE49+Jul!AE49+Aug!AE49+Sep!AE49+Oct!AE49+Nov!AE49+Dec!AE49+Jan!AE49+Feb!AE49+Mar!AE49 -> 0 | AF49: =Apr!AF49+May!AF49+Jun!AF49+Jul!AF49+Aug!AF49+Sep!AF49+Oct!AF49+Nov!AF49+Dec!AF49+Jan!AF49+Feb!AF49+Mar!AF49 -> 0 | AG49: =Apr!AG49+May!AG49+Jun!AG49+Jul!AG49+Aug!AG49+Sep!AG49+Oct!AG49+Nov!AG49+Dec!AG49+Jan!AG49+Feb!AG49+Mar!AG49 -> 0 | AI49: =SUM(AE49:AH49) -> 0 | AJ49: =Apr!AJ49+May!AJ49+Jun!AJ49+Jul!AJ49+Aug!AJ49+Sep!AJ49+Oct!AJ49+Nov!AJ49+Dec!AJ49+Jan!AJ49+Feb!AJ49+Mar!AJ49 -> 0 | AK49: =AD49+AI49+AJ49 -> 0 | AL49: =IF(H49="Exempt",0,ROUND((AD49*H49/100)-SUM(AE49:AG49),2)) -> 0
A50: =+A49+1 -> 35 | J50: =Apr!J50+May!J50+Jun!J50+Jul!J50+Aug!J50+Sep!J50+Oct!J50+Nov!J50+Dec!J50+Jan!J50+Feb!J50+Mar!J50 -> 0 | K50: =Apr!K50+May!K50+Jun!K50+Jul!K50+Aug!K50+Sep!K50+Oct!K50+Nov!K50+Dec!K50+Jan!K50+Feb!K50+Mar!K50 -> 0 | L50: =Apr!L50+May!L50+Jun!L50+Jul!L50+Aug!L50+Sep!L50+Oct!L50+Nov!L50+Dec!L50+Jan!L50+Feb!L50+Mar!L50 -> 0 | M50: =Apr!M50+May!M50+Jun!M50+Jul!M50+Aug!M50+Sep!M50+Oct!M50+Nov!M50+Dec!M50+Jan!M50+Feb!M50+Mar!M50 -> 0 | N50: =Apr!N50+May!N50+Jun!N50+Jul!N50+Aug!N50+Sep!N50+Oct!N50+Nov!N50+Dec!N50+Jan!N50+Feb!N50+Mar!N50 -> 0 | O50: =SUM(K50:N50) -> 0 | P50: =Apr!P50+May!P50+Jun!P50+Jul!P50+Aug!P50+Sep!P50+Oct!P50+Nov!P50+Dec!P50+Jan!P50+Feb!P50+Mar!P50 -> 0 | Q50: =J50+O50+P50 -> 0 | R50: =IF(H50="Exempt",0,ROUND((J50*H50/100)-SUM(K50:M50),2)) -> 0 | T50: =Apr!T50+May!T50+Jun!T50+Jul!T50+Aug!T50+Sep!T50+Oct!T50+Nov!T50+Dec!T50+Jan!T50+Feb!T50+Mar!T50 -> 0 | U50: =Apr!U50+May!U50+Jun!U50+Jul!U50+Aug!U50+Sep!U50+Oct!U50+Nov!U50+Dec!U50+Jan!U50+Feb!U50+Mar!U50 -> 0 | V50: =Apr!V50+May!V50+Jun!V50+Jul!V50+Aug!V50+Sep!V50+Oct!V50+Nov!V50+Dec!V50+Jan!V50+Feb!V50+Mar!V50 -> 0 | W50: =Apr!W50+May!W50+Jun!W50+Jul!W50+Aug!W50+Sep!W50+Oct!W50+Nov!W50+Dec!W50+Jan!W50+Feb!W50+Mar!W50 -> 0 | X50: =Apr!X50+May!X50+Jun!X50+Jul!X50+Aug!X50+Sep!X50+Oct!X50+Nov!X50+Dec!X50+Jan!X50+Feb!X50+Mar!X50 -> 0 | Y50: =SUM(U50:X50) -> 0 | Z50: =Apr!Z50+May!Z50+Jun!Z50+Jul!Z50+Aug!Z50+Sep!Z50+Oct!Z50+Nov!Z50+Dec!Z50+Jan!Z50+Feb!Z50+Mar!Z50 -> 0 | AA50: =T50+Y50+Z50 -> 0 | AB50: =IF(H50="Exempt",0,ROUND((T50*H50/100)-SUM(U50:W50),2)) -> 0 | AD50: =Apr!AD50+May!AD50+Jun!AD50+Jul!AD50+Aug!AD50+Sep!AD50+Oct!AD50+Nov!AD50+Dec!AD50+Jan!AD50+Feb!AD50+Mar!AD50 -> 0 | AE50: =Apr!AE50+May!AE50+Jun!AE50+Jul!AE50+Aug!AE50+Sep!AE50+Oct!AE50+Nov!AE50+Dec!AE50+Jan!AE50+Feb!AE50+Mar!AE50 -> 0 | AF50: =Apr!AF50+May!AF50+Jun!AF50+Jul!AF50+Aug!AF50+Sep!AF50+Oct!AF50+Nov!AF50+Dec!AF50+Jan!AF50+Feb!AF50+Mar!AF50 -> 0 | AG50: =Apr!AG50+May!AG50+Jun!AG50+Jul!AG50+Aug!AG50+Sep!AG50+Oct!AG50+Nov!AG50+Dec!AG50+Jan!AG50+Feb!AG50+Mar!AG50 -> 0 | AI50: =SUM(AE50:AH50) -> 0 | AJ50: =Apr!AJ50+May!AJ50+Jun!AJ50+Jul!AJ50+Aug!AJ50+Sep!AJ50+Oct!AJ50+Nov!AJ50+Dec!AJ50+Jan!AJ50+Feb!AJ50+Mar!AJ50 -> 0 | AK50: =AD50+AI50+AJ50 -> 0 | AL50: =IF(H50="Exempt",0,ROUND((AD50*H50/100)-SUM(AE50:AG50),2)) -> 0
A51: =+A50+1 -> 36 | J51: =Apr!J51+May!J51+Jun!J51+Jul!J51+Aug!J51+Sep!J51+Oct!J51+Nov!J51+Dec!J51+Jan!J51+Feb!J51+Mar!J51 -> 0 | K51: =Apr!K51+May!K51+Jun!K51+Jul!K51+Aug!K51+Sep!K51+Oct!K51+Nov!K51+Dec!K51+Jan!K51+Feb!K51+Mar!K51 -> 0 | L51: =Apr!L51+May!L51+Jun!L51+Jul!L51+Aug!L51+Sep!L51+Oct!L51+Nov!L51+Dec!L51+Jan!L51+Feb!L51+Mar!L51 -> 0 | M51: =Apr!M51+May!M51+Jun!M51+Jul!M51+Aug!M51+Sep!M51+Oct!M51+Nov!M51+Dec!M51+Jan!M51+Feb!M51+Mar!M51 -> 0 | N51: =Apr!N51+May!N51+Jun!N51+Jul!N51+Aug!N51+Sep!N51+Oct!N51+Nov!N51+Dec!N51+Jan!N51+Feb!N51+Mar!N51 -> 0 | O51: =SUM(K51:N51) -> 0 | P51: =Apr!P51+May!P51+Jun!P51+Jul!P51+Aug!P51+Sep!P51+Oct!P51+Nov!P51+Dec!P51+Jan!P51+Feb!P51+Mar!P51 -> 0 | Q51: =J51+O51+P51 -> 0 | R51: =IF(H51="Exempt",0,ROUND((J51*H51/100)-SUM(K51:M51),2)) -> 0 | T51: =Apr!T51+May!T51+Jun!T51+Jul!T51+Aug!T51+Sep!T51+Oct!T51+Nov!T51+Dec!T51+Jan!T51+Feb!T51+Mar!T51 -> 0 | U51: =Apr!U51+May!U51+Jun!U51+Jul!U51+Aug!U51+Sep!U51+Oct!U51+Nov!U51+Dec!U51+Jan!U51+Feb!U51+Mar!U51 -> 0 | V51: =Apr!V51+May!V51+Jun!V51+Jul!V51+Aug!V51+Sep!V51+Oct!V51+Nov!V51+Dec!V51+Jan!V51+Feb!V51+Mar!V51 -> 0 | W51: =Apr!W51+May!W51+Jun!W51+Jul!W51+Aug!W51+Sep!W51+Oct!W51+Nov!W51+Dec!W51+Jan!W51+Feb!W51+Mar!W51 -> 0 | X51: =Apr!X51+May!X51+Jun!X51+Jul!X51+Aug!X51+Sep!X51+Oct!X51+Nov!X51+Dec!X51+Jan!X51+Feb!X51+Mar!X51 -> 0 | Y51: =SUM(U51:X51) -> 0 | Z51: =Apr!Z51+May!Z51+Jun!Z51+Jul!Z51+Aug!Z51+Sep!Z51+Oct!Z51+Nov!Z51+Dec!Z51+Jan!Z51+Feb!Z51+Mar!Z51 -> 0 | AA51: =T51+Y51+Z51 -> 0 | AB51: =IF(H51="Exempt",0,ROUND((T51*H51/100)-SUM(U51:W51),2)) -> 0 | AD51: =Apr!AD51+May!AD51+Jun!AD51+Jul!AD51+Aug!AD51+Sep!AD51+Oct!AD51+Nov!AD51+Dec!AD51+Jan!AD51+Feb!AD51+Mar!AD51 -> 0 | AE51: =Apr!AE51+May!AE51+Jun!AE51+Jul!AE51+Aug!AE51+Sep!AE51+Oct!AE51+Nov!AE51+Dec!AE51+Jan!AE51+Feb!AE51+Mar!AE51 -> 0 | AF51: =Apr!AF51+May!AF51+Jun!AF51+Jul!AF51+Aug!AF51+Sep!AF51+Oct!AF51+Nov!AF51+Dec!AF51+Jan!AF51+Feb!AF51+Mar!AF51 -> 0 | AG51: =Apr!AG51+May!AG51+Jun!AG51+Jul!AG51+Aug!AG51+Sep!AG51+Oct!AG51+Nov!AG51+Dec!AG51+Jan!AG51+Feb!AG51+Mar!AG51 -> 0 | AI51: =SUM(AE51:AH51) -> 0 | AJ51: =Apr!AJ51+May!AJ51+Jun!AJ51+Jul!AJ51+Aug!AJ51+Sep!AJ51+Oct!AJ51+Nov!AJ51+Dec!AJ51+Jan!AJ51+Feb!AJ51+Mar!AJ51 -> 0 | AK51: =AD51+AI51+AJ51 -> 0 | AL51: =IF(H51="Exempt",0,ROUND((AD51*H51/100)-SUM(AE51:AG51),2)) -> 0
A52: =+A51+1 -> 37 | J52: =Apr!J52+May!J52+Jun!J52+Jul!J52+Aug!J52+Sep!J52+Oct!J52+Nov!J52+Dec!J52+Jan!J52+Feb!J52+Mar!J52 -> 0 | K52: =Apr!K52+May!K52+Jun!K52+Jul!K52+Aug!K52+Sep!K52+Oct!K52+Nov!K52+Dec!K52+Jan!K52+Feb!K52+Mar!K52 -> 0 | L52: =Apr!L52+May!L52+Jun!L52+Jul!L52+Aug!L52+Sep!L52+Oct!L52+Nov!L52+Dec!L52+Jan!L52+Feb!L52+Mar!L52 -> 0 | M52: =Apr!M52+May!M52+Jun!M52+Jul!M52+Aug!M52+Sep!M52+Oct!M52+Nov!M52+Dec!M52+Jan!M52+Feb!M52+Mar!M52 -> 0 | N52: =Apr!N52+May!N52+Jun!N52+Jul!N52+Aug!N52+Sep!N52+Oct!N52+Nov!N52+Dec!N52+Jan!N52+Feb!N52+Mar!N52 -> 0 | O52: =SUM(K52:N52) -> 0 | P52: =Apr!P52+May!P52+Jun!P52+Jul!P52+Aug!P52+Sep!P52+Oct!P52+Nov!P52+Dec!P52+Jan!P52+Feb!P52+Mar!P52 -> 0 | Q52: =J52+O52+P52 -> 0 | R52: =IF(H52="Exempt",0,ROUND((J52*H52/100)-SUM(K52:M52),2)) -> 0 | T52: =Apr!T52+May!T52+Jun!T52+Jul!T52+Aug!T52+Sep!T52+Oct!T52+Nov!T52+Dec!T52+Jan!T52+Feb!T52+Mar!T52 -> 0 | U52: =Apr!U52+May!U52+Jun!U52+Jul!U52+Aug!U52+Sep!U52+Oct!U52+Nov!U52+Dec!U52+Jan!U52+Feb!U52+Mar!U52 -> 0 | V52: =Apr!V52+May!V52+Jun!V52+Jul!V52+Aug!V52+Sep!V52+Oct!V52+Nov!V52+Dec!V52+Jan!V52+Feb!V52+Mar!V52 -> 0 | W52: =Apr!W52+May!W52+Jun!W52+Jul!W52+Aug!W52+Sep!W52+Oct!W52+Nov!W52+Dec!W52+Jan!W52+Feb!W52+Mar!W52 -> 0 | X52: =Apr!X52+May!X52+Jun!X52+Jul!X52+Aug!X52+Sep!X52+Oct!X52+Nov!X52+Dec!X52+Jan!X52+Feb!X52+Mar!X52 -> 0 | Y52: =SUM(U52:X52) -> 0 | Z52: =Apr!Z52+May!Z52+Jun!Z52+Jul!Z52+Aug!Z52+Sep!Z52+Oct!Z52+Nov!Z52+Dec!Z52+Jan!Z52+Feb!Z52+Mar!Z52 -> 0 | AA52: =T52+Y52+Z52 -> 0 | AB52: =IF(H52="Exempt",0,ROUND((T52*H52/100)-SUM(U52:W52),2)) -> 0 | AD52: =Apr!AD52+May!AD52+Jun!AD52+Jul!AD52+Aug!AD52+Sep!AD52+Oct!AD52+Nov!AD52+Dec!AD52+Jan!AD52+Feb!AD52+Mar!AD52 -> 0 | AE52: =Apr!AE52+May!AE52+Jun!AE52+Jul!AE52+Aug!AE52+Sep!AE52+Oct!AE52+Nov!AE52+Dec!AE52+Jan!AE52+Feb!AE52+Mar!AE52 -> 0 | AF52: =Apr!AF52+May!AF52+Jun!AF52+Jul!AF52+Aug!AF52+Sep!AF52+Oct!AF52+Nov!AF52+Dec!AF52+Jan!AF52+Feb!AF52+Mar!AF52 -> 0 | AG52: =Apr!AG52+May!AG52+Jun!AG52+Jul!AG52+Aug!AG52+Sep!AG52+Oct!AG52+Nov!AG52+Dec!AG52+Jan!AG52+Feb!AG52+Mar!AG52 -> 0 | AI52: =SUM(AE52:AH52) -> 0 | AJ52: =Apr!AJ52+May!AJ52+Jun!AJ52+Jul!AJ52+Aug!AJ52+Sep!AJ52+Oct!AJ52+Nov!AJ52+Dec!AJ52+Jan!AJ52+Feb!AJ52+Mar!AJ52 -> 0 | AK52: =AD52+AI52+AJ52 -> 0 | AL52: =IF(H52="Exempt",0,ROUND((AD52*H52/100)-SUM(AE52:AG52),2)) -> 0
A53: =+A52+1 -> 38 | J53: =Apr!J53+May!J53+Jun!J53+Jul!J53+Aug!J53+Sep!J53+Oct!J53+Nov!J53+Dec!J53+Jan!J53+Feb!J53+Mar!J53 -> 0 | K53: =Apr!K53+May!K53+Jun!K53+Jul!K53+Aug!K53+Sep!K53+Oct!K53+Nov!K53+Dec!K53+Jan!K53+Feb!K53+Mar!K53 -> 0 | L53: =Apr!L53+May!L53+Jun!L53+Jul!L53+Aug!L53+Sep!L53+Oct!L53+Nov!L53+Dec!L53+Jan!L53+Feb!L53+Mar!L53 -> 0 | M53: =Apr!M53+May!M53+Jun!M53+Jul!M53+Aug!M53+Sep!M53+Oct!M53+Nov!M53+Dec!M53+Jan!M53+Feb!M53+Mar!M53 -> 0 | N53: =Apr!N53+May!N53+Jun!N53+Jul!N53+Aug!N53+Sep!N53+Oct!N53+Nov!N53+Dec!N53+Jan!N53+Feb!N53+Mar!N53 -> 0 | O53: =SUM(K53:N53) -> 0 | P53: =Apr!P53+May!P53+Jun!P53+Jul!P53+Aug!P53+Sep!P53+Oct!P53+Nov!P53+Dec!P53+Jan!P53+Feb!P53+Mar!P53 -> 0 | Q53: =J53+O53+P53 -> 0 | R53: =IF(H53="Exempt",0,ROUND((J53*H53/100)-SUM(K53:M53),2)) -> 0 | T53: =Apr!T53+May!T53+Jun!T53+Jul!T53+Aug!T53+Sep!T53+Oct!T53+Nov!T53+Dec!T53+Jan!T53+Feb!T53+Mar!T53 -> 0 | U53: =Apr!U53+May!U53+Jun!U53+Jul!U53+Aug!U53+Sep!U53+Oct!U53+Nov!U53+Dec!U53+Jan!U53+Feb!U53+Mar!U53 -> 0 | V53: =Apr!V53+May!V53+Jun!V53+Jul!V53+Aug!V53+Sep!V53+Oct!V53+Nov!V53+Dec!V53+Jan!V53+Feb!V53+Mar!V53 -> 0 | W53: =Apr!W53+May!W53+Jun!W53+Jul!W53+Aug!W53+Sep!W53+Oct!W53+Nov!W53+Dec!W53+Jan!W53+Feb!W53+Mar!W53 -> 0 | X53: =Apr!X53+May!X53+Jun!X53+Jul!X53+Aug!X53+Sep!X53+Oct!X53+Nov!X53+Dec!X53+Jan!X53+Feb!X53+Mar!X53 -> 0 | Y53: =SUM(U53:X53) -> 0 | Z53: =Apr!Z53+May!Z53+Jun!Z53+Jul!Z53+Aug!Z53+Sep!Z53+Oct!Z53+Nov!Z53+Dec!Z53+Jan!Z53+Feb!Z53+Mar!Z53 -> 0 | AA53: =T53+Y53+Z53 -> 0 | AB53: =IF(H53="Exempt",0,ROUND((T53*H53/100)-SUM(U53:W53),2)) -> 0 | AD53: =Apr!AD53+May!AD53+Jun!AD53+Jul!AD53+Aug!AD53+Sep!AD53+Oct!AD53+Nov!AD53+Dec!AD53+Jan!AD53+Feb!AD53+Mar!AD53 -> 0 | AE53: =Apr!AE53+May!AE53+Jun!AE53+Jul!AE53+Aug!AE53+Sep!AE53+Oct!AE53+Nov!AE53+Dec!AE53+Jan!AE53+Feb!AE53+Mar!AE53 -> 0 | AF53: =Apr!AF53+May!AF53+Jun!AF53+Jul!AF53+Aug!AF53+Sep!AF53+Oct!AF53+Nov!AF53+Dec!AF53+Jan!AF53+Feb!AF53+Mar!AF53 -> 0 | AG53: =Apr!AG53+May!AG53+Jun!AG53+Jul!AG53+Aug!AG53+Sep!AG53+Oct!AG53+Nov!AG53+Dec!AG53+Jan!AG53+Feb!AG53+Mar!AG53 -> 0 | AI53: =SUM(AE53:AH53) -> 0 | AJ53: =Apr!AJ53+May!AJ53+Jun!AJ53+Jul!AJ53+Aug!AJ53+Sep!AJ53+Oct!AJ53+Nov!AJ53+Dec!AJ53+Jan!AJ53+Feb!AJ53+Mar!AJ53 -> 0 | AK53: =AD53+AI53+AJ53 -> 0 | AL53: =IF(H53="Exempt",0,ROUND((AD53*H53/100)-SUM(AE53:AG53),2)) -> 0
A54: =+A53+1 -> 39 | J54: =Apr!J54+May!J54+Jun!J54+Jul!J54+Aug!J54+Sep!J54+Oct!J54+Nov!J54+Dec!J54+Jan!J54+Feb!J54+Mar!J54 -> 0 | K54: =Apr!K54+May!K54+Jun!K54+Jul!K54+Aug!K54+Sep!K54+Oct!K54+Nov!K54+Dec!K54+Jan!K54+Feb!K54+Mar!K54 -> 0 | L54: =Apr!L54+May!L54+Jun!L54+Jul!L54+Aug!L54+Sep!L54+Oct!L54+Nov!L54+Dec!L54+Jan!L54+Feb!L54+Mar!L54 -> 0 | M54: =Apr!M54+May!M54+Jun!M54+Jul!M54+Aug!M54+Sep!M54+Oct!M54+Nov!M54+Dec!M54+Jan!M54+Feb!M54+Mar!M54 -> 0 | N54: =Apr!N54+May!N54+Jun!N54+Jul!N54+Aug!N54+Sep!N54+Oct!N54+Nov!N54+Dec!N54+Jan!N54+Feb!N54+Mar!N54 -> 0 | O54: =SUM(K54:N54) -> 0 | P54: =Apr!P54+May!P54+Jun!P54+Jul!P54+Aug!P54+Sep!P54+Oct!P54+Nov!P54+Dec!P54+Jan!P54+Feb!P54+Mar!P54 -> 0 | Q54: =J54+O54+P54 -> 0 | R54: =IF(H54="Exempt",0,ROUND((J54*H54/100)-SUM(K54:M54),2)) -> 0 | T54: =Apr!T54+May!T54+Jun!T54+Jul!T54+Aug!T54+Sep!T54+Oct!T54+Nov!T54+Dec!T54+Jan!T54+Feb!T54+Mar!T54 -> 0 | U54: =Apr!U54+May!U54+Jun!U54+Jul!U54+Aug!U54+Sep!U54+Oct!U54+Nov!U54+Dec!U54+Jan!U54+Feb!U54+Mar!U54 -> 0 | V54: =Apr!V54+May!V54+Jun!V54+Jul!V54+Aug!V54+Sep!V54+Oct!V54+Nov!V54+Dec!V54+Jan!V54+Feb!V54+Mar!V54 -> 0 | W54: =Apr!W54+May!W54+Jun!W54+Jul!W54+Aug!W54+Sep!W54+Oct!W54+Nov!W54+Dec!W54+Jan!W54+Feb!W54+Mar!W54 -> 0 | X54: =Apr!X54+May!X54+Jun!X54+Jul!X54+Aug!X54+Sep!X54+Oct!X54+Nov!X54+Dec!X54+Jan!X54+Feb!X54+Mar!X54 -> 0 | Y54: =SUM(U54:X54) -> 0 | Z54: =Apr!Z54+May!Z54+Jun!Z54+Jul!Z54+Aug!Z54+Sep!Z54+Oct!Z54+Nov!Z54+Dec!Z54+Jan!Z54+Feb!Z54+Mar!Z54 -> 0 | AA54: =T54+Y54+Z54 -> 0 | AB54: =IF(H54="Exempt",0,ROUND((T54*H54/100)-SUM(U54:W54),2)) -> 0 | AD54: =Apr!AD54+May!AD54+Jun!AD54+Jul!AD54+Aug!AD54+Sep!AD54+Oct!AD54+Nov!AD54+Dec!AD54+Jan!AD54+Feb!AD54+Mar!AD54 -> 0 | AE54: =Apr!AE54+May!AE54+Jun!AE54+Jul!AE54+Aug!AE54+Sep!AE54+Oct!AE54+Nov!AE54+Dec!AE54+Jan!AE54+Feb!AE54+Mar!AE54 -> 0 | AF54: =Apr!AF54+May!AF54+Jun!AF54+Jul!AF54+Aug!AF54+Sep!AF54+Oct!AF54+Nov!AF54+Dec!AF54+Jan!AF54+Feb!AF54+Mar!AF54 -> 0 | AG54: =Apr!AG54+May!AG54+Jun!AG54+Jul!AG54+Aug!AG54+Sep!AG54+Oct!AG54+Nov!AG54+Dec!AG54+Jan!AG54+Feb!AG54+Mar!AG54 -> 0 | AI54: =SUM(AE54:AH54) -> 0 | AJ54: =Apr!AJ54+May!AJ54+Jun!AJ54+Jul!AJ54+Aug!AJ54+Sep!AJ54+Oct!AJ54+Nov!AJ54+Dec!AJ54+Jan!AJ54+Feb!AJ54+Mar!AJ54 -> 0 | AK54: =AD54+AI54+AJ54 -> 0 | AL54: =IF(H54="Exempt",0,ROUND((AD54*H54/100)-SUM(AE54:AG54),2)) -> 0
A55: =+A54+1 -> 40 | J55: =Apr!J55+May!J55+Jun!J55+Jul!J55+Aug!J55+Sep!J55+Oct!J55+Nov!J55+Dec!J55+Jan!J55+Feb!J55+Mar!J55 -> 0 | K55: =Apr!K55+May!K55+Jun!K55+Jul!K55+Aug!K55+Sep!K55+Oct!K55+Nov!K55+Dec!K55+Jan!K55+Feb!K55+Mar!K55 -> 0 | L55: =Apr!L55+May!L55+Jun!L55+Jul!L55+Aug!L55+Sep!L55+Oct!L55+Nov!L55+Dec!L55+Jan!L55+Feb!L55+Mar!L55 -> 0 | M55: =Apr!M55+May!M55+Jun!M55+Jul!M55+Aug!M55+Sep!M55+Oct!M55+Nov!M55+Dec!M55+Jan!M55+Feb!M55+Mar!M55 -> 0 | N55: =Apr!N55+May!N55+Jun!N55+Jul!N55+Aug!N55+Sep!N55+Oct!N55+Nov!N55+Dec!N55+Jan!N55+Feb!N55+Mar!N55 -> 0 | O55: =SUM(K55:N55) -> 0 | P55: =Apr!P55+May!P55+Jun!P55+Jul!P55+Aug!P55+Sep!P55+Oct!P55+Nov!P55+Dec!P55+Jan!P55+Feb!P55+Mar!P55 -> 0 | Q55: =J55+O55+P55 -> 0 | R55: =IF(H55="Exempt",0,ROUND((J55*H55/100)-SUM(K55:M55),2)) -> 0 | T55: =Apr!T55+May!T55+Jun!T55+Jul!T55+Aug!T55+Sep!T55+Oct!T55+Nov!T55+Dec!T55+Jan!T55+Feb!T55+Mar!T55 -> 0 | U55: =Apr!U55+May!U55+Jun!U55+Jul!U55+Aug!U55+Sep!U55+Oct!U55+Nov!U55+Dec!U55+Jan!U55+Feb!U55+Mar!U55 -> 0 | V55: =Apr!V55+May!V55+Jun!V55+Jul!V55+Aug!V55+Sep!V55+Oct!V55+Nov!V55+Dec!V55+Jan!V55+Feb!V55+Mar!V55 -> 0 | W55: =Apr!W55+May!W55+Jun!W55+Jul!W55+Aug!W55+Sep!W55+Oct!W55+Nov!W55+Dec!W55+Jan!W55+Feb!W55+Mar!W55 -> 0 | X55: =Apr!X55+May!X55+Jun!X55+Jul!X55+Aug!X55+Sep!X55+Oct!X55+Nov!X55+Dec!X55+Jan!X55+Feb!X55+Mar!X55 -> 0 | Y55: =SUM(U55:X55) -> 0 | Z55: =Apr!Z55+May!Z55+Jun!Z55+Jul!Z55+Aug!Z55+Sep!Z55+Oct!Z55+Nov!Z55+Dec!Z55+Jan!Z55+Feb!Z55+Mar!Z55 -> 0 | AA55: =T55+Y55+Z55 -> 0 | AB55: =IF(H55="Exempt",0,ROUND((T55*H55/100)-SUM(U55:W55),2)) -> 0 | AD55: =Apr!AD55+May!AD55+Jun!AD55+Jul!AD55+Aug!AD55+Sep!AD55+Oct!AD55+Nov!AD55+Dec!AD55+Jan!AD55+Feb!AD55+Mar!AD55 -> 0 | AE55: =Apr!AE55+May!AE55+Jun!AE55+Jul!AE55+Aug!AE55+Sep!AE55+Oct!AE55+Nov!AE55+Dec!AE55+Jan!AE55+Feb!AE55+Mar!AE55 -> 0 | AF55: =Apr!AF55+May!AF55+Jun!AF55+Jul!AF55+Aug!AF55+Sep!AF55+Oct!AF55+Nov!AF55+Dec!AF55+Jan!AF55+Feb!AF55+Mar!AF55 -> 0 | AG55: =Apr!AG55+May!AG55+Jun!AG55+Jul!AG55+Aug!AG55+Sep!AG55+Oct!AG55+Nov!AG55+Dec!AG55+Jan!AG55+Feb!AG55+Mar!AG55 -> 0 | AI55: =SUM(AE55:AH55) -> 0 | AJ55: =Apr!AJ55+May!AJ55+Jun!AJ55+Jul!AJ55+Aug!AJ55+Sep!AJ55+Oct!AJ55+Nov!AJ55+Dec!AJ55+Jan!AJ55+Feb!AJ55+Mar!AJ55 -> 0 | AK55: =AD55+AI55+AJ55 -> 0 | AL55: =IF(H55="Exempt",0,ROUND((AD55*H55/100)-SUM(AE55:AG55),2)) -> 0
A56: =+A55+1 -> 41 | J56: =Apr!J56+May!J56+Jun!J56+Jul!J56+Aug!J56+Sep!J56+Oct!J56+Nov!J56+Dec!J56+Jan!J56+Feb!J56+Mar!J56 -> 0 | K56: =Apr!K56+May!K56+Jun!K56+Jul!K56+Aug!K56+Sep!K56+Oct!K56+Nov!K56+Dec!K56+Jan!K56+Feb!K56+Mar!K56 -> 0 | L56: =Apr!L56+May!L56+Jun!L56+Jul!L56+Aug!L56+Sep!L56+Oct!L56+Nov!L56+Dec!L56+Jan!L56+Feb!L56+Mar!L56 -> 0 | M56: =Apr!M56+May!M56+Jun!M56+Jul!M56+Aug!M56+Sep!M56+Oct!M56+Nov!M56+Dec!M56+Jan!M56+Feb!M56+Mar!M56 -> 0 | N56: =Apr!N56+May!N56+Jun!N56+Jul!N56+Aug!N56+Sep!N56+Oct!N56+Nov!N56+Dec!N56+Jan!N56+Feb!N56+Mar!N56 -> 0 | O56: =SUM(K56:N56) -> 0 | P56: =Apr!P56+May!P56+Jun!P56+Jul!P56+Aug!P56+Sep!P56+Oct!P56+Nov!P56+Dec!P56+Jan!P56+Feb!P56+Mar!P56 -> 0 | Q56: =J56+O56+P56 -> 0 | R56: =IF(H56="Exempt",0,ROUND((J56*H56/100)-SUM(K56:M56),2)) -> 0 | T56: =Apr!T56+May!T56+Jun!T56+Jul!T56+Aug!T56+Sep!T56+Oct!T56+Nov!T56+Dec!T56+Jan!T56+Feb!T56+Mar!T56 -> 0 | U56: =Apr!U56+May!U56+Jun!U56+Jul!U56+Aug!U56+Sep!U56+Oct!U56+Nov!U56+Dec!U56+Jan!U56+Feb!U56+Mar!U56 -> 0 | V56: =Apr!V56+May!V56+Jun!V56+Jul!V56+Aug!V56+Sep!V56+Oct!V56+Nov!V56+Dec!V56+Jan!V56+Feb!V56+Mar!V56 -> 0 | W56: =Apr!W56+May!W56+Jun!W56+Jul!W56+Aug!W56+Sep!W56+Oct!W56+Nov!W56+Dec!W56+Jan!W56+Feb!W56+Mar!W56 -> 0 | X56: =Apr!X56+May!X56+Jun!X56+Jul!X56+Aug!X56+Sep!X56+Oct!X56+Nov!X56+Dec!X56+Jan!X56+Feb!X56+Mar!X56 -> 0 | Y56: =SUM(U56:X56) -> 0 | Z56: =Apr!Z56+May!Z56+Jun!Z56+Jul!Z56+Aug!Z56+Sep!Z56+Oct!Z56+Nov!Z56+Dec!Z56+Jan!Z56+Feb!Z56+Mar!Z56 -> 0 | AA56: =T56+Y56+Z56 -> 0 | AB56: =IF(H56="Exempt",0,ROUND((T56*H56/100)-SUM(U56:W56),2)) -> 0 | AD56: =Apr!AD56+May!AD56+Jun!AD56+Jul!AD56+Aug!AD56+Sep!AD56+Oct!AD56+Nov!AD56+Dec!AD56+Jan!AD56+Feb!AD56+Mar!AD56 -> 0 | AE56: =Apr!AE56+May!AE56+Jun!AE56+Jul!AE56+Aug!AE56+Sep!AE56+Oct!AE56+Nov!AE56+Dec!AE56+Jan!AE56+Feb!AE56+Mar!AE56 -> 0 | AF56: =Apr!AF56+May!AF56+Jun!AF56+Jul!AF56+Aug!AF56+Sep!AF56+Oct!AF56+Nov!AF56+Dec!AF56+Jan!AF56+Feb!AF56+Mar!AF56 -> 0 | AG56: =Apr!AG56+May!AG56+Jun!AG56+Jul!AG56+Aug!AG56+Sep!AG56+Oct!AG56+Nov!AG56+Dec!AG56+Jan!AG56+Feb!AG56+Mar!AG56 -> 0 | AI56: =SUM(AE56:AH56) -> 0 | AJ56: =Apr!AJ56+May!AJ56+Jun!AJ56+Jul!AJ56+Aug!AJ56+Sep!AJ56+Oct!AJ56+Nov!AJ56+Dec!AJ56+Jan!AJ56+Feb!AJ56+Mar!AJ56 -> 0 | AK56: =AD56+AI56+AJ56 -> 0 | AL56: =IF(H56="Exempt",0,ROUND((AD56*H56/100)-SUM(AE56:AG56),2)) -> 0
... A59: =+A58+1 -> 44 | J59: =Apr!J59+May!J59+Jun!J59+Jul!J59+Aug!J59+Sep!J59+Oct!J59+Nov!J59+Dec!J59+Jan!J59+Feb!J59+Mar!J59 -> 0 | K59: =Apr!K59+May!K59+Jun!K59+Jul!K59+Aug!K59+Sep!K59+Oct!K59+Nov!K59+Dec!K59+Jan!K59+Feb!K59+Mar!K59 -> 0 | L59: =Apr!L59+May!L59+Jun!L59+Jul!L59+Aug!L59+Sep!L59+Oct!L59+Nov!L59+Dec!L59+Jan!L59+Feb!L59+Mar!L59 -> 0 | M59: =Apr!M59+May!M59+Jun!M59+Jul!M59+Aug!M59+Sep!M59+Oct!M59+Nov!M59+Dec!M59+Jan!M59+Feb!M59+Mar!M59 -> 0 | N59: =Apr!N59+May!N59+Jun!N59+Jul!N59+Aug!N59+Sep!N59+Oct!N59+Nov!N59+Dec!N59+Jan!N59+Feb!N59+Mar!N59 -> 0 | O59: =SUM(K59:N59) -> 0 | P59: =Apr!P59+May!P59+Jun!P59+Jul!P59+Aug!P59+Sep!P59+Oct!P59+Nov!P59+Dec!P59+Jan!P59+Feb!P59+Mar!P59 -> 0 | Q59: =J59+O59+P59 -> 0 | R59: =IF(H59="Exempt",0,ROUND((J59*H59/100)-SUM(K59:M59),2)) -> 0 | T59: =Apr!T59+May!T59+Jun!T59+Jul!T59+Aug!T59+Sep!T59+Oct!T59+Nov!T59+Dec!T59+Jan!T59+Feb!T59+Mar!T59 -> 0 | U59: =Apr!U59+May!U59+Jun!U59+Jul!U59+Aug!U59+Sep!U59+Oct!U59+Nov!U59+Dec!U59+Jan!U59+Feb!U59+Mar!U59 -> 0 | V59: =Apr!V59+May!V59+Jun!V59+Jul!V59+Aug!V59+Sep!V59+Oct!V59+Nov!V59+Dec!V59+Jan!V59+Feb!V59+Mar!V59 -> 0 | W59: =Apr!W59+May!W59+Jun!W59+Jul!W59+Aug!W59+Sep!W59+Oct!W59+Nov!W59+Dec!W59+Jan!W59+Feb!W59+Mar!W59 -> 0 | X59: =Apr!X59+May!X59+Jun!X59+Jul!X59+Aug!X59+Sep!X59+Oct!X59+Nov!X59+Dec!X59+Jan!X59+Feb!X59+Mar!X59 -> 0 | Y59: =SUM(U59:X59) -> 0 | Z59: =Apr!Z59+May!Z59+Jun!Z59+Jul!Z59+Aug!Z59+Sep!Z59+Oct!Z59+Nov!Z59+Dec!Z59+Jan!Z59+Feb!Z59+Mar!Z59 -> 0 | AA59: =T59+Y59+Z59 -> 0 | AB59: =IF(H59="Exempt",0,ROUND((T59*H59/100)-SUM(U59:W59),2)) -> 0 | AD59: =Apr!AD59+May!AD59+Jun!AD59+Jul!AD59+Aug!AD59+Sep!AD59+Oct!AD59+Nov!AD59+Dec!AD59+Jan!AD59+Feb!AD59+Mar!AD59 -> 0 | AE59: =Apr!AE59+May!AE59+Jun!AE59+Jul!AE59+Aug!AE59+Sep!AE59+Oct!AE59+Nov!AE59+Dec!AE59+Jan!AE59+Feb!AE59+Mar!AE59 -> 0 | AF59: =Apr!AF59+May!AF59+Jun!AF59+Jul!AF59+Aug!AF59+Sep!AF59+Oct!AF59+Nov!AF59+Dec!AF59+Jan!AF59+Feb!AF59+Mar!AF59 -> 0 | AG59: =Apr!AG59+May!AG59+Jun!AG59+Jul!AG59+Aug!AG59+Sep!AG59+Oct!AG59+Nov!AG59+Dec!AG59+Jan!AG59+Feb!AG59+Mar!AG59 -> 0 | AI59: =SUM(AE59:AH59) -> 0 | AJ59: =Apr!AJ59+May!AJ59+Jun!AJ59+Jul!AJ59+Aug!AJ59+Sep!AJ59+Oct!AJ59+Nov!AJ59+Dec!AJ59+Jan!AJ59+Feb!AJ59+Mar!AJ59 -> 0 | AK59: =AD59+AI59+AJ59 -> 0 | AL59: =IF(H59="Exempt",0,ROUND((AD59*H59/100)-SUM(AE59:AG59),2)) -> 0
A60: =+A59+1 -> 45 | B60: Sales | C60: DISCOUNT | D60: Materials | E60: Registered | F60: Credit Note | H60: 5 | J60: =Apr!J60+May!J60+Jun!J60+Jul!J60+Aug!J60+Sep!J60+Oct!J60+Nov!J60+Dec!J60+Jan!J60+Feb!J60+Mar!J60 -> 0 | K60: =Apr!K60+May!K60+Jun!K60+Jul!K60+Aug!K60+Sep!K60+Oct!K60+Nov!K60+Dec!K60+Jan!K60+Feb!K60+Mar!K60 -> 0 | L60: =Apr!L60+May!L60+Jun!L60+Jul!L60+Aug!L60+Sep!L60+Oct!L60+Nov!L60+Dec!L60+Jan!L60+Feb!L60+Mar!L60 -> 0 | M60: =Apr!M60+May!M60+Jun!M60+Jul!M60+Aug!M60+Sep!M60+Oct!M60+Nov!M60+Dec!M60+Jan!M60+Feb!M60+Mar!M60 -> 0 | N60: =Apr!N60+May!N60+Jun!N60+Jul!N60+Aug!N60+Sep!N60+Oct!N60+Nov!N60+Dec!N60+Jan!N60+Feb!N60+Mar!N60 -> 0 | O60: =SUM(K60:N60) -> 0 | P60: =Apr!P60+May!P60+Jun!P60+Jul!P60+Aug!P60+Sep!P60+Oct!P60+Nov!P60+Dec!P60+Jan!P60+Feb!P60+Mar!P60 -> 0 | Q60: =J60+O60+P60 -> 0 | R60: =IF(H60="Exempt",0,ROUND((J60*H60/100)-SUM(K60:M60),2)) -> 0 | T60: =Apr!T60+May!T60+Jun!T60+Jul!T60+Aug!T60+Sep!T60+Oct!T60+Nov!T60+Dec!T60+Jan!T60+Feb!T60+Mar!T60 -> 0 | U60: =Apr!U60+May!U60+Jun!U60+Jul!U60+Aug!U60+Sep!U60+Oct!U60+Nov!U60+Dec!U60+Jan!U60+Feb!U60+Mar!U60 -> 0 | V60: =Apr!V60+May!V60+Jun!V60+Jul!V60+Aug!V60+Sep!V60+Oct!V60+Nov!V60+Dec!V60+Jan!V60+Feb!V60+Mar!V60 -> 0 | W60: =Apr!W60+May!W60+Jun!W60+Jul!W60+Aug!W60+Sep!W60+Oct!W60+Nov!W60+Dec!W60+Jan!W60+Feb!W60+Mar!W60 -> 0 | X60: =Apr!X60+May!X60+Jun!X60+Jul!X60+Aug!X60+Sep!X60+Oct!X60+Nov!X60+Dec!X60+Jan!X60+Feb!X60+Mar!X60 -> 0 | Y60: =SUM(U60:X60) -> 0 | Z60: =Apr!Z60+May!Z60+Jun!Z60+Jul!Z60+Aug!Z60+Sep!Z60+Oct!Z60+Nov!Z60+Dec!Z60+Jan!Z60+Feb!Z60+Mar!Z60 -> 0 | AA60: =T60+Y60+Z60 -> 0 | AB60: =IF(H60="Exempt",0,ROUND((T60*H60/100)-SUM(U60:W60),2)) -> 0 | AD60: =Apr!AD60+May!AD60+Jun!AD60+Jul!AD60+Aug!AD60+Sep!AD60+Oct!AD60+Nov!AD60+Dec!AD60+Jan!AD60+Feb!AD60+Mar!AD60 -> 0 | AE60: =Apr!AE60+May!AE60+Jun!AE60+Jul!AE60+Aug!AE60+Sep!AE60+Oct!AE60+Nov!AE60+Dec!AE60+Jan!AE60+Feb!AE60+Mar!AE60 -> 0 | AF60: =Apr!AF60+May!AF60+Jun!AF60+Jul!AF60+Aug!AF60+Sep!AF60+Oct!AF60+Nov!AF60+Dec!AF60+Jan!AF60+Feb!AF60+Mar!AF60 -> 0 | AG60: =Apr!AG60+May!AG60+Jun!AG60+Jul!AG60+Aug!AG60+Sep!AG60+Oct!AG60+Nov!AG60+Dec!AG60+Jan!AG60+Feb!AG60+Mar!AG60 -> 0 | AI60: =SUM(AE60:AH60) -> 0 | AJ60: =Apr!AJ60+May!AJ60+Jun!AJ60+Jul!AJ60+Aug!AJ60+Sep!AJ60+Oct!AJ60+Nov!AJ60+Dec!AJ60+Jan!AJ60+Feb!AJ60+Mar!AJ60 -> 0 | AK60: =AD60+AI60+AJ60 -> 0 | AL60: =IF(H60="Exempt",0,ROUND((AD60*H60/100)-SUM(AE60:AG60),2)) -> 0
A61: =+A60+1 -> 46 | B61: Sales | C61: DISCOUNT | D61: Materials | E61: Unregistered | F61: Credit Note | H61: 5 | J61: =Apr!J61+May!J61+Jun!J61+Jul!J61+Aug!J61+Sep!J61+Oct!J61+Nov!J61+Dec!J61+Jan!J61+Feb!J61+Mar!J61 -> 0 | K61: =Apr!K61+May!K61+Jun!K61+Jul!K61+Aug!K61+Sep!K61+Oct!K61+Nov!K61+Dec!K61+Jan!K61+Feb!K61+Mar!K61 -> 0 | L61: =Apr!L61+May!L61+Jun!L61+Jul!L61+Aug!L61+Sep!L61+Oct!L61+Nov!L61+Dec!L61+Jan!L61+Feb!L61+Mar!L61 -> 0 | M61: =Apr!M61+May!M61+Jun!M61+Jul!M61+Aug!M61+Sep!M61+Oct!M61+Nov!M61+Dec!M61+Jan!M61+Feb!M61+Mar!M61 -> 0 | N61: =Apr!N61+May!N61+Jun!N61+Jul!N61+Aug!N61+Sep!N61+Oct!N61+Nov!N61+Dec!N61+Jan!N61+Feb!N61+Mar!N61 -> 0 | O61: =SUM(K61:N61) -> 0 | P61: =Apr!P61+May!P61+Jun!P61+Jul!P61+Aug!P61+Sep!P61+Oct!P61+Nov!P61+Dec!P61+Jan!P61+Feb!P61+Mar!P61 -> 0 | Q61: =J61+O61+P61 -> 0 | R61: =IF(H61="Exempt",0,ROUND((J61*H61/100)-SUM(K61:M61),2)) -> 0 | T61: =Apr!T61+May!T61+Jun!T61+Jul!T61+Aug!T61+Sep!T61+Oct!T61+Nov!T61+Dec!T61+Jan!T61+Feb!T61+Mar!T61 -> 0 | U61: =Apr!U61+May!U61+Jun!U61+Jul!U61+Aug!U61+Sep!U61+Oct!U61+Nov!U61+Dec!U61+Jan!U61+Feb!U61+Mar!U61 -> 0 | V61: =Apr!V61+May!V61+Jun!V61+Jul!V61+Aug!V61+Sep!V61+Oct!V61+Nov!V61+Dec!V61+Jan!V61+Feb!V61+Mar!V61 -> 0 | W61: =Apr!W61+May!W61+Jun!W61+Jul!W61+Aug!W61+Sep!W61+Oct!W61+Nov!W61+Dec!W61+Jan!W61+Feb!W61+Mar!W61 -> 0 | X61: =Apr!X61+May!X61+Jun!X61+Jul!X61+Aug!X61+Sep!X61+Oct!X61+Nov!X61+Dec!X61+Jan!X61+Feb!X61+Mar!X61 -> 0 | Y61: =SUM(U61:X61) -> 0 | Z61: =Apr!Z61+May!Z61+Jun!Z61+Jul!Z61+Aug!Z61+Sep!Z61+Oct!Z61+Nov!Z61+Dec!Z61+Jan!Z61+Feb!Z61+Mar!Z61 -> 0 | AA61: =T61+Y61+Z61 -> 0 | AB61: =IF(H61="Exempt",0,ROUND((T61*H61/100)-SUM(U61:W61),2)) -> 0 | AD61: =Apr!AD61+May!AD61+Jun!AD61+Jul!AD61+Aug!AD61+Sep!AD61+Oct!AD61+Nov!AD61+Dec!AD61+Jan!AD61+Feb!AD61+Mar!AD61 -> 0 | AE61: =Apr!AE61+May!AE61+Jun!AE61+Jul!AE61+Aug!AE61+Sep!AE61+Oct!AE61+Nov!AE61+Dec!AE61+Jan!AE61+Feb!AE61+Mar!AE61 -> 0 | AF61: =Apr!AF61+May!AF61+Jun!AF61+Jul!AF61+Aug!AF61+Sep!AF61+Oct!AF61+Nov!AF61+Dec!AF61+Jan!AF61+Feb!AF61+Mar!AF61 -> 0 | AG61: =Apr!AG61+May!AG61+Jun!AG61+Jul!AG61+Aug!AG61+Sep!AG61+Oct!AG61+Nov!AG61+Dec!AG61+Jan!AG61+Feb!AG61+Mar!AG61 -> 0 | AI61: =SUM(AE61:AH61) -> 0 | AJ61: =Apr!AJ61+May!AJ61+Jun!AJ61+Jul!AJ61+Aug!AJ61+Sep!AJ61+Oct!AJ61+Nov!AJ61+Dec!AJ61+Jan!AJ61+Feb!AJ61+Mar!AJ61 -> 0 | AK61: =AD61+AI61+AJ61 -> 0 | AL61: =IF(H61="Exempt",0,ROUND((AD61*H61/100)-SUM(AE61:AG61),2)) -> 0
A62: =+A61+1 -> 47 | B62: Sales | C62: DISCOUNT | D62: Materials | E62: Composition | F62: Credit Note | H62: 5 | J62: =Apr!J62+May!J62+Jun!J62+Jul!J62+Aug!J62+Sep!J62+Oct!J62+Nov!J62+Dec!J62+Jan!J62+Feb!J62+Mar!J62 -> 0 | K62: =Apr!K62+May!K62+Jun!K62+Jul!K62+Aug!K62+Sep!K62+Oct!K62+Nov!K62+Dec!K62+Jan!K62+Feb!K62+Mar!K62 -> 0 | L62: =Apr!L62+May!L62+Jun!L62+Jul!L62+Aug!L62+Sep!L62+Oct!L62+Nov!L62+Dec!L62+Jan!L62+Feb!L62+Mar!L62 -> 0 | M62: =Apr!M62+May!M62+Jun!M62+Jul!M62+Aug!M62+Sep!M62+Oct!M62+Nov!M62+Dec!M62+Jan!M62+Feb!M62+Mar!M62 -> 0 | N62: =Apr!N62+May!N62+Jun!N62+Jul!N62+Aug!N62+Sep!N62+Oct!N62+Nov!N62+Dec!N62+Jan!N62+Feb!N62+Mar!N62 -> 0 | O62: =SUM(K62:N62) -> 0 | P62: =Apr!P62+May!P62+Jun!P62+Jul!P62+Aug!P62+Sep!P62+Oct!P62+Nov!P62+Dec!P62+Jan!P62+Feb!P62+Mar!P62 -> 0 | Q62: =J62+O62+P62 -> 0 | R62: =IF(H62="Exempt",0,ROUND((J62*H62/100)-SUM(K62:M62),2)) -> 0 | T62: =Apr!T62+May!T62+Jun!T62+Jul!T62+Aug!T62+Sep!T62+Oct!T62+Nov!T62+Dec!T62+Jan!T62+Feb!T62+Mar!T62 -> 0 | U62: =Apr!U62+May!U62+Jun!U62+Jul!U62+Aug!U62+Sep!U62+Oct!U62+Nov!U62+Dec!U62+Jan!U62+Feb!U62+Mar!U62 -> 0 | V62: =Apr!V62+May!V62+Jun!V62+Jul!V62+Aug!V62+Sep!V62+Oct!V62+Nov!V62+Dec!V62+Jan!V62+Feb!V62+Mar!V62 -> 0 | W62: =Apr!W62+May!W62+Jun!W62+Jul!W62+Aug!W62+Sep!W62+Oct!W62+Nov!W62+Dec!W62+Jan!W62+Feb!W62+Mar!W62 -> 0 | X62: =Apr!X62+May!X62+Jun!X62+Jul!X62+Aug!X62+Sep!X62+Oct!X62+Nov!X62+Dec!X62+Jan!X62+Feb!X62+Mar!X62 -> 0 | Y62: =SUM(U62:X62) -> 0 | Z62: =Apr!Z62+May!Z62+Jun!Z62+Jul!Z62+Aug!Z62+Sep!Z62+Oct!Z62+Nov!Z62+Dec!Z62+Jan!Z62+Feb!Z62+Mar!Z62 -> 0 | AA62: =T62+Y62+Z62 -> 0 | AB62: =IF(H62="Exempt",0,ROUND((T62*H62/100)-SUM(U62:W62),2)) -> 0 | AD62: =Apr!AD62+May!AD62+Jun!AD62+Jul!AD62+Aug!AD62+Sep!AD62+Oct!AD62+Nov!AD62+Dec!AD62+Jan!AD62+Feb!AD62+Mar!AD62 -> 0 | AE62: =Apr!AE62+May!AE62+Jun!AE62+Jul!AE62+Aug!AE62+Sep!AE62+Oct!AE62+Nov!AE62+Dec!AE62+Jan!AE62+Feb!AE62+Mar!AE62 -> 0 | AF62: =Apr!AF62+May!AF62+Jun!AF62+Jul!AF62+Aug!AF62+Sep!AF62+Oct!AF62+Nov!AF62+Dec!AF62+Jan!AF62+Feb!AF62+Mar!AF62 -> 0 | AG62: =Apr!AG62+May!AG62+Jun!AG62+Jul!AG62+Aug!AG62+Sep!AG62+Oct!AG62+Nov!AG62+Dec!AG62+Jan!AG62+Feb!AG62+Mar!AG62 -> 0 | AI62: =SUM(AE62:AH62) -> 0 | AJ62: =Apr!AJ62+May!AJ62+Jun!AJ62+Jul!AJ62+Aug!AJ62+Sep!AJ62+Oct!AJ62+Nov!AJ62+Dec!AJ62+Jan!AJ62+Feb!AJ62+Mar!AJ62 -> 0 | AK62: =AD62+AI62+AJ62 -> 0 | AL62: =IF(H62="Exempt",0,ROUND((AD62*H62/100)-SUM(AE62:AG62),2)) -> 0
A63: =+A62+1 -> 48 | B63: Sales | C63: GOODS RETURN | D63: Materials | E63: Registered | F63: Credit Note | H63: 5 | J63: =Apr!J63+May!J63+Jun!J63+Jul!J63+Aug!J63+Sep!J63+Oct!J63+Nov!J63+Dec!J63+Jan!J63+Feb!J63+Mar!J63 -> 0 | K63: =Apr!K63+May!K63+Jun!K63+Jul!K63+Aug!K63+Sep!K63+Oct!K63+Nov!K63+Dec!K63+Jan!K63+Feb!K63+Mar!K63 -> 0 | L63: =Apr!L63+May!L63+Jun!L63+Jul!L63+Aug!L63+Sep!L63+Oct!L63+Nov!L63+Dec!L63+Jan!L63+Feb!L63+Mar!L63 -> 0 | M63: =Apr!M63+May!M63+Jun!M63+Jul!M63+Aug!M63+Sep!M63+Oct!M63+Nov!M63+Dec!M63+Jan!M63+Feb!M63+Mar!M63 -> 0 | N63: =Apr!N63+May!N63+Jun!N63+Jul!N63+Aug!N63+Sep!N63+Oct!N63+Nov!N63+Dec!N63+Jan!N63+Feb!N63+Mar!N63 -> 0 | O63: =SUM(K63:N63) -> 0 | P63: =Apr!P63+May!P63+Jun!P63+Jul!P63+Aug!P63+Sep!P63+Oct!P63+Nov!P63+Dec!P63+Jan!P63+Feb!P63+Mar!P63 -> 0 | Q63: =J63+O63+P63 -> 0 | R63: =IF(H63="Exempt",0,ROUND((J63*H63/100)-SUM(K63:M63),2)) -> 0 | T63: =Apr!T63+May!T63+Jun!T63+Jul!T63+Aug!T63+Sep!T63+Oct!T63+Nov!T63+Dec!T63+Jan!T63+Feb!T63+Mar!T63 -> 0 | U63: =Apr!U63+May!U63+Jun!U63+Jul!U63+Aug!U63+Sep!U63+Oct!U63+Nov!U63+Dec!U63+Jan!U63+Feb!U63+Mar!U63 -> 0 | V63: =Apr!V63+May!V63+Jun!V63+Jul!V63+Aug!V63+Sep!V63+Oct!V63+Nov!V63+Dec!V63+Jan!V63+Feb!V63+Mar!V63 -> 0 | W63: =Apr!W63+May!W63+Jun!W63+Jul!W63+Aug!W63+Sep!W63+Oct!W63+Nov!W63+Dec!W63+Jan!W63+Feb!W63+Mar!W63 -> 0 | X63: =Apr!X63+May!X63+Jun!X63+Jul!X63+Aug!X63+Sep!X63+Oct!X63+Nov!X63+Dec!X63+Jan!X63+Feb!X63+Mar!X63 -> 0 | Y63: =SUM(U63:X63) -> 0 | Z63: =Apr!Z63+May!Z63+Jun!Z63+Jul!Z63+Aug!Z63+Sep!Z63+Oct!Z63+Nov!Z63+Dec!Z63+Jan!Z63+Feb!Z63+Mar!Z63 -> 0 | AA63: =T63+Y63+Z63 -> 0 | AB63: =IF(H63="Exempt",0,ROUND((T63*H63/100)-SUM(U63:W63),2)) -> 0 | AD63: =Apr!AD63+May!AD63+Jun!AD63+Jul!AD63+Aug!AD63+Sep!AD63+Oct!AD63+Nov!AD63+Dec!AD63+Jan!AD63+Feb!AD63+Mar!AD63 -> 0 | AE63: =Apr!AE63+May!AE63+Jun!AE63+Jul!AE63+Aug!AE63+Sep!AE63+Oct!AE63+Nov!AE63+Dec!AE63+Jan!AE63+Feb!AE63+Mar!AE63 -> 0 | AF63: =Apr!AF63+May!AF63+Jun!AF63+Jul!AF63+Aug!AF63+Sep!AF63+Oct!AF63+Nov!AF63+Dec!AF63+Jan!AF63+Feb!AF63+Mar!AF63 -> 0 | AG63: =Apr!AG63+May!AG63+Jun!AG63+Jul!AG63+Aug!AG63+Sep!AG63+Oct!AG63+Nov!AG63+Dec!AG63+Jan!AG63+Feb!AG63+Mar!AG63 -> 0 | AI63: =SUM(AE63:AH63) -> 0 | AJ63: =Apr!AJ63+May!AJ63+Jun!AJ63+Jul!AJ63+Aug!AJ63+Sep!AJ63+Oct!AJ63+Nov!AJ63+Dec!AJ63+Jan!AJ63+Feb!AJ63+Mar!AJ63 -> 0 | AK63: =AD63+AI63+AJ63 -> 0 | AL63: =IF(H63="Exempt",0,ROUND((AD63*H63/100)-SUM(AE63:AG63),2)) -> 0
A64: =+A63+1 -> 49 | B64: Sales | C64: GOODS RETURN | D64: Materials | E64: Unregistered | F64: Credit Note | H64: 5 | J64: =Apr!J64+May!J64+Jun!J64+Jul!J64+Aug!J64+Sep!J64+Oct!J64+Nov!J64+Dec!J64+Jan!J64+Feb!J64+Mar!J64 -> 0 | K64: =Apr!K64+May!K64+Jun!K64+Jul!K64+Aug!K64+Sep!K64+Oct!K64+Nov!K64+Dec!K64+Jan!K64+Feb!K64+Mar!K64 -> 0 | L64: =Apr!L64+May!L64+Jun!L64+Jul!L64+Aug!L64+Sep!L64+Oct!L64+Nov!L64+Dec!L64+Jan!L64+Feb!L64+Mar!L64 -> 0 | M64: =Apr!M64+May!M64+Jun!M64+Jul!M64+Aug!M64+Sep!M64+Oct!M64+Nov!M64+Dec!M64+Jan!M64+Feb!M64+Mar!M64 -> 0 | N64: =Apr!N64+May!N64+Jun!N64+Jul!N64+Aug!N64+Sep!N64+Oct!N64+Nov!N64+Dec!N64+Jan!N64+Feb!N64+Mar!N64 -> 0 | O64: =SUM(K64:N64) -> 0 | P64: =Apr!P64+May!P64+Jun!P64+Jul!P64+Aug!P64+Sep!P64+Oct!P64+Nov!P64+Dec!P64+Jan!P64+Feb!P64+Mar!P64 -> 0 | Q64: =J64+O64+P64 -> 0 | R64: =IF(H64="Exempt",0,ROUND((J64*H64/100)-SUM(K64:M64),2)) -> 0 | T64: =Apr!T64+May!T64+Jun!T64+Jul!T64+Aug!T64+Sep!T64+Oct!T64+Nov!T64+Dec!T64+Jan!T64+Feb!T64+Mar!T64 -> 0 | U64: =Apr!U64+May!U64+Jun!U64+Jul!U64+Aug!U64+Sep!U64+Oct!U64+Nov!U64+Dec!U64+Jan!U64+Feb!U64+Mar!U64 -> 0 | V64: =Apr!V64+May!V64+Jun!V64+Jul!V64+Aug!V64+Sep!V64+Oct!V64+Nov!V64+Dec!V64+Jan!V64+Feb!V64+Mar!V64 -> 0 | W64: =Apr!W64+May!W64+Jun!W64+Jul!W64+Aug!W64+Sep!W64+Oct!W64+Nov!W64+Dec!W64+Jan!W64+Feb!W64+Mar!W64 -> 0 | X64: =Apr!X64+May!X64+Jun!X64+Jul!X64+Aug!X64+Sep!X64+Oct!X64+Nov!X64+Dec!X64+Jan!X64+Feb!X64+Mar!X64 -> 0 | Y64: =SUM(U64:X64) -> 0 | Z64: =Apr!Z64+May!Z64+Jun!Z64+Jul!Z64+Aug!Z64+Sep!Z64+Oct!Z64+Nov!Z64+Dec!Z64+Jan!Z64+Feb!Z64+Mar!Z64 -> 0 | AA64: =T64+Y64+Z64 -> 0 | AB64: =IF(H64="Exempt",0,ROUND((T64*H64/100)-SUM(U64:W64),2)) -> 0 | AD64: =Apr!AD64+May!AD64+Jun!AD64+Jul!AD64+Aug!AD64+Sep!AD64+Oct!AD64+Nov!AD64+Dec!AD64+Jan!AD64+Feb!AD64+Mar!AD64 -> 0 | AE64: =Apr!AE64+May!AE64+Jun!AE64+Jul!AE64+Aug!AE64+Sep!AE64+Oct!AE64+Nov!AE64+Dec!AE64+Jan!AE64+Feb!AE64+Mar!AE64 -> 0 | AF64: =Apr!AF64+May!AF64+Jun!AF64+Jul!AF64+Aug!AF64+Sep!AF64+Oct!AF64+Nov!AF64+Dec!AF64+Jan!AF64+Feb!AF64+Mar!AF64 -> 0 | AG64: =Apr!AG64+May!AG64+Jun!AG64+Jul!AG64+Aug!AG64+Sep!AG64+Oct!AG64+Nov!AG64+Dec!AG64+Jan!AG64+Feb!AG64+Mar!AG64 -> 0 | AI64: =SUM(AE64:AH64) -> 0 | AJ64: =Apr!AJ64+May!AJ64+Jun!AJ64+Jul!AJ64+Aug!AJ64+Sep!AJ64+Oct!AJ64+Nov!AJ64+Dec!AJ64+Jan!AJ64+Feb!AJ64+Mar!AJ64 -> 0 | AK64: =AD64+AI64+AJ64 -> 0 | AL64: =IF(H64="Exempt",0,ROUND((AD64*H64/100)-SUM(AE64:AG64),2)) -> 0
A65: =+A64+1 -> 50 | B65: Sales | C65: GOODS RETURN | D65: Materials | E65: Registered | F65: Credit Note | H65: 12 | J65: =Apr!J65+May!J65+Jun!J65+Jul!J65+Aug!J65+Sep!J65+Oct!J65+Nov!J65+Dec!J65+Jan!J65+Feb!J65+Mar!J65 -> 0 | K65: =Apr!K65+May!K65+Jun!K65+Jul!K65+Aug!K65+Sep!K65+Oct!K65+Nov!K65+Dec!K65+Jan!K65+Feb!K65+Mar!K65 -> 0 | L65: =Apr!L65+May!L65+Jun!L65+Jul!L65+Aug!L65+Sep!L65+Oct!L65+Nov!L65+Dec!L65+Jan!L65+Feb!L65+Mar!L65 -> 0 | M65: =Apr!M65+May!M65+Jun!M65+Jul!M65+Aug!M65+Sep!M65+Oct!M65+Nov!M65+Dec!M65+Jan!M65+Feb!M65+Mar!M65 -> 0 | N65: =Apr!N65+May!N65+Jun!N65+Jul!N65+Aug!N65+Sep!N65+Oct!N65+Nov!N65+Dec!N65+Jan!N65+Feb!N65+Mar!N65 -> 0 | O65: =SUM(K65:N65) -> 0 | P65: =Apr!P65+May!P65+Jun!P65+Jul!P65+Aug!P65+Sep!P65+Oct!P65+Nov!P65+Dec!P65+Jan!P65+Feb!P65+Mar!P65 -> 0 | Q65: =J65+O65+P65 -> 0 | R65: =IF(H65="Exempt",0,ROUND((J65*H65/100)-SUM(K65:M65),2)) -> 0 | T65: =Apr!T65+May!T65+Jun!T65+Jul!T65+Aug!T65+Sep!T65+Oct!T65+Nov!T65+Dec!T65+Jan!T65+Feb!T65+Mar!T65 -> 0 | U65: =Apr!U65+May!U65+Jun!U65+Jul!U65+Aug!U65+Sep!U65+Oct!U65+Nov!U65+Dec!U65+Jan!U65+Feb!U65+Mar!U65 -> 0 | V65: =Apr!V65+May!V65+Jun!V65+Jul!V65+Aug!V65+Sep!V65+Oct!V65+Nov!V65+Dec!V65+Jan!V65+Feb!V65+Mar!V65 -> 0 | W65: =Apr!W65+May!W65+Jun!W65+Jul!W65+Aug!W65+Sep!W65+Oct!W65+Nov!W65+Dec!W65+Jan!W65+Feb!W65+Mar!W65 -> 0 | X65: =Apr!X65+May!X65+Jun!X65+Jul!X65+Aug!X65+Sep!X65+Oct!X65+Nov!X65+Dec!X65+Jan!X65+Feb!X65+Mar!X65 -> 0 | Y65: =SUM(U65:X65) -> 0 | Z65: =Apr!Z65+May!Z65+Jun!Z65+Jul!Z65+Aug!Z65+Sep!Z65+Oct!Z65+Nov!Z65+Dec!Z65+Jan!Z65+Feb!Z65+Mar!Z65 -> 0 | AA65: =T65+Y65+Z65 -> 0 | AB65: =IF(H65="Exempt",0,ROUND((T65*H65/100)-SUM(U65:W65),2)) -> 0 | AD65: =Apr!AD65+May!AD65+Jun!AD65+Jul!AD65+Aug!AD65+Sep!AD65+Oct!AD65+Nov!AD65+Dec!AD65+Jan!AD65+Feb!AD65+Mar!AD65 -> 0 | AE65: =Apr!AE65+May!AE65+Jun!AE65+Jul!AE65+Aug!AE65+Sep!AE65+Oct!AE65+Nov!AE65+Dec!AE65+Jan!AE65+Feb!AE65+Mar!AE65 -> 0 | AF65: =Apr!AF65+May!AF65+Jun!AF65+Jul!AF65+Aug!AF65+Sep!AF65+Oct!AF65+Nov!AF65+Dec!AF65+Jan!AF65+Feb!AF65+Mar!AF65 -> 0 | AG65: =Apr!AG65+May!AG65+Jun!AG65+Jul!AG65+Aug!AG65+Sep!AG65+Oct!AG65+Nov!AG65+Dec!AG65+Jan!AG65+Feb!AG65+Mar!AG65 -> 0 | AI65: =SUM(AE65:AH65) -> 0 | AJ65: =Apr!AJ65+May!AJ65+Jun!AJ65+Jul!AJ65+Aug!AJ65+Sep!AJ65+Oct!AJ65+Nov!AJ65+Dec!AJ65+Jan!AJ65+Feb!AJ65+Mar!AJ65 -> 0 | AK65: =AD65+AI65+AJ65 -> 0 | AL65: =IF(H65="Exempt",0,ROUND((AD65*H65/100)-SUM(AE65:AG65),2)) -> 0
A66: =+A65+1 -> 51 | B66: Sales | C66: GOODS RETURN | D66: Materials | E66: Registered | F66: Credit Note | H66: 12 | J66: =Apr!J66+May!J66+Jun!J66+Jul!J66+Aug!J66+Sep!J66+Oct!J66+Nov!J66+Dec!J66+Jan!J66+Feb!J66+Mar!J66 -> 0 | K66: =Apr!K66+May!K66+Jun!K66+Jul!K66+Aug!K66+Sep!K66+Oct!K66+Nov!K66+Dec!K66+Jan!K66+Feb!K66+Mar!K66 -> 0 | L66: =Apr!L66+May!L66+Jun!L66+Jul!L66+Aug!L66+Sep!L66+Oct!L66+Nov!L66+Dec!L66+Jan!L66+Feb!L66+Mar!L66 -> 0 | M66: =Apr!M66+May!M66+Jun!M66+Jul!M66+Aug!M66+Sep!M66+Oct!M66+Nov!M66+Dec!M66+Jan!M66+Feb!M66+Mar!M66 -> 0 | N66: =Apr!N66+May!N66+Jun!N66+Jul!N66+Aug!N66+Sep!N66+Oct!N66+Nov!N66+Dec!N66+Jan!N66+Feb!N66+Mar!N66 -> 0 | O66: =SUM(K66:N66) -> 0 | P66: =Apr!P66+May!P66+Jun!P66+Jul!P66+Aug!P66+Sep!P66+Oct!P66+Nov!P66+Dec!P66+Jan!P66+Feb!P66+Mar!P66 -> 0 | Q66: =J66+O66+P66 -> 0 | R66: =IF(H66="Exempt",0,ROUND((J66*H66/100)-SUM(K66:M66),2)) -> 0 | T66: =Apr!T66+May!T66+Jun!T66+Jul!T66+Aug!T66+Sep!T66+Oct!T66+Nov!T66+Dec!T66+Jan!T66+Feb!T66+Mar!T66 -> 0 | U66: =Apr!U66+May!U66+Jun!U66+Jul!U66+Aug!U66+Sep!U66+Oct!U66+Nov!U66+Dec!U66+Jan!U66+Feb!U66+Mar!U66 -> 0 | V66: =Apr!V66+May!V66+Jun!V66+Jul!V66+Aug!V66+Sep!V66+Oct!V66+Nov!V66+Dec!V66+Jan!V66+Feb!V66+Mar!V66 -> 0 | W66: =Apr!W66+May!W66+Jun!W66+Jul!W66+Aug!W66+Sep!W66+Oct!W66+Nov!W66+Dec!W66+Jan!W66+Feb!W66+Mar!W66 -> 0 | X66: =Apr!X66+May!X66+Jun!X66+Jul!X66+Aug!X66+Sep!X66+Oct!X66+Nov!X66+Dec!X66+Jan!X66+Feb!X66+Mar!X66 -> 0 | Y66: =SUM(U66:X66) -> 0 | Z66: =Apr!Z66+May!Z66+Jun!Z66+Jul!Z66+Aug!Z66+Sep!Z66+Oct!Z66+Nov!Z66+Dec!Z66+Jan!Z66+Feb!Z66+Mar!Z66 -> 0 | AA66: =T66+Y66+Z66 -> 0 | AB66: =IF(H66="Exempt",0,ROUND((T66*H66/100)-SUM(U66:W66),2)) -> 0 | AD66: =Apr!AD66+May!AD66+Jun!AD66+Jul!AD66+Aug!AD66+Sep!AD66+Oct!AD66+Nov!AD66+Dec!AD66+Jan!AD66+Feb!AD66+Mar!AD66 -> 0 | AE66: =Apr!AE66+May!AE66+Jun!AE66+Jul!AE66+Aug!AE66+Sep!AE66+Oct!AE66+Nov!AE66+Dec!AE66+Jan!AE66+Feb!AE66+Mar!AE66 -> 0 | AF66: =Apr!AF66+May!AF66+Jun!AF66+Jul!AF66+Aug!AF66+Sep!AF66+Oct!AF66+Nov!AF66+Dec!AF66+Jan!AF66+Feb!AF66+Mar!AF66 -> 0 | AG66: =Apr!AG66+May!AG66+Jun!AG66+Jul!AG66+Aug!AG66+Sep!AG66+Oct!AG66+Nov!AG66+Dec!AG66+Jan!AG66+Feb!AG66+Mar!AG66 -> 0 | AI66: =SUM(AE66:AH66) -> 0 | AJ66: =Apr!AJ66+May!AJ66+Jun!AJ66+Jul!AJ66+Aug!AJ66+Sep!AJ66+Oct!AJ66+Nov!AJ66+Dec!AJ66+Jan!AJ66+Feb!AJ66+Mar!AJ66 -> 0 | AK66: =AD66+AI66+AJ66 -> 0 | AL66: =IF(H66="Exempt",0,ROUND((AD66*H66/100)-SUM(AE66:AG66),2)) -> 0
A67: =+A66+1 -> 52 | J67: =Apr!J67+May!J67+Jun!J67+Jul!J67+Aug!J67+Sep!J67+Oct!J67+Nov!J67+Dec!J67+Jan!J67+Feb!J67+Mar!J67 -> 0 | K67: =Apr!K67+May!K67+Jun!K67+Jul!K67+Aug!K67+Sep!K67+Oct!K67+Nov!K67+Dec!K67+Jan!K67+Feb!K67+Mar!K67 -> 0 | L67: =Apr!L67+May!L67+Jun!L67+Jul!L67+Aug!L67+Sep!L67+Oct!L67+Nov!L67+Dec!L67+Jan!L67+Feb!L67+Mar!L67 -> 0 | M67: =Apr!M67+May!M67+Jun!M67+Jul!M67+Aug!M67+Sep!M67+Oct!M67+Nov!M67+Dec!M67+Jan!M67+Feb!M67+Mar!M67 -> 0 | N67: =Apr!N67+May!N67+Jun!N67+Jul!N67+Aug!N67+Sep!N67+Oct!N67+Nov!N67+Dec!N67+Jan!N67+Feb!N67+Mar!N67 -> 0 | O67: =SUM(K67:N67) -> 0 | P67: =Apr!P67+May!P67+Jun!P67+Jul!P67+Aug!P67+Sep!P67+Oct!P67+Nov!P67+Dec!P67+Jan!P67+Feb!P67+Mar!P67 -> 0 | Q67: =J67+O67+P67 -> 0 | R67: =IF(H67="Exempt",0,ROUND((J67*H67/100)-SUM(K67:M67),2)) -> 0 | T67: =Apr!T67+May!T67+Jun!T67+Jul!T67+Aug!T67+Sep!T67+Oct!T67+Nov!T67+Dec!T67+Jan!T67+Feb!T67+Mar!T67 -> 0 | U67: =Apr!U67+May!U67+Jun!U67+Jul!U67+Aug!U67+Sep!U67+Oct!U67+Nov!U67+Dec!U67+Jan!U67+Feb!U67+Mar!U67 -> 0 | V67: =Apr!V67+May!V67+Jun!V67+Jul!V67+Aug!V67+Sep!V67+Oct!V67+Nov!V67+Dec!V67+Jan!V67+Feb!V67+Mar!V67 -> 0 | W67: =Apr!W67+May!W67+Jun!W67+Jul!W67+Aug!W67+Sep!W67+Oct!W67+Nov!W67+Dec!W67+Jan!W67+Feb!W67+Mar!W67 -> 0 | X67: =Apr!X67+May!X67+Jun!X67+Jul!X67+Aug!X67+Sep!X67+Oct!X67+Nov!X67+Dec!X67+Jan!X67+Feb!X67+Mar!X67 -> 0 | Y67: =SUM(U67:X67) -> 0 | Z67: =Apr!Z67+May!Z67+Jun!Z67+Jul!Z67+Aug!Z67+Sep!Z67+Oct!Z67+Nov!Z67+Dec!Z67+Jan!Z67+Feb!Z67+Mar!Z67 -> 0 | AA67: =T67+Y67+Z67 -> 0 | AB67: =IF(H67="Exempt",0,ROUND((T67*H67/100)-SUM(U67:W67),2)) -> 0 | AD67: =Apr!AD67+May!AD67+Jun!AD67+Jul!AD67+Aug!AD67+Sep!AD67+Oct!AD67+Nov!AD67+Dec!AD67+Jan!AD67+Feb!AD67+Mar!AD67 -> 0 | AE67: =Apr!AE67+May!AE67+Jun!AE67+Jul!AE67+Aug!AE67+Sep!AE67+Oct!AE67+Nov!AE67+Dec!AE67+Jan!AE67+Feb!AE67+Mar!AE67 -> 0 | AF67: =Apr!AF67+May!AF67+Jun!AF67+Jul!AF67+Aug!AF67+Sep!AF67+Oct!AF67+Nov!AF67+Dec!AF67+Jan!AF67+Feb!AF67+Mar!AF67 -> 0 | AG67: =Apr!AG67+May!AG67+Jun!AG67+Jul!AG67+Aug!AG67+Sep!AG67+Oct!AG67+Nov!AG67+Dec!AG67+Jan!AG67+Feb!AG67+Mar!AG67 -> 0 | AI67: =SUM(AE67:AH67) -> 0 | AJ67: =Apr!AJ67+May!AJ67+Jun!AJ67+Jul!AJ67+Aug!AJ67+Sep!AJ67+Oct!AJ67+Nov!AJ67+Dec!AJ67+Jan!AJ67+Feb!AJ67+Mar!AJ67 -> 0 | AK67: =AD67+AI67+AJ67 -> 0 | AL67: =IF(H67="Exempt",0,ROUND((AD67*H67/100)-SUM(AE67:AG67),2)) -> 0
A68: =+A67+1 -> 53 | J68: =Apr!J68+May!J68+Jun!J68+Jul!J68+Aug!J68+Sep!J68+Oct!J68+Nov!J68+Dec!J68+Jan!J68+Feb!J68+Mar!J68 -> 0 | K68: =Apr!K68+May!K68+Jun!K68+Jul!K68+Aug!K68+Sep!K68+Oct!K68+Nov!K68+Dec!K68+Jan!K68+Feb!K68+Mar!K68 -> 0 | L68: =Apr!L68+May!L68+Jun!L68+Jul!L68+Aug!L68+Sep!L68+Oct!L68+Nov!L68+Dec!L68+Jan!L68+Feb!L68+Mar!L68 -> 0 | M68: =Apr!M68+May!M68+Jun!M68+Jul!M68+Aug!M68+Sep!M68+Oct!M68+Nov!M68+Dec!M68+Jan!M68+Feb!M68+Mar!M68 -> 0 | N68: =Apr!N68+May!N68+Jun!N68+Jul!N68+Aug!N68+Sep!N68+Oct!N68+Nov!N68+Dec!N68+Jan!N68+Feb!N68+Mar!N68 -> 0 | O68: =SUM(K68:N68) -> 0 | P68: =Apr!P68+May!P68+Jun!P68+Jul!P68+Aug!P68+Sep!P68+Oct!P68+Nov!P68+Dec!P68+Jan!P68+Feb!P68+Mar!P68 -> 0 | Q68: =J68+O68+P68 -> 0 | R68: =IF(H68="Exempt",0,ROUND((J68*H68/100)-SUM(K68:M68),2)) -> 0 | T68: =Apr!T68+May!T68+Jun!T68+Jul!T68+Aug!T68+Sep!T68+Oct!T68+Nov!T68+Dec!T68+Jan!T68+Feb!T68+Mar!T68 -> 0 | U68: =Apr!U68+May!U68+Jun!U68+Jul!U68+Aug!U68+Sep!U68+Oct!U68+Nov!U68+Dec!U68+Jan!U68+Feb!U68+Mar!U68 -> 0 | V68: =Apr!V68+May!V68+Jun!V68+Jul!V68+Aug!V68+Sep!V68+Oct!V68+Nov!V68+Dec!V68+Jan!V68+Feb!V68+Mar!V68 -> 0 | W68: =Apr!W68+May!W68+Jun!W68+Jul!W68+Aug!W68+Sep!W68+Oct!W68+Nov!W68+Dec!W68+Jan!W68+Feb!W68+Mar!W68 -> 0 | X68: =Apr!X68+May!X68+Jun!X68+Jul!X68+Aug!X68+Sep!X68+Oct!X68+Nov!X68+Dec!X68+Jan!X68+Feb!X68+Mar!X68 -> 0 | Y68: =SUM(U68:X68) -> 0 | Z68: =Apr!Z68+May!Z68+Jun!Z68+Jul!Z68+Aug!Z68+Sep!Z68+Oct!Z68+Nov!Z68+Dec!Z68+Jan!Z68+Feb!Z68+Mar!Z68 -> 0 | AA68: =T68+Y68+Z68 -> 0 | AB68: =IF(H68="Exempt",0,ROUND((T68*H68/100)-SUM(U68:W68),2)) -> 0 | AD68: =Apr!AD68+May!AD68+Jun!AD68+Jul!AD68+Aug!AD68+Sep!AD68+Oct!AD68+Nov!AD68+Dec!AD68+Jan!AD68+Feb!AD68+Mar!AD68 -> 0 | AE68: =Apr!AE68+May!AE68+Jun!AE68+Jul!AE68+Aug!AE68+Sep!AE68+Oct!AE68+Nov!AE68+Dec!AE68+Jan!AE68+Feb!AE68+Mar!AE68 -> 0 | AF68: =Apr!AF68+May!AF68+Jun!AF68+Jul!AF68+Aug!AF68+Sep!AF68+Oct!AF68+Nov!AF68+Dec!AF68+Jan!AF68+Feb!AF68+Mar!AF68 -> 0 | AG68: =Apr!AG68+May!AG68+Jun!AG68+Jul!AG68+Aug!AG68+Sep!AG68+Oct!AG68+Nov!AG68+Dec!AG68+Jan!AG68+Feb!AG68+Mar!AG68 -> 0 | AI68: =SUM(AE68:AH68) -> 0 | AJ68: =Apr!AJ68+May!AJ68+Jun!AJ68+Jul!AJ68+Aug!AJ68+Sep!AJ68+Oct!AJ68+Nov!AJ68+Dec!AJ68+Jan!AJ68+Feb!AJ68+Mar!AJ68 -> 0 | AK68: =AD68+AI68+AJ68 -> 0 | AL68: =IF(H68="Exempt",0,ROUND((AD68*H68/100)-SUM(AE68:AG68),2)) -> 0
A69: =+A68+1 -> 54 | J69: =Apr!J69+May!J69+Jun!J69+Jul!J69+Aug!J69+Sep!J69+Oct!J69+Nov!J69+Dec!J69+Jan!J69+Feb!J69+Mar!J69 -> 0 | K69: =Apr!K69+May!K69+Jun!K69+Jul!K69+Aug!K69+Sep!K69+Oct!K69+Nov!K69+Dec!K69+Jan!K69+Feb!K69+Mar!K69 -> 0 | L69: =Apr!L69+May!L69+Jun!L69+Jul!L69+Aug!L69+Sep!L69+Oct!L69+Nov!L69+Dec!L69+Jan!L69+Feb!L69+Mar!L69 -> 0 | M69: =Apr!M69+May!M69+Jun!M69+Jul!M69+Aug!M69+Sep!M69+Oct!M69+Nov!M69+Dec!M69+Jan!M69+Feb!M69+Mar!M69 -> 0 | N69: =Apr!N69+May!N69+Jun!N69+Jul!N69+Aug!N69+Sep!N69+Oct!N69+Nov!N69+Dec!N69+Jan!N69+Feb!N69+Mar!N69 -> 0 | O69: =SUM(K69:N69) -> 0 | P69: =Apr!P69+May!P69+Jun!P69+Jul!P69+Aug!P69+Sep!P69+Oct!P69+Nov!P69+Dec!P69+Jan!P69+Feb!P69+Mar!P69 -> 0 | Q69: =J69+O69+P69 -> 0 | R69: =IF(H69="Exempt",0,ROUND((J69*H69/100)-SUM(K69:M69),2)) -> 0 | T69: =Apr!T69+May!T69+Jun!T69+Jul!T69+Aug!T69+Sep!T69+Oct!T69+Nov!T69+Dec!T69+Jan!T69+Feb!T69+Mar!T69 -> 0 | U69: =Apr!U69+May!U69+Jun!U69+Jul!U69+Aug!U69+Sep!U69+Oct!U69+Nov!U69+Dec!U69+Jan!U69+Feb!U69+Mar!U69 -> 0 | V69: =Apr!V69+May!V69+Jun!V69+Jul!V69+Aug!V69+Sep!V69+Oct!V69+Nov!V69+Dec!V69+Jan!V69+Feb!V69+Mar!V69 -> 0 | W69: =Apr!W69+May!W69+Jun!W69+Jul!W69+Aug!W69+Sep!W69+Oct!W69+Nov!W69+Dec!W69+Jan!W69+Feb!W69+Mar!W69 -> 0 | X69: =Apr!X69+May!X69+Jun!X69+Jul!X69+Aug!X69+Sep!X69+Oct!X69+Nov!X69+Dec!X69+Jan!X69+Feb!X69+Mar!X69 -> 0 | Y69: =SUM(U69:X69) -> 0 | Z69: =Apr!Z69+May!Z69+Jun!Z69+Jul!Z69+Aug!Z69+Sep!Z69+Oct!Z69+Nov!Z69+Dec!Z69+Jan!Z69+Feb!Z69+Mar!Z69 -> 0 | AA69: =T69+Y69+Z69 -> 0 | AB69: =IF(H69="Exempt",0,ROUND((T69*H69/100)-SUM(U69:W69),2)) -> 0 | AD69: =Apr!AD69+May!AD69+Jun!AD69+Jul!AD69+Aug!AD69+Sep!AD69+Oct!AD69+Nov!AD69+Dec!AD69+Jan!AD69+Feb!AD69+Mar!AD69 -> 0 | AE69: =Apr!AE69+May!AE69+Jun!AE69+Jul!AE69+Aug!AE69+Sep!AE69+Oct!AE69+Nov!AE69+Dec!AE69+Jan!AE69+Feb!AE69+Mar!AE69 -> 0 | AF69: =Apr!AF69+May!AF69+Jun!AF69+Jul!AF69+Aug!AF69+Sep!AF69+Oct!AF69+Nov!AF69+Dec!AF69+Jan!AF69+Feb!AF69+Mar!AF69 -> 0 | AG69: =Apr!AG69+May!AG69+Jun!AG69+Jul!AG69+Aug!AG69+Sep!AG69+Oct!AG69+Nov!AG69+Dec!AG69+Jan!AG69+Feb!AG69+Mar!AG69 -> 0 | AI69: =SUM(AE69:AH69) -> 0 | AJ69: =Apr!AJ69+May!AJ69+Jun!AJ69+Jul!AJ69+Aug!AJ69+Sep!AJ69+Oct!AJ69+Nov!AJ69+Dec!AJ69+Jan!AJ69+Feb!AJ69+Mar!AJ69 -> 0 | AK69: =AD69+AI69+AJ69 -> 0 | AL69: =IF(H69="Exempt",0,ROUND((AD69*H69/100)-SUM(AE69:AG69),2)) -> 0
A70: =+A69+1 -> 55 | J70: =Apr!J70+May!J70+Jun!J70+Jul!J70+Aug!J70+Sep!J70+Oct!J70+Nov!J70+Dec!J70+Jan!J70+Feb!J70+Mar!J70 -> 0 | K70: =Apr!K70+May!K70+Jun!K70+Jul!K70+Aug!K70+Sep!K70+Oct!K70+Nov!K70+Dec!K70+Jan!K70+Feb!K70+Mar!K70 -> 0 | L70: =Apr!L70+May!L70+Jun!L70+Jul!L70+Aug!L70+Sep!L70+Oct!L70+Nov!L70+Dec!L70+Jan!L70+Feb!L70+Mar!L70 -> 0 | M70: =Apr!M70+May!M70+Jun!M70+Jul!M70+Aug!M70+Sep!M70+Oct!M70+Nov!M70+Dec!M70+Jan!M70+Feb!M70+Mar!M70 -> 0 | N70: =Apr!N70+May!N70+Jun!N70+Jul!N70+Aug!N70+Sep!N70+Oct!N70+Nov!N70+Dec!N70+Jan!N70+Feb!N70+Mar!N70 -> 0 | O70: =SUM(K70:N70) -> 0 | P70: =Apr!P70+May!P70+Jun!P70+Jul!P70+Aug!P70+Sep!P70+Oct!P70+Nov!P70+Dec!P70+Jan!P70+Feb!P70+Mar!P70 -> 0 | Q70: =J70+O70+P70 -> 0 | R70: =IF(H70="Exempt",0,ROUND((J70*H70/100)-SUM(K70:M70),2)) -> 0 | T70: =Apr!T70+May!T70+Jun!T70+Jul!T70+Aug!T70+Sep!T70+Oct!T70+Nov!T70+Dec!T70+Jan!T70+Feb!T70+Mar!T70 -> 0 | U70: =Apr!U70+May!U70+Jun!U70+Jul!U70+Aug!U70+Sep!U70+Oct!U70+Nov!U70+Dec!U70+Jan!U70+Feb!U70+Mar!U70 -> 0 | V70: =Apr!V70+May!V70+Jun!V70+Jul!V70+Aug!V70+Sep!V70+Oct!V70+Nov!V70+Dec!V70+Jan!V70+Feb!V70+Mar!V70 -> 0 | W70: =Apr!W70+May!W70+Jun!W70+Jul!W70+Aug!W70+Sep!W70+Oct!W70+Nov!W70+Dec!W70+Jan!W70+Feb!W70+Mar!W70 -> 0 | X70: =Apr!X70+May!X70+Jun!X70+Jul!X70+Aug!X70+Sep!X70+Oct!X70+Nov!X70+Dec!X70+Jan!X70+Feb!X70+Mar!X70 -> 0 | Y70: =SUM(U70:X70) -> 0 | Z70: =Apr!Z70+May!Z70+Jun!Z70+Jul!Z70+Aug!Z70+Sep!Z70+Oct!Z70+Nov!Z70+Dec!Z70+Jan!Z70+Feb!Z70+Mar!Z70 -> 0 | AA70: =T70+Y70+Z70 -> 0 | AB70: =IF(H70="Exempt",0,ROUND((T70*H70/100)-SUM(U70:W70),2)) -> 0 | AD70: =Apr!AD70+May!AD70+Jun!AD70+Jul!AD70+Aug!AD70+Sep!AD70+Oct!AD70+Nov!AD70+Dec!AD70+Jan!AD70+Feb!AD70+Mar!AD70 -> 0 | AE70: =Apr!AE70+May!AE70+Jun!AE70+Jul!AE70+Aug!AE70+Sep!AE70+Oct!AE70+Nov!AE70+Dec!AE70+Jan!AE70+Feb!AE70+Mar!AE70 -> 0 | AF70: =Apr!AF70+May!AF70+Jun!AF70+Jul!AF70+Aug!AF70+Sep!AF70+Oct!AF70+Nov!AF70+Dec!AF70+Jan!AF70+Feb!AF70+Mar!AF70 -> 0 | AG70: =Apr!AG70+May!AG70+Jun!AG70+Jul!AG70+Aug!AG70+Sep!AG70+Oct!AG70+Nov!AG70+Dec!AG70+Jan!AG70+Feb!AG70+Mar!AG70 -> 0 | AI70: =SUM(AE70:AH70) -> 0 | AJ70: =Apr!AJ70+May!AJ70+Jun!AJ70+Jul!AJ70+Aug!AJ70+Sep!AJ70+Oct!AJ70+Nov!AJ70+Dec!AJ70+Jan!AJ70+Feb!AJ70+Mar!AJ70 -> 0 | AK70: =AD70+AI70+AJ70 -> 0 | AL70: =IF(H70="Exempt",0,ROUND((AD70*H70/100)-SUM(AE70:AG70),2)) -> 0
A71: =+A70+1 -> 56 | J71: =Apr!J71+May!J71+Jun!J71+Jul!J71+Aug!J71+Sep!J71+Oct!J71+Nov!J71+Dec!J71+Jan!J71+Feb!J71+Mar!J71 -> 0 | K71: =Apr!K71+May!K71+Jun!K71+Jul!K71+Aug!K71+Sep!K71+Oct!K71+Nov!K71+Dec!K71+Jan!K71+Feb!K71+Mar!K71 -> 0 | L71: =Apr!L71+May!L71+Jun!L71+Jul!L71+Aug!L71+Sep!L71+Oct!L71+Nov!L71+Dec!L71+Jan!L71+Feb!L71+Mar!L71 -> 0 | M71: =Apr!M71+May!M71+Jun!M71+Jul!M71+Aug!M71+Sep!M71+Oct!M71+Nov!M71+Dec!M71+Jan!M71+Feb!M71+Mar!M71 -> 0 | N71: =Apr!N71+May!N71+Jun!N71+Jul!N71+Aug!N71+Sep!N71+Oct!N71+Nov!N71+Dec!N71+Jan!N71+Feb!N71+Mar!N71 -> 0 | O71: =SUM(K71:N71) -> 0 | P71: =Apr!P71+May!P71+Jun!P71+Jul!P71+Aug!P71+Sep!P71+Oct!P71+Nov!P71+Dec!P71+Jan!P71+Feb!P71+Mar!P71 -> 0 | Q71: =J71+O71+P71 -> 0 | R71: =IF(H71="Exempt",0,ROUND((J71*H71/100)-SUM(K71:M71),2)) -> 0 | T71: =Apr!T71+May!T71+Jun!T71+Jul!T71+Aug!T71+Sep!T71+Oct!T71+Nov!T71+Dec!T71+Jan!T71+Feb!T71+Mar!T71 -> 0 | U71: =Apr!U71+May!U71+Jun!U71+Jul!U71+Aug!U71+Sep!U71+Oct!U71+Nov!U71+Dec!U71+Jan!U71+Feb!U71+Mar!U71 -> 0 | V71: =Apr!V71+May!V71+Jun!V71+Jul!V71+Aug!V71+Sep!V71+Oct!V71+Nov!V71+Dec!V71+Jan!V71+Feb!V71+Mar!V71 -> 0 | W71: =Apr!W71+May!W71+Jun!W71+Jul!W71+Aug!W71+Sep!W71+Oct!W71+Nov!W71+Dec!W71+Jan!W71+Feb!W71+Mar!W71 -> 0 | X71: =Apr!X71+May!X71+Jun!X71+Jul!X71+Aug!X71+Sep!X71+Oct!X71+Nov!X71+Dec!X71+Jan!X71+Feb!X71+Mar!X71 -> 0 | Y71: =SUM(U71:X71) -> 0 | Z71: =Apr!Z71+May!Z71+Jun!Z71+Jul!Z71+Aug!Z71+Sep!Z71+Oct!Z71+Nov!Z71+Dec!Z71+Jan!Z71+Feb!Z71+Mar!Z71 -> 0 | AA71: =T71+Y71+Z71 -> 0 | AB71: =IF(H71="Exempt",0,ROUND((T71*H71/100)-SUM(U71:W71),2)) -> 0 | AD71: =Apr!AD71+May!AD71+Jun!AD71+Jul!AD71+Aug!AD71+Sep!AD71+Oct!AD71+Nov!AD71+Dec!AD71+Jan!AD71+Feb!AD71+Mar!AD71 -> 0 | AE71: =Apr!AE71+May!AE71+Jun!AE71+Jul!AE71+Aug!AE71+Sep!AE71+Oct!AE71+Nov!AE71+Dec!AE71+Jan!AE71+Feb!AE71+Mar!AE71 -> 0 | AF71: =Apr!AF71+May!AF71+Jun!AF71+Jul!AF71+Aug!AF71+Sep!AF71+Oct!AF71+Nov!AF71+Dec!AF71+Jan!AF71+Feb!AF71+Mar!AF71 -> 0 | AG71: =Apr!AG71+May!AG71+Jun!AG71+Jul!AG71+Aug!AG71+Sep!AG71+Oct!AG71+Nov!AG71+Dec!AG71+Jan!AG71+Feb!AG71+Mar!AG71 -> 0 | AI71: =SUM(AE71:AH71) -> 0 | AJ71: =Apr!AJ71+May!AJ71+Jun!AJ71+Jul!AJ71+Aug!AJ71+Sep!AJ71+Oct!AJ71+Nov!AJ71+Dec!AJ71+Jan!AJ71+Feb!AJ71+Mar!AJ71 -> 0 | AK71: =AD71+AI71+AJ71 -> 0 | AL71: =IF(H71="Exempt",0,ROUND((AD71*H71/100)-SUM(AE71:AG71),2)) -> 0
A72: =+A71+1 -> 57 | J72: =Apr!J72+May!J72+Jun!J72+Jul!J72+Aug!J72+Sep!J72+Oct!J72+Nov!J72+Dec!J72+Jan!J72+Feb!J72+Mar!J72 -> 0 | K72: =Apr!K72+May!K72+Jun!K72+Jul!K72+Aug!K72+Sep!K72+Oct!K72+Nov!K72+Dec!K72+Jan!K72+Feb!K72+Mar!K72 -> 0 | L72: =Apr!L72+May!L72+Jun!L72+Jul!L72+Aug!L72+Sep!L72+Oct!L72+Nov!L72+Dec!L72+Jan!L72+Feb!L72+Mar!L72 -> 0 | M72: =Apr!M72+May!M72+Jun!M72+Jul!M72+Aug!M72+Sep!M72+Oct!M72+Nov!M72+Dec!M72+Jan!M72+Feb!M72+Mar!M72 -> 0 | N72: =Apr!N72+May!N72+Jun!N72+Jul!N72+Aug!N72+Sep!N72+Oct!N72+Nov!N72+Dec!N72+Jan!N72+Feb!N72+Mar!N72 -> 0 | O72: =SUM(K72:N72) -> 0 | P72: =Apr!P72+May!P72+Jun!P72+Jul!P72+Aug!P72+Sep!P72+Oct!P72+Nov!P72+Dec!P72+Jan!P72+Feb!P72+Mar!P72 -> 0 | Q72: =J72+O72+P72 -> 0 | R72: =IF(H72="Exempt",0,ROUND((J72*H72/100)-SUM(K72:M72),2)) -> 0 | T72: =Apr!T72+May!T72+Jun!T72+Jul!T72+Aug!T72+Sep!T72+Oct!T72+Nov!T72+Dec!T72+Jan!T72+Feb!T72+Mar!T72 -> 0 | U72: =Apr!U72+May!U72+Jun!U72+Jul!U72+Aug!U72+Sep!U72+Oct!U72+Nov!U72+Dec!U72+Jan!U72+Feb!U72+Mar!U72 -> 0 | V72: =Apr!V72+May!V72+Jun!V72+Jul!V72+Aug!V72+Sep!V72+Oct!V72+Nov!V72+Dec!V72+Jan!V72+Feb!V72+Mar!V72 -> 0 | W72: =Apr!W72+May!W72+Jun!W72+Jul!W72+Aug!W72+Sep!W72+Oct!W72+Nov!W72+Dec!W72+Jan!W72+Feb!W72+Mar!W72 -> 0 | X72: =Apr!X72+May!X72+Jun!X72+Jul!X72+Aug!X72+Sep!X72+Oct!X72+Nov!X72+Dec!X72+Jan!X72+Feb!X72+Mar!X72 -> 0 | Y72: =SUM(U72:X72) -> 0 | Z72: =Apr!Z72+May!Z72+Jun!Z72+Jul!Z72+Aug!Z72+Sep!Z72+Oct!Z72+Nov!Z72+Dec!Z72+Jan!Z72+Feb!Z72+Mar!Z72 -> 0 | AA72: =T72+Y72+Z72 -> 0 | AB72: =IF(H72="Exempt",0,ROUND((T72*H72/100)-SUM(U72:W72),2)) -> 0 | AD72: =Apr!AD72+May!AD72+Jun!AD72+Jul!AD72+Aug!AD72+Sep!AD72+Oct!AD72+Nov!AD72+Dec!AD72+Jan!AD72+Feb!AD72+Mar!AD72 -> 0 | AE72: =Apr!AE72+May!AE72+Jun!AE72+Jul!AE72+Aug!AE72+Sep!AE72+Oct!AE72+Nov!AE72+Dec!AE72+Jan!AE72+Feb!AE72+Mar!AE72 -> 0 | AF72: =Apr!AF72+May!AF72+Jun!AF72+Jul!AF72+Aug!AF72+Sep!AF72+Oct!AF72+Nov!AF72+Dec!AF72+Jan!AF72+Feb!AF72+Mar!AF72 -> 0 | AG72: =Apr!AG72+May!AG72+Jun!AG72+Jul!AG72+Aug!AG72+Sep!AG72+Oct!AG72+Nov!AG72+Dec!AG72+Jan!AG72+Feb!AG72+Mar!AG72 -> 0 | AI72: =SUM(AE72:AH72) -> 0 | AJ72: =Apr!AJ72+May!AJ72+Jun!AJ72+Jul!AJ72+Aug!AJ72+Sep!AJ72+Oct!AJ72+Nov!AJ72+Dec!AJ72+Jan!AJ72+Feb!AJ72+Mar!AJ72 -> 0 | AK72: =AD72+AI72+AJ72 -> 0 | AL72: =IF(H72="Exempt",0,ROUND((AD72*H72/100)-SUM(AE72:AG72),2)) -> 0
A73: =+A72+1 -> 58 | J73: =Apr!J73+May!J73+Jun!J73+Jul!J73+Aug!J73+Sep!J73+Oct!J73+Nov!J73+Dec!J73+Jan!J73+Feb!J73+Mar!J73 -> 0 | K73: =Apr!K73+May!K73+Jun!K73+Jul!K73+Aug!K73+Sep!K73+Oct!K73+Nov!K73+Dec!K73+Jan!K73+Feb!K73+Mar!K73 -> 0 | L73: =Apr!L73+May!L73+Jun!L73+Jul!L73+Aug!L73+Sep!L73+Oct!L73+Nov!L73+Dec!L73+Jan!L73+Feb!L73+Mar!L73 -> 0 | M73: =Apr!M73+May!M73+Jun!M73+Jul!M73+Aug!M73+Sep!M73+Oct!M73+Nov!M73+Dec!M73+Jan!M73+Feb!M73+Mar!M73 -> 0 | N73: =Apr!N73+May!N73+Jun!N73+Jul!N73+Aug!N73+Sep!N73+Oct!N73+Nov!N73+Dec!N73+Jan!N73+Feb!N73+Mar!N73 -> 0 | O73: =SUM(K73:N73) -> 0 | P73: =Apr!P73+May!P73+Jun!P73+Jul!P73+Aug!P73+Sep!P73+Oct!P73+Nov!P73+Dec!P73+Jan!P73+Feb!P73+Mar!P73 -> 0 | Q73: =J73+O73+P73 -> 0 | R73: =IF(H73="Exempt",0,ROUND((J73*H73/100)-SUM(K73:M73),2)) -> 0 | T73: =Apr!T73+May!T73+Jun!T73+Jul!T73+Aug!T73+Sep!T73+Oct!T73+Nov!T73+Dec!T73+Jan!T73+Feb!T73+Mar!T73 -> 0 | U73: =Apr!U73+May!U73+Jun!U73+Jul!U73+Aug!U73+Sep!U73+Oct!U73+Nov!U73+Dec!U73+Jan!U73+Feb!U73+Mar!U73 -> 0 | V73: =Apr!V73+May!V73+Jun!V73+Jul!V73+Aug!V73+Sep!V73+Oct!V73+Nov!V73+Dec!V73+Jan!V73+Feb!V73+Mar!V73 -> 0 | W73: =Apr!W73+May!W73+Jun!W73+Jul!W73+Aug!W73+Sep!W73+Oct!W73+Nov!W73+Dec!W73+Jan!W73+Feb!W73+Mar!W73 -> 0 | X73: =Apr!X73+May!X73+Jun!X73+Jul!X73+Aug!X73+Sep!X73+Oct!X73+Nov!X73+Dec!X73+Jan!X73+Feb!X73+Mar!X73 -> 0 | Y73: =SUM(U73:X73) -> 0 | Z73: =Apr!Z73+May!Z73+Jun!Z73+Jul!Z73+Aug!Z73+Sep!Z73+Oct!Z73+Nov!Z73+Dec!Z73+Jan!Z73+Feb!Z73+Mar!Z73 -> 0 | AA73: =T73+Y73+Z73 -> 0 | AB73: =IF(H73="Exempt",0,ROUND((T73*H73/100)-SUM(U73:W73),2)) -> 0 | AD73: =Apr!AD73+May!AD73+Jun!AD73+Jul!AD73+Aug!AD73+Sep!AD73+Oct!AD73+Nov!AD73+Dec!AD73+Jan!AD73+Feb!AD73+Mar!AD73 -> 0 | AE73: =Apr!AE73+May!AE73+Jun!AE73+Jul!AE73+Aug!AE73+Sep!AE73+Oct!AE73+Nov!AE73+Dec!AE73+Jan!AE73+Feb!AE73+Mar!AE73 -> 0 | AF73: =Apr!AF73+May!AF73+Jun!AF73+Jul!AF73+Aug!AF73+Sep!AF73+Oct!AF73+Nov!AF73+Dec!AF73+Jan!AF73+Feb!AF73+Mar!AF73 -> 0 | AG73: =Apr!AG73+May!AG73+Jun!AG73+Jul!AG73+Aug!AG73+Sep!AG73+Oct!AG73+Nov!AG73+Dec!AG73+Jan!AG73+Feb!AG73+Mar!AG73 -> 0 | AI73: =SUM(AE73:AH73) -> 0 | AJ73: =Apr!AJ73+May!AJ73+Jun!AJ73+Jul!AJ73+Aug!AJ73+Sep!AJ73+Oct!AJ73+Nov!AJ73+Dec!AJ73+Jan!AJ73+Feb!AJ73+Mar!AJ73 -> 0 | AK73: =AD73+AI73+AJ73 -> 0 | AL73: =IF(H73="Exempt",0,ROUND((AD73*H73/100)-SUM(AE73:AG73),2)) -> 0
A74: =+A73+1 -> 59 | J74: =Apr!J74+May!J74+Jun!J74+Jul!J74+Aug!J74+Sep!J74+Oct!J74+Nov!J74+Dec!J74+Jan!J74+Feb!J74+Mar!J74 -> 0 | K74: =Apr!K74+May!K74+Jun!K74+Jul!K74+Aug!K74+Sep!K74+Oct!K74+Nov!K74+Dec!K74+Jan!K74+Feb!K74+Mar!K74 -> 0 | L74: =Apr!L74+May!L74+Jun!L74+Jul!L74+Aug!L74+Sep!L74+Oct!L74+Nov!L74+Dec!L74+Jan!L74+Feb!L74+Mar!L74 -> 0 | M74: =Apr!M74+May!M74+Jun!M74+Jul!M74+Aug!M74+Sep!M74+Oct!M74+Nov!M74+Dec!M74+Jan!M74+Feb!M74+Mar!M74 -> 0 | N74: =Apr!N74+May!N74+Jun!N74+Jul!N74+Aug!N74+Sep!N74+Oct!N74+Nov!N74+Dec!N74+Jan!N74+Feb!N74+Mar!N74 -> 0 | O74: =SUM(K74:N74) -> 0 | P74: =Apr!P74+May!P74+Jun!P74+Jul!P74+Aug!P74+Sep!P74+Oct!P74+Nov!P74+Dec!P74+Jan!P74+Feb!P74+Mar!P74 -> 0 | Q74: =J74+O74+P74 -> 0 | R74: =IF(H74="Exempt",0,ROUND((J74*H74/100)-SUM(K74:M74),2)) -> 0 | T74: =Apr!T74+May!T74+Jun!T74+Jul!T74+Aug!T74+Sep!T74+Oct!T74+Nov!T74+Dec!T74+Jan!T74+Feb!T74+Mar!T74 -> 0 | U74: =Apr!U74+May!U74+Jun!U74+Jul!U74+Aug!U74+Sep!U74+Oct!U74+Nov!U74+Dec!U74+Jan!U74+Feb!U74+Mar!U74 -> 0 | V74: =Apr!V74+May!V74+Jun!V74+Jul!V74+Aug!V74+Sep!V74+Oct!V74+Nov!V74+Dec!V74+Jan!V74+Feb!V74+Mar!V74 -> 0 | W74: =Apr!W74+May!W74+Jun!W74+Jul!W74+Aug!W74+Sep!W74+Oct!W74+Nov!W74+Dec!W74+Jan!W74+Feb!W74+Mar!W74 -> 0 | X74: =Apr!X74+May!X74+Jun!X74+Jul!X74+Aug!X74+Sep!X74+Oct!X74+Nov!X74+Dec!X74+Jan!X74+Feb!X74+Mar!X74 -> 0 | Y74: =SUM(U74:X74) -> 0 | Z74: =Apr!Z74+May!Z74+Jun!Z74+Jul!Z74+Aug!Z74+Sep!Z74+Oct!Z74+Nov!Z74+Dec!Z74+Jan!Z74+Feb!Z74+Mar!Z74 -> 0 | AA74: =T74+Y74+Z74 -> 0 | AB74: =IF(H74="Exempt",0,ROUND((T74*H74/100)-SUM(U74:W74),2)) -> 0 | AD74: =Apr!AD74+May!AD74+Jun!AD74+Jul!AD74+Aug!AD74+Sep!AD74+Oct!AD74+Nov!AD74+Dec!AD74+Jan!AD74+Feb!AD74+Mar!AD74 -> 0 | AE74: =Apr!AE74+May!AE74+Jun!AE74+Jul!AE74+Aug!AE74+Sep!AE74+Oct!AE74+Nov!AE74+Dec!AE74+Jan!AE74+Feb!AE74+Mar!AE74 -> 0 | AF74: =Apr!AF74+May!AF74+Jun!AF74+Jul!AF74+Aug!AF74+Sep!AF74+Oct!AF74+Nov!AF74+Dec!AF74+Jan!AF74+Feb!AF74+Mar!AF74 -> 0 | AG74: =Apr!AG74+May!AG74+Jun!AG74+Jul!AG74+Aug!AG74+Sep!AG74+Oct!AG74+Nov!AG74+Dec!AG74+Jan!AG74+Feb!AG74+Mar!AG74 -> 0 | AI74: =SUM(AE74:AH74) -> 0 | AJ74: =Apr!AJ74+May!AJ74+Jun!AJ74+Jul!AJ74+Aug!AJ74+Sep!AJ74+Oct!AJ74+Nov!AJ74+Dec!AJ74+Jan!AJ74+Feb!AJ74+Mar!AJ74 -> 0 | AK74: =AD74+AI74+AJ74 -> 0 | AL74: =IF(H74="Exempt",0,ROUND((AD74*H74/100)-SUM(AE74:AG74),2)) -> 0
A75: =+A74+1 -> 60 | J75: =Apr!J75+May!J75+Jun!J75+Jul!J75+Aug!J75+Sep!J75+Oct!J75+Nov!J75+Dec!J75+Jan!J75+Feb!J75+Mar!J75 -> 0 | K75: =Apr!K75+May!K75+Jun!K75+Jul!K75+Aug!K75+Sep!K75+Oct!K75+Nov!K75+Dec!K75+Jan!K75+Feb!K75+Mar!K75 -> 0 | L75: =Apr!L75+May!L75+Jun!L75+Jul!L75+Aug!L75+Sep!L75+Oct!L75+Nov!L75+Dec!L75+Jan!L75+Feb!L75+Mar!L75 -> 0 | M75: =Apr!M75+May!M75+Jun!M75+Jul!M75+Aug!M75+Sep!M75+Oct!M75+Nov!M75+Dec!M75+Jan!M75+Feb!M75+Mar!M75 -> 0 | N75: =Apr!N75+May!N75+Jun!N75+Jul!N75+Aug!N75+Sep!N75+Oct!N75+Nov!N75+Dec!N75+Jan!N75+Feb!N75+Mar!N75 -> 0 | O75: =SUM(K75:N75) -> 0 | P75: =Apr!P75+May!P75+Jun!P75+Jul!P75+Aug!P75+Sep!P75+Oct!P75+Nov!P75+Dec!P75+Jan!P75+Feb!P75+Mar!P75 -> 0 | Q75: =J75+O75+P75 -> 0 | R75: =IF(H75="Exempt",0,ROUND((J75*H75/100)-SUM(K75:M75),2)) -> 0 | T75: =Apr!T75+May!T75+Jun!T75+Jul!T75+Aug!T75+Sep!T75+Oct!T75+Nov!T75+Dec!T75+Jan!T75+Feb!T75+Mar!T75 -> 0 | U75: =Apr!U75+May!U75+Jun!U75+Jul!U75+Aug!U75+Sep!U75+Oct!U75+Nov!U75+Dec!U75+Jan!U75+Feb!U75+Mar!U75 -> 0 | V75: =Apr!V75+May!V75+Jun!V75+Jul!V75+Aug!V75+Sep!V75+Oct!V75+Nov!V75+Dec!V75+Jan!V75+Feb!V75+Mar!V75 -> 0 | W75: =Apr!W75+May!W75+Jun!W75+Jul!W75+Aug!W75+Sep!W75+Oct!W75+Nov!W75+Dec!W75+Jan!W75+Feb!W75+Mar!W75 -> 0 | X75: =Apr!X75+May!X75+Jun!X75+Jul!X75+Aug!X75+Sep!X75+Oct!X75+Nov!X75+Dec!X75+Jan!X75+Feb!X75+Mar!X75 -> 0 | Y75: =SUM(U75:X75) -> 0 | Z75: =Apr!Z75+May!Z75+Jun!Z75+Jul!Z75+Aug!Z75+Sep!Z75+Oct!Z75+Nov!Z75+Dec!Z75+Jan!Z75+Feb!Z75+Mar!Z75 -> 0 | AA75: =T75+Y75+Z75 -> 0 | AB75: =IF(H75="Exempt",0,ROUND((T75*H75/100)-SUM(U75:W75),2)) -> 0 | AD75: =Apr!AD75+May!AD75+Jun!AD75+Jul!AD75+Aug!AD75+Sep!AD75+Oct!AD75+Nov!AD75+Dec!AD75+Jan!AD75+Feb!AD75+Mar!AD75 -> 0 | AE75: =Apr!AE75+May!AE75+Jun!AE75+Jul!AE75+Aug!AE75+Sep!AE75+Oct!AE75+Nov!AE75+Dec!AE75+Jan!AE75+Feb!AE75+Mar!AE75 -> 0 | AF75: =Apr!AF75+May!AF75+Jun!AF75+Jul!AF75+Aug!AF75+Sep!AF75+Oct!AF75+Nov!AF75+Dec!AF75+Jan!AF75+Feb!AF75+Mar!AF75 -> 0 | AG75: =Apr!AG75+May!AG75+Jun!AG75+Jul!AG75+Aug!AG75+Sep!AG75+Oct!AG75+Nov!AG75+Dec!AG75+Jan!AG75+Feb!AG75+Mar!AG75 -> 0 | AI75: =SUM(AE75:AH75) -> 0 | AJ75: =Apr!AJ75+May!AJ75+Jun!AJ75+Jul!AJ75+Aug!AJ75+Sep!AJ75+Oct!AJ75+Nov!AJ75+Dec!AJ75+Jan!AJ75+Feb!AJ75+Mar!AJ75 -> 0 | AK75: =AD75+AI75+AJ75 -> 0 | AL75: =IF(H75="Exempt",0,ROUND((AD75*H75/100)-SUM(AE75:AG75),2)) -> 0
A76: =+A75+1 -> 61 | J76: =Apr!J76+May!J76+Jun!J76+Jul!J76+Aug!J76+Sep!J76+Oct!J76+Nov!J76+Dec!J76+Jan!J76+Feb!J76+Mar!J76 -> 0 | K76: =Apr!K76+May!K76+Jun!K76+Jul!K76+Aug!K76+Sep!K76+Oct!K76+Nov!K76+Dec!K76+Jan!K76+Feb!K76+Mar!K76 -> 0 | L76: =Apr!L76+May!L76+Jun!L76+Jul!L76+Aug!L76+Sep!L76+Oct!L76+Nov!L76+Dec!L76+Jan!L76+Feb!L76+Mar!L76 -> 0 | M76: =Apr!M76+May!M76+Jun!M76+Jul!M76+Aug!M76+Sep!M76+Oct!M76+Nov!M76+Dec!M76+Jan!M76+Feb!M76+Mar!M76 -> 0 | N76: =Apr!N76+May!N76+Jun!N76+Jul!N76+Aug!N76+Sep!N76+Oct!N76+Nov!N76+Dec!N76+Jan!N76+Feb!N76+Mar!N76 -> 0 | O76: =SUM(K76:N76) -> 0 | P76: =Apr!P76+May!P76+Jun!P76+Jul!P76+Aug!P76+Sep!P76+Oct!P76+Nov!P76+Dec!P76+Jan!P76+Feb!P76+Mar!P76 -> 0 | Q76: =J76+O76+P76 -> 0 | R76: =IF(H76="Exempt",0,ROUND((J76*H76/100)-SUM(K76:M76),2)) -> 0 | T76: =Apr!T76+May!T76+Jun!T76+Jul!T76+Aug!T76+Sep!T76+Oct!T76+Nov!T76+Dec!T76+Jan!T76+Feb!T76+Mar!T76 -> 0 | U76: =Apr!U76+May!U76+Jun!U76+Jul!U76+Aug!U76+Sep!U76+Oct!U76+Nov!U76+Dec!U76+Jan!U76+Feb!U76+Mar!U76 -> 0 | V76: =Apr!V76+May!V76+Jun!V76+Jul!V76+Aug!V76+Sep!V76+Oct!V76+Nov!V76+Dec!V76+Jan!V76+Feb!V76+Mar!V76 -> 0 | W76: =Apr!W76+May!W76+Jun!W76+Jul!W76+Aug!W76+Sep!W76+Oct!W76+Nov!W76+Dec!W76+Jan!W76+Feb!W76+Mar!W76 -> 0 | X76: =Apr!X76+May!X76+Jun!X76+Jul!X76+Aug!X76+Sep!X76+Oct!X76+Nov!X76+Dec!X76+Jan!X76+Feb!X76+Mar!X76 -> 0 | Y76: =SUM(U76:X76) -> 0 | Z76: =Apr!Z76+May!Z76+Jun!Z76+Jul!Z76+Aug!Z76+Sep!Z76+Oct!Z76+Nov!Z76+Dec!Z76+Jan!Z76+Feb!Z76+Mar!Z76 -> 0 | AA76: =T76+Y76+Z76 -> 0 | AB76: =IF(H76="Exempt",0,ROUND((T76*H76/100)-SUM(U76:W76),2)) -> 0 | AD76: =Apr!AD76+May!AD76+Jun!AD76+Jul!AD76+Aug!AD76+Sep!AD76+Oct!AD76+Nov!AD76+Dec!AD76+Jan!AD76+Feb!AD76+Mar!AD76 -> 0 | AE76: =Apr!AE76+May!AE76+Jun!AE76+Jul!AE76+Aug!AE76+Sep!AE76+Oct!AE76+Nov!AE76+Dec!AE76+Jan!AE76+Feb!AE76+Mar!AE76 -> 0 | AF76: =Apr!AF76+May!AF76+Jun!AF76+Jul!AF76+Aug!AF76+Sep!AF76+Oct!AF76+Nov!AF76+Dec!AF76+Jan!AF76+Feb!AF76+Mar!AF76 -> 0 | AG76: =Apr!AG76+May!AG76+Jun!AG76+Jul!AG76+Aug!AG76+Sep!AG76+Oct!AG76+Nov!AG76+Dec!AG76+Jan!AG76+Feb!AG76+Mar!AG76 -> 0 | AI76: =SUM(AE76:AH76) -> 0 | AJ76: =Apr!AJ76+May!AJ76+Jun!AJ76+Jul!AJ76+Aug!AJ76+Sep!AJ76+Oct!AJ76+Nov!AJ76+Dec!AJ76+Jan!AJ76+Feb!AJ76+Mar!AJ76 -> 0 | AK76: =AD76+AI76+AJ76 -> 0 | AL76: =IF(H76="Exempt",0,ROUND((AD76*H76/100)-SUM(AE76:AG76),2)) -> 0
A77: =+A76+1 -> 62 | J77: =Apr!J77+May!J77+Jun!J77+Jul!J77+Aug!J77+Sep!J77+Oct!J77+Nov!J77+Dec!J77+Jan!J77+Feb!J77+Mar!J77 -> 0 | K77: =Apr!K77+May!K77+Jun!K77+Jul!K77+Aug!K77+Sep!K77+Oct!K77+Nov!K77+Dec!K77+Jan!K77+Feb!K77+Mar!K77 -> 0 | L77: =Apr!L77+May!L77+Jun!L77+Jul!L77+Aug!L77+Sep!L77+Oct!L77+Nov!L77+Dec!L77+Jan!L77+Feb!L77+Mar!L77 -> 0 | M77: =Apr!M77+May!M77+Jun!M77+Jul!M77+Aug!M77+Sep!M77+Oct!M77+Nov!M77+Dec!M77+Jan!M77+Feb!M77+Mar!M77 -> 0 | N77: =Apr!N77+May!N77+Jun!N77+Jul!N77+Aug!N77+Sep!N77+Oct!N77+Nov!N77+Dec!N77+Jan!N77+Feb!N77+Mar!N77 -> 0 | O77: =SUM(K77:N77) -> 0 | P77: =Apr!P77+May!P77+Jun!P77+Jul!P77+Aug!P77+Sep!P77+Oct!P77+Nov!P77+Dec!P77+Jan!P77+Feb!P77+Mar!P77 -> 0 | Q77: =J77+O77+P77 -> 0 | R77: =IF(H77="Exempt",0,ROUND((J77*H77/100)-SUM(K77:M77),2)) -> 0 | T77: =Apr!T77+May!T77+Jun!T77+Jul!T77+Aug!T77+Sep!T77+Oct!T77+Nov!T77+Dec!T77+Jan!T77+Feb!T77+Mar!T77 -> 0 | U77: =Apr!U77+May!U77+Jun!U77+Jul!U77+Aug!U77+Sep!U77+Oct!U77+Nov!U77+Dec!U77+Jan!U77+Feb!U77+Mar!U77 -> 0 | V77: =Apr!V77+May!V77+Jun!V77+Jul!V77+Aug!V77+Sep!V77+Oct!V77+Nov!V77+Dec!V77+Jan!V77+Feb!V77+Mar!V77 -> 0 | W77: =Apr!W77+May!W77+Jun!W77+Jul!W77+Aug!W77+Sep!W77+Oct!W77+Nov!W77+Dec!W77+Jan!W77+Feb!W77+Mar!W77 -> 0 | X77: =Apr!X77+May!X77+Jun!X77+Jul!X77+Aug!X77+Sep!X77+Oct!X77+Nov!X77+Dec!X77+Jan!X77+Feb!X77+Mar!X77 -> 0 | Y77: =SUM(U77:X77) -> 0 | Z77: =Apr!Z77+May!Z77+Jun!Z77+Jul!Z77+Aug!Z77+Sep!Z77+Oct!Z77+Nov!Z77+Dec!Z77+Jan!Z77+Feb!Z77+Mar!Z77 -> 0 | AA77: =T77+Y77+Z77 -> 0 | AB77: =IF(H77="Exempt",0,ROUND((T77*H77/100)-SUM(U77:W77),2)) -> 0 | AD77: =Apr!AD77+May!AD77+Jun!AD77+Jul!AD77+Aug!AD77+Sep!AD77+Oct!AD77+Nov!AD77+Dec!AD77+Jan!AD77+Feb!AD77+Mar!AD77 -> 0 | AE77: =Apr!AE77+May!AE77+Jun!AE77+Jul!AE77+Aug!AE77+Sep!AE77+Oct!AE77+Nov!AE77+Dec!AE77+Jan!AE77+Feb!AE77+Mar!AE77 -> 0 | AF77: =Apr!AF77+May!AF77+Jun!AF77+Jul!AF77+Aug!AF77+Sep!AF77+Oct!AF77+Nov!AF77+Dec!AF77+Jan!AF77+Feb!AF77+Mar!AF77 -> 0 | AG77: =Apr!AG77+May!AG77+Jun!AG77+Jul!AG77+Aug!AG77+Sep!AG77+Oct!AG77+Nov!AG77+Dec!AG77+Jan!AG77+Feb!AG77+Mar!AG77 -> 0 | AI77: =SUM(AE77:AH77) -> 0 | AJ77: =Apr!AJ77+May!AJ77+Jun!AJ77+Jul!AJ77+Aug!AJ77+Sep!AJ77+Oct!AJ77+Nov!AJ77+Dec!AJ77+Jan!AJ77+Feb!AJ77+Mar!AJ77 -> 0 | AK77: =AD77+AI77+AJ77 -> 0 | AL77: =IF(H77="Exempt",0,ROUND((AD77*H77/100)-SUM(AE77:AG77),2)) -> 0
A78: =+A77+1 -> 63 | J78: =Apr!J78+May!J78+Jun!J78+Jul!J78+Aug!J78+Sep!J78+Oct!J78+Nov!J78+Dec!J78+Jan!J78+Feb!J78+Mar!J78 -> 0 | K78: =Apr!K78+May!K78+Jun!K78+Jul!K78+Aug!K78+Sep!K78+Oct!K78+Nov!K78+Dec!K78+Jan!K78+Feb!K78+Mar!K78 -> 0 | L78: =Apr!L78+May!L78+Jun!L78+Jul!L78+Aug!L78+Sep!L78+Oct!L78+Nov!L78+Dec!L78+Jan!L78+Feb!L78+Mar!L78 -> 0 | M78: =Apr!M78+May!M78+Jun!M78+Jul!M78+Aug!M78+Sep!M78+Oct!M78+Nov!M78+Dec!M78+Jan!M78+Feb!M78+Mar!M78 -> 0 | N78: =Apr!N78+May!N78+Jun!N78+Jul!N78+Aug!N78+Sep!N78+Oct!N78+Nov!N78+Dec!N78+Jan!N78+Feb!N78+Mar!N78 -> 0 | O78: =SUM(K78:N78) -> 0 | P78: =Apr!P78+May!P78+Jun!P78+Jul!P78+Aug!P78+Sep!P78+Oct!P78+Nov!P78+Dec!P78+Jan!P78+Feb!P78+Mar!P78 -> 0 | Q78: =J78+O78+P78 -> 0 | R78: =IF(H78="Exempt",0,ROUND((J78*H78/100)-SUM(K78:M78),2)) -> 0 | T78: =Apr!T78+May!T78+Jun!T78+Jul!T78+Aug!T78+Sep!T78+Oct!T78+Nov!T78+Dec!T78+Jan!T78+Feb!T78+Mar!T78 -> 0 | U78: =Apr!U78+May!U78+Jun!U78+Jul!U78+Aug!U78+Sep!U78+Oct!U78+Nov!U78+Dec!U78+Jan!U78+Feb!U78+Mar!U78 -> 0 | V78: =Apr!V78+May!V78+Jun!V78+Jul!V78+Aug!V78+Sep!V78+Oct!V78+Nov!V78+Dec!V78+Jan!V78+Feb!V78+Mar!V78 -> 0 | W78: =Apr!W78+May!W78+Jun!W78+Jul!W78+Aug!W78+Sep!W78+Oct!W78+Nov!W78+Dec!W78+Jan!W78+Feb!W78+Mar!W78 -> 0 | X78: =Apr!X78+May!X78+Jun!X78+Jul!X78+Aug!X78+Sep!X78+Oct!X78+Nov!X78+Dec!X78+Jan!X78+Feb!X78+Mar!X78 -> 0 | Y78: =SUM(U78:X78) -> 0 | Z78: =Apr!Z78+May!Z78+Jun!Z78+Jul!Z78+Aug!Z78+Sep!Z78+Oct!Z78+Nov!Z78+Dec!Z78+Jan!Z78+Feb!Z78+Mar!Z78 -> 0 | AA78: =T78+Y78+Z78 -> 0 | AB78: =IF(H78="Exempt",0,ROUND((T78*H78/100)-SUM(U78:W78),2)) -> 0 | AD78: =Apr!AD78+May!AD78+Jun!AD78+Jul!AD78+Aug!AD78+Sep!AD78+Oct!AD78+Nov!AD78+Dec!AD78+Jan!AD78+Feb!AD78+Mar!AD78 -> 0 | AE78: =Apr!AE78+May!AE78+Jun!AE78+Jul!AE78+Aug!AE78+Sep!AE78+Oct!AE78+Nov!AE78+Dec!AE78+Jan!AE78+Feb!AE78+Mar!AE78 -> 0 | AF78: =Apr!AF78+May!AF78+Jun!AF78+Jul!AF78+Aug!AF78+Sep!AF78+Oct!AF78+Nov!AF78+Dec!AF78+Jan!AF78+Feb!AF78+Mar!AF78 -> 0 | AG78: =Apr!AG78+May!AG78+Jun!AG78+Jul!AG78+Aug!AG78+Sep!AG78+Oct!AG78+Nov!AG78+Dec!AG78+Jan!AG78+Feb!AG78+Mar!AG78 -> 0 | AI78: =SUM(AE78:AH78) -> 0 | AJ78: =Apr!AJ78+May!AJ78+Jun!AJ78+Jul!AJ78+Aug!AJ78+Sep!AJ78+Oct!AJ78+Nov!AJ78+Dec!AJ78+Jan!AJ78+Feb!AJ78+Mar!AJ78 -> 0 | AK78: =AD78+AI78+AJ78 -> 0 | AL78: =IF(H78="Exempt",0,ROUND((AD78*H78/100)-SUM(AE78:AG78),2)) -> 0
... A126: =+A125+1 -> 111 | J126: =Apr!J126+May!J126+Jun!J126+Jul!J126+Aug!J126+Sep!J126+Oct!J126+Nov!J126+Dec!J126+Jan!J126+Feb!J126+Mar!J126 -> 0 | K126: =Apr!K126+May!K126+Jun!K126+Jul!K126+Aug!K126+Sep!K126+Oct!K126+Nov!K126+Dec!K126+Jan!K126+Feb!K126+Mar!K126 -> 0 | L126: =Apr!L126+May!L126+Jun!L126+Jul!L126+Aug!L126+Sep!L126+Oct!L126+Nov!L126+Dec!L126+Jan!L126+Feb!L126+Mar!L126 -> 0 | M126: =Apr!M126+May!M126+Jun!M126+Jul!M126+Aug!M126+Sep!M126+Oct!M126+Nov!M126+Dec!M126+Jan!M126+Feb!M126+Mar!M126 -> 0 | N126: =Apr!N126+May!N126+Jun!N126+Jul!N126+Aug!N126+Sep!N126+Oct!N126+Nov!N126+Dec!N126+Jan!N126+Feb!N126+Mar!N126 -> 0 | O126: =SUM(K126:N126) -> 0 | P126: =Apr!P126+May!P126+Jun!P126+Jul!P126+Aug!P126+Sep!P126+Oct!P126+Nov!P126+Dec!P126+Jan!P126+Feb!P126+Mar!P126 -> 0 | Q126: =J126+O126+P126 -> 0 | R126: =IF(H126="Exempt",0,ROUND((J126*H126/100)-SUM(K126:M126),2)) -> 0 | T126: =Apr!T126+May!T126+Jun!T126+Jul!T126+Aug!T126+Sep!T126+Oct!T126+Nov!T126+Dec!T126+Jan!T126+Feb!T126+Mar!T126 -> 0 | U126: =Apr!U126+May!U126+Jun!U126+Jul!U126+Aug!U126+Sep!U126+Oct!U126+Nov!U126+Dec!U126+Jan!U126+Feb!U126+Mar!U126 -> 0 | V126: =Apr!V126+May!V126+Jun!V126+Jul!V126+Aug!V126+Sep!V126+Oct!V126+Nov!V126+Dec!V126+Jan!V126+Feb!V126+Mar!V126 -> 0 | W126: =Apr!W126+May!W126+Jun!W126+Jul!W126+Aug!W126+Sep!W126+Oct!W126+Nov!W126+Dec!W126+Jan!W126+Feb!W126+Mar!W126 -> 0 | X126: =Apr!X126+May!X126+Jun!X126+Jul!X126+Aug!X126+Sep!X126+Oct!X126+Nov!X126+Dec!X126+Jan!X126+Feb!X126+Mar!X126 -> 0 | Y126: =SUM(U126:X126) -> 0 | Z126: =Apr!Z126+May!Z126+Jun!Z126+Jul!Z126+Aug!Z126+Sep!Z126+Oct!Z126+Nov!Z126+Dec!Z126+Jan!Z126+Feb!Z126+Mar!Z126 -> 0 | AA126: =T126+Y126+Z126 -> 0 | AB126: =IF(H126="Exempt",0,ROUND((T126*H126/100)-SUM(U126:W126),2)) -> 0 | AD126: =Apr!AD126+May!AD126+Jun!AD126+Jul!AD126+Aug!AD126+Sep!AD126+Oct!AD126+Nov!AD126+Dec!AD126+Jan!AD126+Feb!AD126+Mar!AD126 -> 0 | AE126: =Apr!AE126+May!AE126+Jun!AE126+Jul!AE126+Aug!AE126+Sep!AE126+Oct!AE126+Nov!AE126+Dec!AE126+Jan!AE126+Feb!AE126+Mar!AE126 -> 0 | AF126: =Apr!AF126+May!AF126+Jun!AF126+Jul!AF126+Aug!AF126+Sep!AF126+Oct!AF126+Nov!AF126+Dec!AF126+Jan!AF126+Feb!AF126+Mar!AF126 -> 0 | AG126: =Apr!AG126+May!AG126+Jun!AG126+Jul!AG126+Aug!AG126+Sep!AG126+Oct!AG126+Nov!AG126+Dec!AG126+Jan!AG126+Feb!AG126+Mar!AG126 -> 0 | AI126: =SUM(AE126:AH126) -> 0 | AJ126: =Apr!AJ126+May!AJ126+Jun!AJ126+Jul!AJ126+Aug!AJ126+Sep!AJ126+Oct!AJ126+Nov!AJ126+Dec!AJ126+Jan!AJ126+Feb!AJ126+Mar!AJ126 -> 0 | AK126: =AD126+AI126+AJ126 -> 0 | AL126: =IF(H126="Exempt",0,ROUND((AD126*H126/100)-SUM(AE126:AG126),2)) -> 0
A127: =+A126+1 -> 112 | B127: Purchases | D127: Materials | E127: Registered | H127: 5 | J127: =Apr!J127+May!J127+Jun!J127+Jul!J127+Aug!J127+Sep!J127+Oct!J127+Nov!J127+Dec!J127+Jan!J127+Feb!J127+Mar!J127 -> 0 | K127: =Apr!K127+May!K127+Jun!K127+Jul!K127+Aug!K127+Sep!K127+Oct!K127+Nov!K127+Dec!K127+Jan!K127+Feb!K127+Mar!K127 -> 0 | L127: =Apr!L127+May!L127+Jun!L127+Jul!L127+Aug!L127+Sep!L127+Oct!L127+Nov!L127+Dec!L127+Jan!L127+Feb!L127+Mar!L127 -> 0 | M127: =Apr!M127+May!M127+Jun!M127+Jul!M127+Aug!M127+Sep!M127+Oct!M127+Nov!M127+Dec!M127+Jan!M127+Feb!M127+Mar!M127 -> 0 | N127: =Apr!N127+May!N127+Jun!N127+Jul!N127+Aug!N127+Sep!N127+Oct!N127+Nov!N127+Dec!N127+Jan!N127+Feb!N127+Mar!N127 -> 0 | O127: =SUM(K127:N127) -> 0 | P127: =Apr!P127+May!P127+Jun!P127+Jul!P127+Aug!P127+Sep!P127+Oct!P127+Nov!P127+Dec!P127+Jan!P127+Feb!P127+Mar!P127 -> 0 | Q127: =J127+O127+P127 -> 0 | R127: =IF(H127="Exempt",0,ROUND((J127*H127/100)-SUM(K127:M127),2)) -> 0 | T127: =Apr!T127+May!T127+Jun!T127+Jul!T127+Aug!T127+Sep!T127+Oct!T127+Nov!T127+Dec!T127+Jan!T127+Feb!T127+Mar!T127 -> 0 | U127: =Apr!U127+May!U127+Jun!U127+Jul!U127+Aug!U127+Sep!U127+Oct!U127+Nov!U127+Dec!U127+Jan!U127+Feb!U127+Mar!U127 -> 0 | V127: =Apr!V127+May!V127+Jun!V127+Jul!V127+Aug!V127+Sep!V127+Oct!V127+Nov!V127+Dec!V127+Jan!V127+Feb!V127+Mar!V127 -> 0 | W127: =Apr!W127+May!W127+Jun!W127+Jul!W127+Aug!W127+Sep!W127+Oct!W127+Nov!W127+Dec!W127+Jan!W127+Feb!W127+Mar!W127 -> 0 | X127: =Apr!X127+May!X127+Jun!X127+Jul!X127+Aug!X127+Sep!X127+Oct!X127+Nov!X127+Dec!X127+Jan!X127+Feb!X127+Mar!X127 -> 0 | Y127: =SUM(U127:X127) -> 0 | Z127: =Apr!Z127+May!Z127+Jun!Z127+Jul!Z127+Aug!Z127+Sep!Z127+Oct!Z127+Nov!Z127+Dec!Z127+Jan!Z127+Feb!Z127+Mar!Z127 -> 0 | AA127: =T127+Y127+Z127 -> 0 | AB127: =IF(H127="Exempt",0,ROUND((T127*H127/100)-SUM(U127:W127),2)) -> 0 | AD127: =Apr!AD127+May!AD127+Jun!AD127+Jul!AD127+Aug!AD127+Sep!AD127+Oct!AD127+Nov!AD127+Dec!AD127+Jan!AD127+Feb!AD127+Mar!AD127 -> 0 | AE127: =Apr!AE127+May!AE127+Jun!AE127+Jul!AE127+Aug!AE127+Sep!AE127+Oct!AE127+Nov!AE127+Dec!AE127+Jan!AE127+Feb!AE127+Mar!AE127 -> 0 | AF127: =Apr!AF127+May!AF127+Jun!AF127+Jul!AF127+Aug!AF127+Sep!AF127+Oct!AF127+Nov!AF127+Dec!AF127+Jan!AF127+Feb!AF127+Mar!AF127 -> 0 | AG127: =Apr!AG127+May!AG127+Jun!AG127+Jul!AG127+Aug!AG127+Sep!AG127+Oct!AG127+Nov!AG127+Dec!AG127+Jan!AG127+Feb!AG127+Mar!AG127 -> 0 | AI127: =SUM(AE127:AH127) -> 0 | AJ127: =Apr!AJ127+May!AJ127+Jun!AJ127+Jul!AJ127+Aug!AJ127+Sep!AJ127+Oct!AJ127+Nov!AJ127+Dec!AJ127+Jan!AJ127+Feb!AJ127+Mar!AJ127 -> 0 | AK127: =AD127+AI127+AJ127 -> 0 | AL127: =IF(H127="Exempt",0,ROUND((AD127*H127/100)-SUM(AE127:AG127),2)) -> 0
A128: =+A127+1 -> 113 | B128: Purchases | D128: Materials | E128: Un-registered | H128: 0 | J128: =Apr!J128+May!J128+Jun!J128+Jul!J128+Aug!J128+Sep!J128+Oct!J128+Nov!J128+Dec!J128+Jan!J128+Feb!J128+Mar!J128 -> 0 | K128: =Apr!K128+May!K128+Jun!K128+Jul!K128+Aug!K128+Sep!K128+Oct!K128+Nov!K128+Dec!K128+Jan!K128+Feb!K128+Mar!K128 -> 0 | L128: =Apr!L128+May!L128+Jun!L128+Jul!L128+Aug!L128+Sep!L128+Oct!L128+Nov!L128+Dec!L128+Jan!L128+Feb!L128+Mar!L128 -> 0 | M128: =Apr!M128+May!M128+Jun!M128+Jul!M128+Aug!M128+Sep!M128+Oct!M128+Nov!M128+Dec!M128+Jan!M128+Feb!M128+Mar!M128 -> 0 | N128: =Apr!N128+May!N128+Jun!N128+Jul!N128+Aug!N128+Sep!N128+Oct!N128+Nov!N128+Dec!N128+Jan!N128+Feb!N128+Mar!N128 -> 0 | O128: =SUM(K128:N128) -> 0 | P128: =Apr!P128+May!P128+Jun!P128+Jul!P128+Aug!P128+Sep!P128+Oct!P128+Nov!P128+Dec!P128+Jan!P128+Feb!P128+Mar!P128 -> 0 | Q128: =J128+O128+P128 -> 0 | R128: =IF(H128="Exempt",0,ROUND((J128*H128/100)-SUM(K128:M128),2)) -> 0 | T128: =Apr!T128+May!T128+Jun!T128+Jul!T128+Aug!T128+Sep!T128+Oct!T128+Nov!T128+Dec!T128+Jan!T128+Feb!T128+Mar!T128 -> 0 | U128: =Apr!U128+May!U128+Jun!U128+Jul!U128+Aug!U128+Sep!U128+Oct!U128+Nov!U128+Dec!U128+Jan!U128+Feb!U128+Mar!U128 -> 0 | V128: =Apr!V128+May!V128+Jun!V128+Jul!V128+Aug!V128+Sep!V128+Oct!V128+Nov!V128+Dec!V128+Jan!V128+Feb!V128+Mar!V128 -> 0 | W128: =Apr!W128+May!W128+Jun!W128+Jul!W128+Aug!W128+Sep!W128+Oct!W128+Nov!W128+Dec!W128+Jan!W128+Feb!W128+Mar!W128 -> 0 | X128: =Apr!X128+May!X128+Jun!X128+Jul!X128+Aug!X128+Sep!X128+Oct!X128+Nov!X128+Dec!X128+Jan!X128+Feb!X128+Mar!X128 -> 0 | Y128: =SUM(U128:X128) -> 0 | Z128: =Apr!Z128+May!Z128+Jun!Z128+Jul!Z128+Aug!Z128+Sep!Z128+Oct!Z128+Nov!Z128+Dec!Z128+Jan!Z128+Feb!Z128+Mar!Z128 -> 0 | AA128: =T128+Y128+Z128 -> 0 | AB128: =IF(H128="Exempt",0,ROUND((T128*H128/100)-SUM(U128:W128),2)) -> 0 | AD128: =Apr!AD128+May!AD128+Jun!AD128+Jul!AD128+Aug!AD128+Sep!AD128+Oct!AD128+Nov!AD128+Dec!AD128+Jan!AD128+Feb!AD128+Mar!AD128 -> 0 | AE128: =Apr!AE128+May!AE128+Jun!AE128+Jul!AE128+Aug!AE128+Sep!AE128+Oct!AE128+Nov!AE128+Dec!AE128+Jan!AE128+Feb!AE128+Mar!AE128 -> 0 | AF128: =Apr!AF128+May!AF128+Jun!AF128+Jul!AF128+Aug!AF128+Sep!AF128+Oct!AF128+Nov!AF128+Dec!AF128+Jan!AF128+Feb!AF128+Mar!AF128 -> 0 | AG128: =Apr!AG128+May!AG128+Jun!AG128+Jul!AG128+Aug!AG128+Sep!AG128+Oct!AG128+Nov!AG128+Dec!AG128+Jan!AG128+Feb!AG128+Mar!AG128 -> 0 | AI128: =SUM(AE128:AH128) -> 0 | AJ128: =Apr!AJ128+May!AJ128+Jun!AJ128+Jul!AJ128+Aug!AJ128+Sep!AJ128+Oct!AJ128+Nov!AJ128+Dec!AJ128+Jan!AJ128+Feb!AJ128+Mar!AJ128 -> 0 | AK128: =AD128+AI128+AJ128 -> 0 | AL128: =IF(H128="Exempt",0,ROUND((AD128*H128/100)-SUM(AE128:AG128),2)) -> 0
A129: =+A128+1 -> 114 | B129: Purchases | D129: Materials | E129: Registered | H129: 5 | J129: =Apr!J129+May!J129+Jun!J129+Jul!J129+Aug!J129+Sep!J129+Oct!J129+Nov!J129+Dec!J129+Jan!J129+Feb!J129+Mar!J129 -> 0 | K129: =Apr!K129+May!K129+Jun!K129+Jul!K129+Aug!K129+Sep!K129+Oct!K129+Nov!K129+Dec!K129+Jan!K129+Feb!K129+Mar!K129 -> 0 | L129: =Apr!L129+May!L129+Jun!L129+Jul!L129+Aug!L129+Sep!L129+Oct!L129+Nov!L129+Dec!L129+Jan!L129+Feb!L129+Mar!L129 -> 0 | M129: =Apr!M129+May!M129+Jun!M129+Jul!M129+Aug!M129+Sep!M129+Oct!M129+Nov!M129+Dec!M129+Jan!M129+Feb!M129+Mar!M129 -> 0 | N129: =Apr!N129+May!N129+Jun!N129+Jul!N129+Aug!N129+Sep!N129+Oct!N129+Nov!N129+Dec!N129+Jan!N129+Feb!N129+Mar!N129 -> 0 | O129: =SUM(K129:N129) -> 0 | P129: =Apr!P129+May!P129+Jun!P129+Jul!P129+Aug!P129+Sep!P129+Oct!P129+Nov!P129+Dec!P129+Jan!P129+Feb!P129+Mar!P129 -> 0 | Q129: =J129+O129+P129 -> 0 | R129: =IF(H129="Exempt",0,ROUND((J129*H129/100)-SUM(K129:M129),2)) -> 0 | T129: =Apr!T129+May!T129+Jun!T129+Jul!T129+Aug!T129+Sep!T129+Oct!T129+Nov!T129+Dec!T129+Jan!T129+Feb!T129+Mar!T129 -> 0 | U129: =Apr!U129+May!U129+Jun!U129+Jul!U129+Aug!U129+Sep!U129+Oct!U129+Nov!U129+Dec!U129+Jan!U129+Feb!U129+Mar!U129 -> 0 | V129: =Apr!V129+May!V129+Jun!V129+Jul!V129+Aug!V129+Sep!V129+Oct!V129+Nov!V129+Dec!V129+Jan!V129+Feb!V129+Mar!V129 -> 0 | W129: =Apr!W129+May!W129+Jun!W129+Jul!W129+Aug!W129+Sep!W129+Oct!W129+Nov!W129+Dec!W129+Jan!W129+Feb!W129+Mar!W129 -> 0 | X129: =Apr!X129+May!X129+Jun!X129+Jul!X129+Aug!X129+Sep!X129+Oct!X129+Nov!X129+Dec!X129+Jan!X129+Feb!X129+Mar!X129 -> 0 | Y129: =SUM(U129:X129) -> 0 | Z129: =Apr!Z129+May!Z129+Jun!Z129+Jul!Z129+Aug!Z129+Sep!Z129+Oct!Z129+Nov!Z129+Dec!Z129+Jan!Z129+Feb!Z129+Mar!Z129 -> 0 | AA129: =T129+Y129+Z129 -> 0 | AB129: =IF(H129="Exempt",0,ROUND((T129*H129/100)-SUM(U129:W129),2)) -> 0 | AD129: =Apr!AD129+May!AD129+Jun!AD129+Jul!AD129+Aug!AD129+Sep!AD129+Oct!AD129+Nov!AD129+Dec!AD129+Jan!AD129+Feb!AD129+Mar!AD129 -> 0 | AE129: =Apr!AE129+May!AE129+Jun!AE129+Jul!AE129+Aug!AE129+Sep!AE129+Oct!AE129+Nov!AE129+Dec!AE129+Jan!AE129+Feb!AE129+Mar!AE129 -> 0 | AF129: =Apr!AF129+May!AF129+Jun!AF129+Jul!AF129+Aug!AF129+Sep!AF129+Oct!AF129+Nov!AF129+Dec!AF129+Jan!AF129+Feb!AF129+Mar!AF129 -> 0 | AG129: =Apr!AG129+May!AG129+Jun!AG129+Jul!AG129+Aug!AG129+Sep!AG129+Oct!AG129+Nov!AG129+Dec!AG129+Jan!AG129+Feb!AG129+Mar!AG129 -> 0 | AI129: =SUM(AE129:AH129) -> 0 | AJ129: =Apr!AJ129+May!AJ129+Jun!AJ129+Jul!AJ129+Aug!AJ129+Sep!AJ129+Oct!AJ129+Nov!AJ129+Dec!AJ129+Jan!AJ129+Feb!AJ129+Mar!AJ129 -> 0 | AK129: =AD129+AI129+AJ129 -> 0 | AL129: =IF(H129="Exempt",0,ROUND((AD129*H129/100)-SUM(AE129:AG129),2)) -> 0
